Workbook
Name Add_SALT: 'Sch. A'!$AI$37
Name Additional_Income: 'Sch. 1'!$AC$56
Name AdditionalCTC: '8812'!$AL$85
Name Address: '1040'!$B$13
Name Adj_Gross_Inc: '1040'!$AL$79
Name Adj_Gross_Inc_Pg2: '1040'!$AL$82
Name AdjustToIncome: 'Sch. 1'!$AC$100
Name AdoptCredit: 'Sch. 3'!$W$20
Name AgPMT_Disaster: '1099-G'!$J$31
Name AgPMT_Other: '1099-G'!$J$32
Name Alaska: '1040'!$BN$10
Name Alien_Spouse: '1040'!$F$27
Name AlienSpouseName: '1040'!$AA$28
Name AlimonyPaid: 'Sch. 1'!$AJ$70
Name AlimonyRcvd: 'Sch. 1'!$AC$16
Name AltMinTaxInc: '6251'!$M$39
Name AMT: '6251'!$R$64
Name AMTExemption: '6251'!$AC$172
Name AMTExemptionFlag: '6251'!$AH$80
Name AO_Credit: '8863'!$AE$33
Name AOC_1: '8863'!$AE$110
Name AOC_2: '8863'!$AE$168
Name AOC_3: '8863'!$AE$226
Name AOC_4: '8863'!$AE$284
Name Apt_No.: '1040'!$AD$13
Name ArcherMSADeduct: 'Sch. 1'!$AC$77
Name BadBirthdate_Spouse: '1040'!$BK$144
Name BadBirthdate_Yours: '1040'!$BK$123
Name BadDeathDate: '1040'!$BR$144
Name BASE_A1: 'Tax Table'!$U$7
Name BASE_A2: 'Tax Table'!$U$8
Name BASE_A3: 'Tax Table'!$U$9
Name BASE_A4: 'Tax Table'!$U$10
Name BASE_A5: 'Tax Table'!$U$11
Name BASE_A6: 'Tax Table'!$U$12
Name BASE_A7: 'Tax Table'!$U$13
Name BASE_B1: 'Tax Table'!$U$17
Name BASE_B2: 'Tax Table'!$U$18
Name BASE_B3: 'Tax Table'!$U$19
Name BASE_B4: 'Tax Table'!$U$20
Name BASE_B5: 'Tax Table'!$U$21
Name BASE_B6: 'Tax Table'!$U$22
Name BASE_B7: 'Tax Table'!$U$23
Name BASE_C1: 'Tax Table'!$U$27
Name BASE_C2: 'Tax Table'!$U$28
Name BASE_C3: 'Tax Table'!$U$29
Name BASE_C4: 'Tax Table'!$U$30
Name BASE_C5: 'Tax Table'!$U$31
Name BASE_C6: 'Tax Table'!$U$32
Name BASE_C7: 'Tax Table'!$U$33
Name BASE_D1: 'Tax Table'!$U$38
Name BASE_D2: 'Tax Table'!$U$39
Name BASE_D3: 'Tax Table'!$U$40
Name BASE_D4: 'Tax Table'!$U$41
Name BASE_D5: 'Tax Table'!$U$42
Name BASE_D6: 'Tax Table'!$U$43
Name BASE_D7: 'Tax Table'!$U$44
Name BeginningOfTaxYear: '1040'!$BI$2
Name Birthday_Needed: '1040'!$BI$136
Name BOTT_A1: 'Tax Table'!$T$7

Sheet 1040
C1: =RevDateTime | H1: NOTE: Check every calculation carefully!!! | AH1: =IF('Table of Contents'!A19="D","DRAFT FORM","") | AU1: =IF(File_Single<>"",1,0) | BT1: Notes
C2: =RevDateTime | H2: www.excel1040.com | AH2: ="© Glenn Reeves, "&TaxYear+1 | AU2: =IF(File_Marr_Joint<>"",1,0) | AW2: Check here to remove blue & green colors from all sheets. | BA2: =(AV2<>"") | BI2: =DATEVALUE("1-JAN-"&TaxYear) | BJ2: =IF(BL2>365,TRUE,FALSE) | BK2: =DATEVALUE("1-JAN-"&TaxYear+1)-1 | BL2: =EndOfTaxYear+1-BeginningOfTaxYear | BN2: Alaska | BO2: Hawaii | BP2: Maine | BQ2: Mass. | BR2: D.C. | BT2: Date
B3: Form | C3: 1040 | G3: =IF(FilingStatusError,"Please check only ONE filing status box.","Department of the Treasury––Internal Revenue Service") | X3: 2025 | AH3: =IF(AND(AT3="",'Table of Contents'!A19="D"),"DRAFT FORM","") | AU3: =IF(File_Marr_Sep<>"",1,0) | AW3: Check here to hide Social Security numbers on forms. | BA3: =(AV3<>"") | BF3: =TaxYear-1 | BN3: =IF(ISERROR(FIND("ALASKA",State)),FALSE,TRUE) | BO3: =IF(ISERROR(FIND("HAWAII",State)),FALSE,TRUE) | BP3: =IF(ISERROR(FIND("MAINE",State)),FALSE,TRUE) | BQ3: =IF(ISERROR(FIND("MASSACHUSETTS",State)),FALSE,TRUE) | BR3: =IF(ISERROR(FIND("DISTRICT",State)),FALSE,TRUE)
F4: =IF(NumFileStatusBoxes=0,"Check one FILING STATUS box.","U.S. Individual Income Tax Return") | AC4: OMB No. 1545-0074 | AH4: =IF(FilingStatusError,"Check only ONE filing status block","IRS Use Only—Do not write or staple in this space.") | AU4: =IF(File_Head<>"",1,0) | AV4: Filing Status: | AX4: =IF(NumFileStatusBoxes=0,"Filing status not indicated.",IF(FilingStatusError,"Check only ONE filing status box.",IF(File_Single<>"","Single",IF(File_Marr_Joint<>"","Married - Filing Jointly",IF(File_Marr_Sep<>"","Married - Filing Separately",IF(File_Head<>"","Head of Household",IF(File_Qual_Widow<>"","Qualifying Widow(er)",""))))))) | BF4: =TaxYear+1 | BN4: =IF(ISERROR(FIND("AK",State)),FALSE,TRUE) | BO4: =IF(ISERROR(FIND("HI",State)),FALSE,TRUE) | BP4: =IF(ISERROR(FIND("ME",State)),FALSE,TRUE) | BQ4: =IF(ISERROR(FIND("MA",State)),FALSE,TRUE) | BR4: =IF(ISERROR(FIND("DC",State)),FALSE,TRUE)
B5: ="For the year Jan. 1–Dec. 31, "&TaxYear&", or other tax year beginning" | Y5: ending | AH5: See separate instructions.
C6: Filed pursuant to section 301.9100-2 | N6: Combat zone | AC6: Deceased | AK6: Spouse
C7: Other | AW7: =IF(File_Marr_Sep<>""," Yes.","") | AX7: =IF(File_Marr_Sep<>"","Did you live apart from your spouse for all of "&TEXT(TaxYear,"0")&"?","") | BB7: =AND(File_Marr_Sep<>"",OR(AV7<>"",AV8<>""))
C8: Your first name and middle initial | R8: =IF(AND(File_Marr_Sep<>"",OR(NOT(LivedApartAnswered),N25="")),"Please answer questions at right regarding your spouse."," Last name") | AH8: Your social security number | AW8: =IF(OR(AND(AV7<>"",AV8<>""),AND(File_Marr_Sep<>"",AV7="",AV8=""))," No.",IF(File_Marr_Sep<>""," No.","")) | AX8: =IF(OR(AND(AV7<>"",AV8<>""),AND(File_Marr_Sep<>"",AV7="",AV8="")),"Please check ONE box.","") | BB8: =AND(File_Marr_Sep<>"",AV7<>"")
AH9: 1010001 | AU9: =IF(File_Qual_Widow<>"",1,0) | AW9: =IF(File_Marr_Sep<>"","Check here if your spouse had no income and is NOT filing a tax return.","") | BN9: =IF(ISERROR(FIND("Alaska",State)),FALSE,TRUE) | BO9: =IF(ISERROR(FIND("Hawaii",State)),FALSE,TRUE) | BP9: =IF(ISERROR(FIND("Maine",State)),FALSE,TRUE) | BQ9: =IF(ISERROR(FIND("Massachusetts",State)),FALSE,TRUE) | BR9: =IF(ISERROR(FIND("D.C.",State)),FALSE,TRUE)
C10: If joint return, spouse's first name and middle initial | R10: Last name | AH10: =IF(AND(File_Marr_Sep<>"",SS_Spouse=""),"Enter spouse's Soc. Sec. number","Spouse's social security number") | AU10: =SUM(AU1:AU9) | BC10: =AND(DependentYOU="",OR(File_Single<>"",File_Marr_Joint<>"",File_Marr_Sep<>"",File_Head<>"",File_Qual_Widow<>"")) | BN10: =OR(BN3,BN4,BN9) | BO10: =OR(BO3,BO4,BO9) | BP10: =OR(BP3,BP4,BP9) | BQ10: =OR(BQ3,BQ4,BQ9) | BR10: =OR(BR3,BR4,BR9)
AH11: =IF(NumFileStatusBoxes=0,"Filing status?",1010002) | AU11: =NumFileStatusBoxes>1 | BG11: =IF(AND(Name_1st_Yours<>"",Name_1st_Sp<>""),Name_1st_Yours&" "&Name_Last_Yours&" & "&Name_1st_Sp&" "&Name_Last_Sp,IF(Name_Last_Yours<>"",Name_1st_Yours&" "&Name_Last_Yours,"")) | BQ11: =OR(BP10,BQ10,BR10)
C12: Home address (number and street). If you have a P.O. box, see instructions. | AD12: Apt. no. | AH12: Check here if your main home, and your spouse's, | AU12: =(NumFileStatusBoxes>1) | BF12: =AND(OR(File_Single<>"",File_Head<>""),OR(sp_over_64<>"",sp_blind<>"",DependentSPOUSE<>"",Dual_Status_Alien<>"")) | BQ12: For 'Patriots' Day or
AH13: ="if filing a joint return, was in the U.S. for more than half of "&TaxYear&"." | AS13: X | AU13: =IF(AND(OR(File_Single<>"",File_Head<>""),OR(sp_over_64<>"",sp_blind<>"")),TRUE,FALSE) | AW13: =IF(AND($BF$13,BI15,BI17),"Birthdates",IF($BF$13,"Enter your birthdate and your spouse's birthdate.",IF(BI15,"Birthdate","Enter your birthdate."))) | BF13: =OR(File_Marr_Joint<>"",File_Marr_Sep<>"",File_Qual_Widow<>"") | BG13: =Name_1st_Yours&" "&Name_Last_Yours | BI13: =Name_1st_Sp&" "&Name_Last_Sp | BQ13: Emancipation Day (D.C.)
C14: City, town, or post office. If you have a foreign address, also complete spaces below. | X14: State | AC14: ZIP Code | AH14: Presidential Election Campaign | AX14: Month (e.g. '11') | AY14: Day (e.g. '9') | AZ14: Year (e.g. '1997') | BF14: =IF(you_over_64<>"",1,0) | BG14: You > 64
AH15: Check here if you, or your spouse if filing jointly, want $3 to go to this fund. Checking a box below will not change your tax or refund. | AW15: You | BF15: =IF(you_blind<>"",1,0) | BG15: You blind | BI15: =AND(YourBirthMonth<>"",YourBirthDay<>"",YourBirthYear<>"") | BJ15: =IF(OR(YourBirthMonth="",YourBirthDay="",YourBirthYear=""),"Enter your birthdate",IF(BL123,"Your birthdate appears to be in error.",IF(BI16,"For IRS purposes, you were "&YourAge&" years old on December 31, "&TaxYear&".","You were "&YourAge&" years old on December 31, "&TaxYear&".")))
C16: Foreign country name | S16: Foreign province/state/county | AC16: Foreign postal code | AX16: =BJ15 | BF16: =IF(AND(OR(File_Marr_Joint<>"",SpouseSep_NoIncome),sp_over_64<>""),1,0) | BG16: Spouse > 64 | BI16: =AND(YourBirthMonth=1,YourBirthDay=1)
AK17: You | AO17: Spouse | AW17: =IF($BF$13,"Spouse ","") | BF17: =IF(AND(OR(File_Marr_Joint<>"",SpouseSep_NoIncome),sp_blind<>""),1,0) | BG17: Spouse blind | BI17: =AND(OR(File_Marr_Sep<>"",File_Marr_Joint<>""),SpouseBirthMonth<>"",SpouseBirthDay<>"",SpouseBirthYear<>"") | BJ17: =IF(AND(File_Marr_Sep="",File_Marr_Joint=""),"",IF(AND(OR(File_Marr_Sep<>"",File_Marr_Joint<>""),OR(SpouseBirthMonth="",SpouseBirthDay="",SpouseBirthYear="")),"Enter spouse's birthdate.",IF(BL144,"Spouse's birthdate appears to be in error.",IF(BI22,"For IRS purposes, you were "&SpouseAge&" years old on December 31, "&TaxYear&".","Your spouse was "&SpouseAge&" years old on December 31, "&TaxYear&"."))))
AV18: =IF(File_Marr_Joint<>"","Check "&CHAR(10)&"if deceased","") | AX18: =BJ17
B20: Filing Status | G20: Single | AC20: Head of Household (HOH) | BF20: =IF(OR(AND(OR(File_Single<>"",File_Head<>""),OR(sp_over_64<>"",sp_blind<>"")),NumFileStatusBoxes=0),0,SUM(BF14:BF17)) | BG20: Total | BI20: =AND(File_Marr_Sep<>"",MFS_Spouse_NotFiling<>"",DependentSPOUSE="")
B22: Check only one box | G22: Married filing jointly (even if only one had income) | AC22: Qualifying Surviving Spouse (QSS) | AW22: =IF(AW24,"Date of death ","") | BI22: =AND(SpouseBirthMonth=1,SpouseBirthDay=1)
AB23: If you checked the HOH or QSS box, enter the child’s name if the qualifying person is a child but not your dependent: | AX23: =IF(AND(SpouseDeceased<>"",OR(SpouseDeathMonth="",SpouseDeathDay="",SpouseDeathYear="")),"Enter date of spouse's death.",IF(AW25,"Spouse must have lived during "&TaxYear&" tax year.",IF(BadDeathDate,"The date of death appears to be in error.","")))
G24: Married filing separately (MFS) Enter spouse's SSN above | AW24: =AND($AV$17<>"",$BF$13) | BI24: =AND($AW$24,SpouseAge>65) | BJ24: Deceased spouse was >65 years old.
G25: and full name here: | AW25: =AND(SpouseDeceased<>"",SpouseDeathYear<>"",SpouseDeathYear<>TaxYear) | BI25: =AND($AW$24,SpouseAge=65) | BJ25: Deceased turned 65 years old during tax year.
G27: If treating a nonresident alien or dual-status alien spouse as a U.S. resident for the entire tax year, check the box and enter their | BI27: =AND($AW$24,OR(SpouseDeathMonth<SpouseBirthMonth,AND(SpouseDeathMonth=SpouseBirthMonth,SpouseDeathDay<SpouseBirthDay))) | BJ27: Spouse passed way before birthday
G28: name (see instructions and attach statement if required): | BI28: =OR(BI24,AND(BI25,NOT(BI27))) | BJ28: Deceased spouse std. deduct. Credit for >64
B30: Digital Assets | F30: ="At any time during "&TaxYear&", did you (a) receive (as a reward, award, or payment for property or service); or (b) sell, "&CHAR(10)&"exchange, gift, or otherwise dispose of a digital asset (or a financial interest in a digital asset)? (See instructions.)"
AN31: Yes | AR31: No | AU31: =IF(AND(DigitalAsset_Yes="",DigitalAsset_No=""),"<< Check one.","")
B33: Dependents | L33: Dependent 1 | U33: Dependent 2 | AD33: Dependent 3 | AL33: Dependent 4 | AU33: Enter information for dependents on the 'Dependents' sheet.
B34: (see instructions) | F34: (1) First name | L34: =IF(Dependents!E7="","",Dependents!E7) | U34: =IF(Dependents!E8="","",Dependents!E8) | AD34: =IF(Dependents!E9="","",Dependents!E9) | AL34: =IF(Dependents!E10="","",Dependents!E10) | BB34: =IF(M47<>"",1,0) | BC34: =(AND(L34<>"",L35<>"",M47="",Q47="")) | BE34: =IF(M47<>"",1,0)
F35: (2) Last name | L35: =IF(Dependents!I7="","",Dependents!I7) | U35: =IF(Dependents!I8="","",Dependents!I8) | AD35: =IF(Dependents!I9="","",Dependents!I9) | AL35: =IF(Dependents!I10="","",Dependents!I10) | BB35: =IF(V47<>"",1,0) | BC35: =(AND(U34<>"",U35<>"",V47="",Z47="")) | BD35: =OR(BC34,BC35,BC36,BC37) | BE35: =IF(V47<>"",1,0)
B36: If more than four dependents, see instructions and check here . . . . | F36: (3) SSN | L36: =IF(Dependents!M7="","",Dependents!M7) | U36: =IF(Dependents!M8="","",Dependents!M8) | AD36: =IF(Dependents!M9="","",Dependents!M9) | AL36: =IF(Dependents!M10="","",Dependents!M10) | BB36: =IF(AE47<>"",1,0) | BC36: =(AND(AD34<>"",AD35<>"",AE47="",AI47="")) | BD36: =IF(DependentYOU="",1,0) | BE36: =IF(AE47<>"",1,0)
F37: (4) Relationship | L37: =IF(Dependents!S7="","",Dependents!S7) | U37: =IF(Dependents!S8="","",Dependents!S8) | AD37: =IF(Dependents!S9="","",Dependents!S9) | AL37: =IF(Dependents!S10="","",Dependents!S10) | BB37: =IF(AM47<>"",1,0) | BC37: =(AND(AL34<>"",AL35<>"",AM47="",AQ47="")) | BD37: =IF(AND(File_Marr_Joint<>"",DependentSPOUSE=""),1,0) | BE37: =IF(AM47<>"",1,0)
F38: (5) Check if lived with you more than
N39: (a) | O39: =IF(Dependents!Z7="","","X") | P39: Yes | W39: (a) | X39: =IF(Dependents!Z8="","","X") | Y39: Yes | AE39: (a) | AF39: =IF(Dependents!Z9="","","X") | AG39: Yes | AM39: (a) | AN39: =IF(Dependents!Z10="","","X") | AO39: Yes
D41: =IF(DependentsGT4,"X","") | F41: ="than half of "&TaxYear | N41: (b) | O41: =IF(Dependents!AC7="","","X") | P41: And in the U.S. | W41: (b) | X41: =IF(Dependents!AC8="","","X") | Y41: And in the U.S. | AE41: (b) | AF41: =IF(Dependents!AC9="","","X") | AG41: And in the U.S. | AM41: (b) | AN41: =IF(Dependents!AC10="","","X") | AO41: And in the U.S. | AZ41: =IF(OR(NumFileStatusBoxes=0,NumFileStatusBoxes>1),0,SUM(BD36,BD37,AW47,AW48)) | BA41: Tax Family Size (for Form 8962, Premium Tax Credit)
AZ42: Determine the number of individuals in your tax family using your tax return. Your tax family generally includes you, your spouse if you are filing a joint return, and your dependents. If you checked the “Someone can claim you as a dependent” box, or if you’re filing jointly and you checked the “Someone can claim your spouse as a dependent” box on your tax return, you or your spouse are not included in the tax family size calculation for purposes of Form 8962, Premium Tax Credit, line 1.
F43: (6) Check if | AN43: Full-time student
M44: =IF(Dependents!AF7="","","X") | N44: Full-time student | Q44: =IF(Dependents!AI7="","","X") | R44: Permanently and totally disabled | V44: =IF(Dependents!AF8="","","X") | W44: Full-time student | Z44: =IF(Dependents!AI8="","","X") | AA44: Permanently and totally disabled | AE44: =IF(Dependents!AF9="","","X") | AF44: Full-time student | AI44: =IF(Dependents!AI9="","","X") | AJ44: Permanently and totally disabled | AM44: =IF(Dependents!AF10="","","X") | AQ44: =IF(Dependents!AI10="","","X") | AR44: Permanently and totally disabled
F46: (7) Credits | AN46: Child tax credit
M47: =IF(Dependents!BB7="","","X") | N47: Child tax credit | Q47: =IF(Dependents!BK7="","","X") | R47: Credit for other dependents | V47: =IF(Dependents!BB8="","","X") | W47: Child tax credit | Z47: =IF(Dependents!BK8="","","X") | AA47: Credit for other dependents | AE47: =IF(Dependents!BB9="","","X") | AF47: Child tax credit | AI47: =IF(Dependents!BK9="","","X") | AJ47: Credit for other dependents | AM47: =IF(Dependents!BB10="","","X") | AQ47: =IF(Dependents!BK10="","","X") | AR47: Credit for other dependents | AW47: =Qual_Child_Count | AX47: Number of qualifying children.
AW48: =DependentCount | AX48: Number of other dependents.
G49: ="Check if your filing status is MFS or HOH and you lived apart from your spouse for the last 6 months of "&TaxYear&", or you are legally"&CHAR(10)&"separated according to your state law under a written separation agreement or a decree of separate maintenance and you did not"&CHAR(10)&"live in the same household as your spouse at the end of "&TaxYear&"."
AX50: Manual Override
B51: Income | F51: 1 | G51: a | H51: Total amount from Form(s) W-2, box 1 (see instructions) | AJ51: . . . . . . . . . . . . . . . . . | AK51: 1a | AL51: =IF(AX51<>"",ROUND(AX51,0),W2_Wages) | AV51: 4a | AW51: =AND(CONV2ROTH=0,ROUND(IRA_Gross,0)=IRA_Taxable) | AY51: =OR(AX51<>"",AX61<>"",AY61<>"",AX62<>"",AY62<>"",AX65<>"",AY65<>"",AX68<>"",AY68<>"",AX71<>"",AY71<>"")
G52: b | H52: Household employee wages not reported on Form(s) W-2 | AJ52: . . . . . . . . . . . . . . . . | AK52: 1b
B53: Attach Form(s) W-2 here. Also attach Forms W-2G and 1099-R if tax was withheld. | G53: c | H53: Tip income not reported on line 1a (see instructions) | AJ53: . . . . . . . . . . . . . . . . . . | AK53: 1c
G54: d | H54: Medicaid waiver payments not reported on Form(s) W-2 (see instructions) | AJ54: . . . . . . . . . . | AK54: 1d
G55: e | H55: Taxable dependent care benefits from Form 2441, line 26 | AJ55: . . . . . . . . . . . . . . . . | AK55: 1e | AL55: =IF(AX55<>"",ROUND(AX55,0),Dependent_Care)
G56: f | H56: Employer provided adoption benefits from Form 8839, line 29 | AJ56: . . . . . . . . . . . . . . . | AK56: 1f
G57: g | H57: Wages from Form 8919, line 6 | AJ57: . . . . . . . . . . . . . . . . . . . . . . . . . | AK57: 1g | AL57: =IF(AX57<>"",ROUND(AX57,0),IF(F8919_Line6_Both=0,"",F8919_Line6_Both)) | AU57: =IF(AL57="",0,AL57)
B58: If you did not get a Form W-2, see instructions. | G58: h | H58: Other earned income (see instructions) | AJ58: . . . . . . . . . . . . . . . . . . . . . . | AK58: 1h
G59: i | H59: Nontaxable combat pay election (see instructions) | AD59: . . . . . . . . . | AF59: 1i | AG59: =IF(AX59<>"",ROUND(AX59,0),'W-2s'!D93) | AU59: Source: Form W-2, line 12 'Q'
G60: z | H60: Add lines 1a through 1h | AJ60: . . . . . . . . . . . . . . . . . . . . . . . . . | AK60: 1z | AL60: =IF(AX60<>"",ROUND(AX60,0),SUM(AL51, ROUND(AL52,0),ROUND(AL53,0),ROUND(AL54,0),AL55,ROUND(AL56,0),AU57,ROUND(AL58,0))) | AW60: =IRA_Gross=IRA_Taxable | AY60: Manual Override
B61: Attach Sch. B if required. | F61: 2 | G61: a | H61: Tax-exempt interest | P61: . . . . | Q61: =F61&"a" | S61: =IF(AX61<>"",ROUND(AX61,0),SUM(TaxExemptInterest,Exempt_Interest_DIV)) | Z61: b | AA61: Taxable interest | AJ61: . . . . . . . | AK61: =F61&"b" | AL61: =IF(AY61<>"",ROUND(AY61,0),Interest_Inc) | AV61: 5a | AW61: =ROUND(PA_Gross,0)=PA_Taxable
F62: 3 | G62: a | H62: Qualified dividends | P62: . . . . | Q62: =F62&"a" | S62: =IF(AX62<>"",ROUND(AX62,0),ROUND(QualDiv_1099DIV,0)) | Z62: b | AA62: Ordinary dividends | AJ62: . . . . . . . | AK62: =F62&"b" | AL62: =IF(AY62<>"",ROUND(AY62,0),Dividend_Inc) | AW62: =AU64<>"" | BI62: Standard versus Itemized Deduction
G64: c | H64: Check if your child's dividends are included in | U64: 1 | W64: Line 3a | AA64: 2 | AC64: Line 3b | AU64: =IF(OrdinaryDividends<Qualified_Dividends,"Error: Qualified dividends "&CHAR(10)&"(line 3a)"&CHAR(10)&"must be included in"&CHAR(10)&"ordinary dividends "&CHAR(10)&"(line 3b).",IF(AND(OrdinaryDividends<>0,Qualified_Dividends<>"",OrdinaryDividends<>Qualified_Dividends),"Caution: Be sure to include all of line 3a, Qualified Dividends, in line 3b, Ordinary Dividend, amount.",IF(AND(IRA_Taxable<>0,AW60,PA_Taxable<>0,AW61),"Linse 4a and 5a are blank"&CHAR(10)&"per IRS instructions.",IF(AND(IRA_Taxable<>0,AW60),"Line 4a is blank per"&CHAR(10)&"IRS instructions.",IF(AND(PA_Taxable<>0,AW61),"Line 5a is blank per"&CHAR(10)&"IRS instructions.",IF(AY51,"Use Sheets W-2, "&CHAR(10)&"1099-INT, 1099-DIV, 1099-R, and "&CHAR(10)&"SSA-1099 for accurate results.",""))))))
F65: =F62+1 | G65: a | H65: IRA distributions | P65: . . . . | Q65: =F65&"a" | S65: =IF(AX65<>"",ROUND(AX65,0),IF(AW60,"",SUM(ROUND(IRA_Gross,0),ROUND(CONV2ROTH,0)))) | Z65: b | AA65: Taxable amount | AJ65: . . . . . . . | AK65: =F65&"b" | AL65: =IF(AY65<>"",ROUND(AY65,0),ROUND(SUM(IRA_Taxable_1099R,IRAContrib_Taxable1,IRAContrib_Taxable2,IRAConvert_Taxable1,IRAConvert_Taxable2,RothIRADist_Taxable1,RothIRADist_Taxable2),0)) | BI65: =IF(File_Single<>"",SD_Adj_Single,IF(OR(File_Marr_Joint<>"",File_Qual_Widow<>""),SD_Adj_MFJW,IF(File_Marr_Sep<>"",SD_Adj_MFS,IF(File_Head<>"",SD_Adj_HOH,0)))) | BJ65: =SchA_Filed | BK65: =NOT(ItemizedDeduct)
G67: c | H67: Check if (see instructions) | U67: 1 | W67: Rollover | AA67: 2 | AC67: QCD | AE67: 3 | BI67: Standard | BJ67: Itemized
F68: 5 | G68: a | H68: Pensions and annuities | P68: . . | Q68: 5a | S68: =IF(AX68<>"",ROUND(AX68,0),IF(AW61,"",ROUND(PA_Gross,0))) | Z68: b | AA68: Taxable amount | AJ68: . . . . . . . | AK68: =F68&"b" | AL68: =IF(AY68<>"",ROUND(AY68,0),ROUND(PA_Taxable_1099R,0))
G70: c | H70: Check if (see instructions) | U70: 1 | W70: Rollover | AA70: 2 | AC70: PSO | AE70: 3 | BI70: =IF(OR(Dual_Status_Alien<>"",ISERROR(Over_65_or_Blind)),0, IF('Line 12e (SD Depnts)'!L4,Std_Ded_Wrks_For_Dep, IF(Over_65_or_Blind>0,BI65,BI73))) | BJ70: =Tot_Item_Deduct
F71: 6 | G71: a | H71: Social security benefits | P71: . . | Q71: =F71&"a" | S71: =IF(AX71<>"",ROUND(AX71,0),ROUND('Line 6ab (SS Bene)'!I13,0)) | Z71: b | AA71: Taxable amount | AJ71: . . . . . . . . | AK71: =F71&"b" | AL71: =IF(AY71<>"",ROUND(AY71,0),IF(ISERROR(ROUND(Tax_SS_Benefits,0)),"See 'Line 6ab' sheet.",ROUND(Tax_SS_Benefits,0)))
G72: c | H72: If you elect to use the lump-sum election method, check here (see instructions) | AH72: . . . . . | AJ72: .
G73: d | H73: If you are married filing separately and lived apart from your spouse the entire year (see inst.), check here | AI73: =IF(AND(SocSecBenefits<>"",SocSecBenefits>0,LivedApart),"X","") | AJ73: . | BI73: =IF(File_Single<>"",SD_Single,IF(OR(File_Marr_Joint<>"",File_Qual_Widow<>""),SD_MFJW,IF(File_Head<>"",SD_Head,IF(File_Marr_Sep<>"",SD_Single,0))))
F74: 7 | G74: a | H74: Capital gain or (loss). Attach Schedule D if required | AH74: . . . . . . . . . | AJ74: . | AK74: 7a | AL74: =IF(AX74<>"",ROUND(AX74,0),IF(SchD_NotReqd,'1099-DIV'!H95,IF('Sch. D'!A59,'Sch. D'!O57,IF('Sch. D'!A63,0,'Sch. D'!W84)))) | BI74: NQDL
G75: b | H75: Check if: | L75: Schedule D not required | T75: Includes child’s capital gain or (loss) | AY75: =$K$75<>"" | BI75: =IF(AND(StdDeduct,NQDisasterLoss<>"",NQDisasterLoss>0),SUM(Standard,NQDisasterLoss),Standard)
F76: =F74+1 | H76: Other income from Schedule 1, line 10 | AJ76: . . . . . . . . . . . . . . . . . . . . . . . | AK76: 8 | AL76: =IF(AX76<>"",ROUND(AX76,0),Additional_Income)
F77: 9 | H77: Add lines 1z, 2b, 3b, 4b, 5b, 6b, 7a, and 8. This is your total income | AJ77: . . . . . . . . . . . . | AK77: 9 | AL77: =IF(AX77<>"",ROUND(AX77,0),SUM(AL60,TaxableInterest,OrdinaryDividends,IRA_Taxable,PA_Taxable,SocSecBenefits_Taxable,CapitalGains,AL76))
F78: 10 | H78: Adjustments to income from Schedule 1, line 26 | AJ78: . . . . . . . . . . . . . . . . . . . . | AK78: 10 | AL78: =IF(AX78<>"",ROUND(AX78,0),SUM(AdjustToIncome)) | BI78: =IF(File_Single<>"",SD_Adj_Single,IF(OR(File_Marr_Joint<>"",File_Qual_Widow<>""),SD_Adj_MFJW,IF(File_Marr_Sep<>"",SD_Adj_MFS,IF(File_Head<>"",SD_Adj_HOH,0))))
F79: 11 | G79: a | H79: Subtract line 10 from line 9. This is your adjusted gross income | AJ79: . . . . . . . . . . . . . | AK79: 11a | AL79: =IF(AX79<>"",ROUND(AX79,0),SUM(Total_Income,-AL78)) | BH79: SD_Adj_Single | BI79: =SD_Adj_Single
B80: For Disclosure, Privacy Act, and Paperwork Reduction Act Notice, see separate instructions. | AG80: Cat. No. 11320B | AP80: Form 1040 | AS80: ="("&TaxYear&")" | BH80: SD_Adj_MFJW | BI80: =SD_Adj_MFJW
B81: ="Form 1040 ("&TaxYear&")" | AP81: =IF(AND(Birthday_Needed,BF13,OR(BI122,BI143)),"Enter your birthdate and your spouse's birthdates above.",IF(AND(Birthday_Needed,BI122),"Enter your birthdate above.","")) | AS81: Page 2 | BH81: SD_Adj_MFS | BI81: =SD_Adj_MFS
B82: Tax and Credits | F82: 11 | G82: b | H82: Amount from line 11a (adjusted gross income) | AJ82: . . . . . . . . . . . . . . | AK82: 11b | AL82: =Adj_Gross_Inc | AZ82: =IF(AND(DependentSPOUSE="",MFS_Spouse_NotFiling<>""),BH94&BH95,"") | BH82: SD_Adj_HOH | BI82: =SD_Adj_HOH
F84: 12 | G84: a | H84: Someone can claim: | P84: You as a dependent | Z84: Your spouse as a dependent | AU84: =AND(DependentSPOUSE="",File_Marr_Joint<>"")
B86: Standard deduction for --- | G86: b | I86: Spouse itemizes on a separate return | W86: c | Z86: You were a dual-status alien
G88: d | H88: You: | K88: =IF(BadBirthdate_Yours,"",IF(YourBirthDate<$BJ$133,"X","")) | L88: =IF(AND(Name_1st_Yours<>"",NOT($BI$15))," Enter your birthdate in box at right."," Were born before January 2, "&TaxYear-64) | AB88: Are blind
B89: • | C89: Single or Married filing separately,
H90: Spouse: | K90: =IF(OR(File_Single<>"",File_Head<>"",AND(File_Marr_Sep<>"",MFS_Spouse_NotFiling=""),BadBirthdate_Spouse,AND(SpouseDeceased<>"",BadDeathDate)),"",IF(AND(SpouseDeceased<>"",BI28),"X",IF(AND(SpouseDeceased="",SpouseBirthDate<$BJ$133),"X",""))) | L90: =IF(AND(Name_1st_Yours<>"",NOT($BI$15))," Enter your birthdate in box at right."," Were born before January 2, "&TaxYear-64) | AB90: Is blind | BA90: 2000 | BB90: 1600 | BC90: 1600 | BD90: 2000
G91: e | H91: Standard deduction or itemized deductions (from Schedule A) | AJ91: . . . . . . . . . . . . . . . | AK91: 12e | AL91: =IF(AX91<>"",ROUND(AX91,0),IF(OR(AND(Total_Income=0,Adj_Gross_Inc=0),NumFileStatusBoxes=0,NumFileStatusBoxes>1,Birthday_Needed,$BF$12),0, IF(AND(NQDisasterLoss>0,StdDeduct),SD_AND_NQDL,IF(ItemizedDeduct,Tot_Item_Deduct,Standard )))) | AU91: =IF(AX78<>"","Manual Override",IF(FilingStatusError,"Filing status error.",IF(Birthday_Needed,"Birthdate(s) needed.",IF($BF$12,"Filing status error or invalid spouse input.",IF(NumFileStatusBoxes=0,"Filing status not indicated.", IF(Dual_Status_Alien<>"","Deduction is $0 due to spouse itemizing or dual-status alien.", IF(OR(DependentYOU<>"",DependentSPOUSE<>""),"Line 12a - Standard Deduction for Dependents",IF(AND(NQDisasterLoss>0,StdDeduct),"Standard deduction plus net qualified disaster losses"&CHAR(10)&"on Sch. A, Line 16.",IF(ItemizedDeduct,"Schedule A",IF(Over_65_or_Blind>0,"See Standard "&CHAR(10)&" Deduction Calculation"&CHAR(10)&" at right →","Standard Deduction")))))))))) | BC91: =IF(NumFileStatusBoxes=0,"Filing status not indicated.",IF(AND($BF$13,$BI$15,$BI$17),"",IF($BF$13,"Enter your birthdate and your spouse's birthdate above.",IF(NOT($BI$15),"Enter your birthdate above.",""))))
C92: 15750 | F92: 13a | H92: Qualified business income deduction from Form 8995 or Form 8995-A | AJ92: =IF(AND(AT92="",QBID_1040<>"",QBID_1040<>0,QBID_Income2High),"Error: See Form 8995.",". . . . . . . . . . . . . . ") | AK92: 13a | AL92: =IF(AX92<>"",ROUND(AX92,0),IF(QBID="",0,QBID)) | AY92: =IF(AY98,"Enter total taxes from "&CHAR(10)&"line 16 (1), (2), & (3) ↓ ↓ ↓","") | AZ92: Standard Deduction Calculation | BI92: Deduct_Age_Bonus, Deduct_Tip_Income, Deduct_OT_Income, Deduct_New_AutoLoan_Interest
B93: • | C93: Married filing | F93: 13b | H93: Additional deductions from Schedule 1-A, line 38 | AJ93: . . . . . . . . . . . . . . . . . . . . . | AK93: 13b | AL93: =IF(AX93<>"",ROUND(AX93,0),'Sch. 1-A'!AD105) | BF93: =IF(BD122="",0,BD122)
C94: jointly or | F94: 14 | H94: Add lines 12e, 13a, and 13b | AJ94: . . . . . . . . . . . . . . . . . . . . . . . . . . . . . . | AK94: 14 | AL94: =IF(AX94<>"",ROUND(AX94,0),SUM(AL91,QBID_1040,AL93)) | BA94: Single | BB94: MFJ or QSS | BC94: MFS | BD94: Head-of-H | BH94: NOTE: If your filing status is married filing separately, your spouse had no income, isn't filing a return, can't be claimed as a dependent on another person's return, and your spouse > 64 years old, or is blind,
C95: Qualifying | F95: 15 | H95: Subtract line 14 from line 11. | P95: If zero or less, enter -0-. | X95: This is your taxable income | AJ95: . . . . . . . | AK95: 15 | AL95: =IF(AX95<>"",ROUND(AX95,0),MAX(0,SUM(Adj_Gross_Inc,-TotalDeductions))) | AZ95: Std. Deduct. (Base) | BA95: =SD_Single | BB95: =SD_MFJW | BC95: =SD_Single | BD95: =SD_Head | BH95: you can check the appropriate boxes on the 'Age/Blindness' line.
C96: surviving spouse, | F96: 16 | H96: Tax (see instructions). Check if any from Form(s): | V96: 1 | X96: 8814 | AA96: 2 | AC96: 4972 | AE96: 3 | AJ96: . . | AK96: 16 | AL96: =IF(AX96<>"",ROUND(AX96,0),IF(OR(Birthday_Needed,FilingStatusError),"",IF(FEI_Tax_Worksheet,Tax_FEI_TW,IF(CGTW,SUM(CGTW_Tax,AO77),IF(SchDTW_Used,SUM(SchDTW_Tax,AO77),SUM(AY97,BM100)))))) | AU96: The tax in Line 16 is | AZ96: plus age > 64 | BA96: =IF(OR(YouR65,you_blind),BA90,"") | BB96: =IF(AND(YouR65,sp_over_64<>""),2*BB90,IF(OR(YouR65,sp_over_64<>""),BB90,"")) | BC96: =SUM(BF14,BF16)*BC90 | BD96: =IF(YouR65,BD90,"") | BI96: Taxable_Inc | BJ96: Single | BK96: MFJ/QW | BL96: MFS | BM96: HOH
C97: 31500 | F97: 17 | H97: Amount from Schedule 2, line 3 | AJ97: . . . . . . . . . . . . . . . . . . . . . . . . . . . . . | AK97: 17 | AL97: =IF(AX97<>"",ROUND(AX97,0),Schedule2_Tax) | AU97: calculated using: | AY97: =ROUND(AY96,0) | AZ97: plus Blind | BA97: =IF(you_blind="","",BA90) | BB97: =IF(AND(you_blind<>"",sp_blind<>""),2*BB90,IF(OR(you_blind<>"",sp_blind<>""),BB90,"")) | BC97: =SUM(BF15,BF17)*BC90 | BD97: =IF(you_blind="","",BD90) | BI97: =Taxable_Inc | BJ97: =LOOKUP(BI97,'Tax Table'!$B$2:$B$2063,'Tax Table'!$D$2:$D$2063) | BK97: =LOOKUP(BI97,'Tax Table'!$B$2:$B$2063,'Tax Table'!$E$2:$E$2063) | BL97: =LOOKUP(BI97,'Tax Table'!$B$2:$B$2063,'Tax Table'!$F$2:$F$2063) | BM97: =LOOKUP(BI97,'Tax Table'!$B$2:$B$2063,'Tax Table'!$G$2:$G$2063)
B98: • | C98: Head of | F98: 18 | H98: Add lines 16 and 17 | AJ98: . . . . . . . . . . . . . . . . . . . . . . . . . . . . . . . . | AK98: 18 | AL98: =IF(AX98<>"",ROUND(AX98,0),SUM(Tax_SubTotal,AL97)) | AU98: =IF(AX96<>"","Manual override",IF(FilingStatusError,"Filing status information needed or needs corrected.",IF(Birthday_Needed,"Birthdate information needed.",IF(OR(Total_Income=0,Taxable_Inc=""),"",IF(FEI_Tax_Worksheet,"FEI Tax Worksheet on "&CHAR(10)&"'Line 16 (QDCG Tax)'"&CHAR(10)&AY102,IF(CGTW,"QD & CG Tax WS"&CHAR(10)&"'Line 16 (QDCG Tax)'"&CHAR(10)&AY102,IF(SchDTW_Used,"Sch. D Tax Worksheet"&CHAR(10)&AY102,IF(Taxable_Inc<100000,"Tax Table"&CHAR(10)&AY102,"Tax Formula"&CHAR(10)&AY102)))))))) | AY98: =OR(W96<>"",AB96<>"",AF96<>"") | AZ98: Adj. Std. Deduct. | BA98: =IF(File_Single="","",SUM(BA95,BA96,BA97)) | BB98: =SUM(BB95,BB96,BB97) | BC98: =SUM(BC95,BC96,BC97) | BD98: =SUM(BD95,BD96,BD97) | BJ98: =IF(BI97<SectA_a2,"---",IF(BI97<=SectA_a3,ROUND(BI97*(SectA_b3/100),0)-SectA_d3,IF(BI97<=SectA_a4,ROUND(BI97*(SectA_b4/100),0)-SectA_d4,IF(BI97<=SectA_a5,ROUND(BI97*(SectA_b5/100),0)-SectA_d5,IF(BI97<=SectA_a6,ROUND(BI97*(SectA_b6/100),0)-SectA_d6,ROUND(BI97*(SectA_b7/100),0)-SectA_d7))))) | BK98: =IF(BI97<SectB_a2,"---",IF(BI97<=SectB_a3,ROUND(BI97*(SectB_b3/100),0)-SectB_d3,IF(BI97<=SectB_a4,ROUND(BI97*(SectB_b4/100),0)-SectB_d4,IF(BI97<=SectB_a5,ROUND(BI97*(SectB_b5/100),0)-SectB_d5,IF(BI97<=SectB_a6,ROUND(BI97*(SectB_b6/100),0)-SectB_d6,ROUND(BI97*(SectB_b7/100),0)-SectB_d7))))) | BL98: =IF(BI97<SectC_a1,"---",IF(BI97<=SectC_a2,ROUND(BI97*(SectC_b2/100),0)-SectC_d2,IF(BI97<=SectC_a3,ROUND(BI97*(SectC_b3/100),0)-SectC_d3,IF(BI97<=SectC_a4,ROUND(BI97*(SectC_b4/100),0)-SectC_d4,IF(BI97<=SectC_a5,ROUND(BI97*(SectC_b5/100),0)-SectC_d5,ROUND(BI97*(SectC_b6/100),0)-SectC_d6))))) | BM98: =IF(BI97<SectD_a2,"---",IF(BI97<=SectD_a3,ROUND(BI97*(SectD_b3/100),0)-SectD_d3,IF(BI97<=SectD_a4,ROUND(BI97*(SectD_b4/100),0)-SectD_d4,IF(BI97<=SectD_a5,ROUND(BI97*(SectD_b5/100),0)-SectD_d5,IF(BI97<=SectD_a6,ROUND(BI97*(SectD_b6/100),0)-SectD_d6,ROUND(BI97*(SectD_b7/100),0)-SectD_d7)))))
C99: household, | F99: 19 | H99: Child tax credit or credit for other dependents from Schedule 8812 | AJ99: . . . . . . . . . . . . . . . | AK99: 19 | AL99: =IF(AX99<>"",ROUND(AX99,0),CTCorCOD) | AY99: =IF(W96<>"","& Form 8814 "&"","") | BI99: =IF(File_Single<>"",BJ97,IF(File_Marr_Joint<>"",BK97,IF(File_Marr_Sep<>"", BL97,IF(File_Head<>"",BM97,IF(File_Qual_Widow<>"",BK97,"Filing status?"))))) | BJ99: ="<100k"
C100: 23625 | F100: 20 | H100: Amount from Schedule 3, line 8 | AJ100: . . . . . . . . . . . . . . . . . . . . . . . . . . . . | AK100: 20 | AL100: =IF(AX100<>"",ROUND(AX100,0),Sch3_NonRefundCredits) | AY100: =IF(AB96<>"","& Form 4972 "&"","") | BI100: =IF(File_Single<>"",BJ98,IF(OR(File_Marr_Joint<>"",File_Qual_Widow<>""),BK98,IF(File_Marr_Sep<>"", BL98,IF(File_Head<>"",BM98,"Filing status?")))) | BJ100: =">=100k" | BL100: Tax >> | BM100: =IF(NumFileStatusBoxes=0,"FilingStatus?",IF(BI97>100000,ROUND(BI100,0),ROUND(BI99,0)))
B101: • | C101: If you checked a | F101: 21 | H101: Add lines 19 and 20 | AJ101: . . . . . . . . . . . . . . . . . . . . . . . . . . . . . . . . | AK101: 21 | AL101: =IF(AX101<>"",ROUND(AX101,0),SUM(AL99,AL100)) | AU101: =IF(AND(AT101="",F8960_Applicable)," Check Form 8960.",IF(F8960_Applicable,"Form 8960 checked.","")) | AY101: =IF(AF96<>"","& Form "&AG96&" ","")
C102: a box on line | F102: 22 | H102: Subtract line 21 from line 18. If zero or less, enter -0- | AJ102: . . . . . . . . . . . . . . . . . . . . | AK102: =F102 | AL102: =IF(AX102<>"",ROUND(AX102,0),MAX(0,SUM(Tax,-AL101))) | AY102: =AY99&AY100&AY101
C103: 12a, 12b, 12c, | F103: 23 | H103: Other taxes, including self-employment tax, from Schedule 2, line 21 | AJ103: . . . . . . . . . . . . . . | AK103: =F103 | AL103: =IF(AX103<>"",ROUND(AX103,0),TotalOtherTaxes)
C104: or 12d, see instr. | F104: 24 | H104: Add lines 22 and 23. This is your total tax | AJ104: . . . . . . . . . . . . . . . . . . . . . . . | AK104: =F104 | AL104: =SUM(AL102,AL103)
B105: Payments and Refundable Credits | F105: 25 | H105: Federal income tax withheld from:
G106: a | H106: Form(s) W-2 | AD106: . . . . . . . . . . . . . . . . . . . . . . . . . | AE106: 25a | AF106: =IF(AX106<>"",ROUND(AX106,0),W2_Tax_Withheld)
G107: b | H107: Form(s) 1099 | AD107: . . . . . . . . . . . . . . . . . . . . . . . . . | AE107: 25b | AF107: =IF(AX107<>"",ROUND(AX107,0),SUM(F1099INT_FedTaxWH,F1099DIV_FedTaxWH,F1099G_FedTaxWH,F1099NEC_FedTaxWH,IRA_FedTaxWH,PA_FedTaxWH,CONV_FedTaxWH,SS_FedTaxWH_You,SS_FedTaxWH_Spouse,ROUND(AU107,0))) | AW107: 25b (add)
G108: c | H108: Other forms (see instructions) | AD108: . . . . . . . . . . . . . . . . . . . | AE108: 25c | AF108: =IF(AX108<>"",ROUND(AX108,0),SUM(F8959_WH,ROUND(AU108,0))) | AW108: 25c (add)
G109: d | H109: Add lines 25a through 25c | AJ109: . . . . . . . . . . . . . . . . . . . . . . . . . . . . . . | AK109: 25d | AL109: =SUM(W2_FedTaxWH,F1099_FedTaxWH,ROUND(AF108,0)) | AU109: =IF($AU$113>0,"Form 8959, Line 24,","")
F110: 26 | H110: =TaxYear&" estimated tax payments and amount applied from "&TaxYear-1&" return" | AJ110: . . . . . . . . . . . . . . . . . | AK110: 26 | AU110: =IF($AU$113>0,"<<< added "&TEXT($AU$113,"$0")&" to Line 25c.","")
H111: ="If you made estimated tax payments with your former spouse in "&TaxYear&","
B112: If you have a qualifying child, you may need to attach Sch EIC. | H112: enter their SSN (see instructions):
F113: 27 | G113: a | H113: Earned income credit (EIC) | AD113: . . . . . . . . . . . . . . . . . . . . | AE113: 27a | AF113: =IF(AX113<>"",ROUND(AX113,0),IF(AI117<>"",0,EarnedIncomeCredit)) | AU113: =IF(ISERROR(F8959_WH),0,F8959_WH)
...

Sheet Coversheet
B1: www.excel1040.com | D1: or | E1: https://sites.google.com/view/incometaxspreadsheet/home
B2: =IF(AND(TaxYearStart<>"",TaxYearEnd<>""),"For tax year "&TEXT(TaxYearStart,"mmm. d")&" - "&TEXT(TaxYearEnd,"mmm. dd, yyyy")&".","For tax year Jan. 1 - Dec. 31, "&TaxYear&".") | G2: Spreadsheet Revision Date/Time: | H2: =RevDateTime
B4: -- DISCLAIMER -- These spreadsheets are provided "as is", with no warranty of any kind, expressed or implied, and in no event will Glenn Reeves be liable for direct, indirect, incidental, or consequential damages resulting from the use of any of these spreadsheets. Glenn Reeves specifically disclaims the role of tax adviser. These spreadsheets attempt to perform the mechanics of tax preparation in accordance with IRS forms and instructions. The user must assume responsibility as to the correctness and appropriateness of any and all amounts entered and results produced.
B14: No password is needed. If you find a data entry cell to be protected, it is because it is a calculated value using input from another location in the spreadsheet. Read the instructions for that line to determine where the values are derived. However, for most calculated cells, a manual override cell is provided if you need to override the calculated value. After a while, you will figure out that the spreadsheet is completely functional without needing to unprotect it.
B24: Errors If you find an error, first check the revision date/time above against the revision number of the latest spreadsheet to be published at:
E26: https://sites.google.com/view/incometaxspreadsheet/home/changes
C27: If you find you're using an earlier version, review the changes made since your version
C28: to determine if the problem you've encountered has already been fixed.
C29: If so, please download the latest version and begin again. (There is no simple way to migrate...)
C30: If you cannot determine (or you're not sure) as to whether or not the problem(s) you've found
C31: has been corrected, please do your fellow taxpayers a favor by reporting the problem to:
E32: incometaxspreadsheet@gmail.com
B35: SUMMARY
B36: Adjusted Gross Income | E36: =Adj_Gross_Inc | G36: Form 1040, Line 11 | M36: Single | N36: =IF(Taxable_Inc="","---",IF(Taxable_Inc<BOTT_A2,TEXT(RATE_A1,"0%"),IF(Taxable_Inc<BOTT_A3,TEXT(RATE_A2,"0%"),IF(Taxable_Inc<BOTT_A4,TEXT(RATE_A3,"0%"),IF(Taxable_Inc<BOTT_A5,TEXT(RATE_A4,"0%"),IF(Taxable_Inc<BOTT_A6,TEXT(RATE_A5,"0%"),IF(Taxable_Inc<BOTT_A7,TEXT(RATE_A6,"0%"),TEXT(RATE_A7,"0.0%"))))))))
B37: Total Deductions | E37: =TotalDeductions | G37: Form 1040, Line 14
B38: Taxable Income | E38: =Taxable_Inc | G38: Form 1040, Line 15 | M38: MFJ or QW | N38: =IF(Taxable_Inc="","---",IF(Taxable_Inc<BOTT_B2,TEXT(RATE_B1,"0%"),IF(Taxable_Inc<BOTT_B3,TEXT(RATE_B2,"0%"),IF(Taxable_Inc<BOTT_B4,TEXT(RATE_B3,"0%"),IF(Taxable_Inc<BOTT_B5,TEXT(RATE_B4,"0%"),IF(Taxable_Inc<BOTT_B6,TEXT(RATE_B5,"0%"),IF(Taxable_Inc<BOTT_B7,TEXT(RATE_B6,"0%"),TEXT(RATE_B7,"0.0%"))))))))
B39: Total Tax | E39: =Tot_Tax | G39: Form 1040, Line 24 | M39: MFS | N39: =IF(Taxable_Inc="","---",IF(Taxable_Inc<BOTT_C2,TEXT(RATE_C1,"0%"),IF(Taxable_Inc<BOTT_C3,TEXT(RATE_C2,"0%"),IF(Taxable_Inc<BOTT_C4,TEXT(RATE_C3,"0%"),IF(Taxable_Inc<BOTT_C5,TEXT(RATE_C4,"0%"),IF(Taxable_Inc<BOTT_C6,TEXT(RATE_C5,"0%"),IF(Taxable_Inc<BOTT_C7,TEXT(RATE_C6,"0%"),TEXT(RATE_C7,"0.0%"))))))))
B40: Total Payments/Credits | E40: =Tot_Payments | G40: Form 1040, Line 33 | M40: HOH | N40: =IF(Taxable_Inc="","---",IF(Taxable_Inc<BOTT_D2,TEXT(RATE_D1,"0%"),IF(Taxable_Inc<BOTT_D3,TEXT(RATE_D2,"0%"),IF(Taxable_Inc<BOTT_D4,TEXT(RATE_D3,"0%"),IF(Taxable_Inc<BOTT_D5,TEXT(RATE_D4,"0%"),IF(Taxable_Inc<BOTT_D6,TEXT(RATE_D5,"0%"),IF(Taxable_Inc<BOTT_D7,TEXT(RATE_D6,"0%"),TEXT(RATE_D7,"0.0%"))))))))
B41: =IF(Overpaid>0,"Amount You Overpaid",IF(AND(E41<>"",E41>0),"Amount You Underpaid","")) | E41: =IF(Overpaid>0,Overpaid,IF(SUM(Tot_Tax,-Tot_Payments)>0,SUM(Tot_Tax,-Tot_Payments),"")) | G41: =IF(Overpaid>0,"Form 1040, Line 34","")
B42: =IF(TaxPenalty>0,"Penalty/Interest","") | E42: =IF(TaxPenalty>0,TaxPenalty,"") | G42: =IF(TaxPenalty>0,"Form 1040, Line 38","")
B43: =IF(Overpaid>0,"Amount To be Refunded","Amount You Owe") | E43: =IF('1040'!AL126>0,'1040'!AL126,You_Owe) | G43: =IF(Overpaid>0,"Form 1040, Line 35a","Form 1040, Line 37")
B44: =IF(AND('1040'!AD129<>"",'1040'!AD129>0),"Amount applied to your "&TaxYear+1&" estimated tax","") | E44: =IF(AND('1040'!AD129<>"",'1040'!AD129>1000),TEXT('1040'!AD129,"$0,000"),IF(AND('1040'!AD129<>"",'1040'!AD129>0),TEXT('1040'!AD129,"$0"),"")) | G44: =IF(AND('1040'!AD129<>"",'1040'!AD129>0),"Form 1040, Line 36","")
B46: Tax Bracket | E46: =IF(File_Single<>"",N36,IF(OR(File_Marr_Joint<>"",File_Qual_Widow<>""),N38,IF(File_Marr_Sep<>"",N39,IF(File_Head<>"",N40,"---"))))
B47: Effective Tax Rate | E47: =IF(E36=0,"---",E39/E36)
B51: This spreadsheet is free. However, if you would like to show your appreciation, you may make a contribution by clicking one of the following links and sending money as indicated.
C56: PayPal | E56: Zelle (App)
C57: https://paypal.me/incometaxspreadsheet | E57: https://www.zellepay.com/
C58: (Send to: IncomeTaxSpreadsheet@gmail.com ) | E58: (Send to: IncomeTaxSpreadsheet@gmail.com )
C60: Google Pay | E60: Venmo
C61: https://pay.google.com/payments/ | E61: https://www.venmo.com
C62: (Send to: IncomeTaxSpreadsheet@gmail.com ) | E62: (Send to: @Glenn-Reeves-2 )
C64: US Mail:
C65: Glenn Reeves
C66: (Tax Calculator)
C67: 4802 N 124th Ct
C68: Kansas City, KS 66109-3809
D70: Thank you for using my spreadsheet and for any money you decide to send!

Sheet Table of Contents
A2: Draft / Final | B2: Sheet Name (with hyperlink)
C3: Federal Income Tax Spreadsheet
C4: Table of Contents | G4: Draft IRS | H4: Final IRS | I4: Draft IRS | J4: Final IRS | K4: Updated | L4: Updated
C5: ="© Glenn Reeves, "&TaxYear+1 | F5: Form | G5: Instruction | H5: Instruction | I5: Form | J5: Form | K5: Draft Form | L5: Final
C6: Title / Description | F6: Last checked | G6: =MAX(G7:L72)
A7: =IF(L7<>"","F",IF(K7<>"","D","")) | B7: Coversheet | C7: Possible tax return coversheet which includes a disclaimer, important notes, and a summary.
A8: =IF(L8<>"","F",IF(K8<>"","D","")) | B8: Table of Contents | C8: Table of contents with links to the sheets included in this spreadsheet.
A9: =IF(L9<>"","F",IF(K9<>"","D","")) | B9: Instructions | C9: Important notes, general notes, and instructions to help you get started.
A10: =IF(L10<>"","F",IF(K10<>"","D","")) | B10: W-2s | C10: Form W-2, Wage and Tax Statement | E10: 1 | F10: =B10
A11: =IF(L11<>"","F",IF(K11<>"","D","")) | B11: 1099-INT | C11: Form 1099-INT, Interest Income | E11: 2 | F11: =B11
A12: =IF(L12<>"","F",IF(K12<>"","D","")) | B12: 1099-DIV | C12: Form 1099-DIV, Dividend Income | E12: 3 | F12: =B12
A13: =IF(L13<>"","F",IF(K13<>"","D","")) | B13: 1099-G | C13: Form 1099-G, Certain Government Payments | E13: 4 | F13: =B13
A14: =IF(L14<>"","F",IF(K14<>"","D","")) | B14: 1099-MISC | C14: Form 1099-MISC, Miscellaneous Income (Way too complicated -- included for information) | E14: 5 | F14: =B14
A15: =IF(L15<>"","F",IF(K15<>"","D","")) | B15: 1099-NEC | C15: Form 1099-NEC, Nonemployee Compensation | E15: 6 | F15: =B15
A16: =IF(L16<>"","F",IF(K16<>"","D","")) | B16: 1099-R | C16: Form 1099-R, Distributions From Pensions, Annuities, Retirement or Profit-Sharing Plans, IRAs, Insurance Contracts, etc. | E16: 7 | F16: =B16
A17: =IF(L17<>"","F",IF(K17<>"","D","")) | B17: Lines 4ab (IRA Dist.) | C17: IRA Distributions -- Lines 4a and 4b -- to determine how to report non-taxable and taxable IRA distributions. | E17: 8 | F17: =B17
A18: =IF(L18<>"","F",IF(K18<>"","D","")) | B18: SSA-1099 | C18: Form SSA-1099, Social Security Benefit Statement and IRS Notice 703, To See If Your Social Security Benefits May Be Taxable | E18: 9 | F18: =B18
A19: =IF(L19<>"","F",IF(K19<>"","D","")) | B19: 1040 | C19: Form 1040, U.S. Individual Income Tax Return | E19: 10 | F19: =B19 | G19: 45999 | I19: 45996 | J19: 46024 | K19: 45922 | L19: 46026
A20: =IF(L20<>"","F",IF(K20<>"","D","")) | B20: Sch. 1 | C20: Schedule 1, Additional Income and Adjustments to Income | E20: 11 | F20: =B20 | G20: 45999 | H20: 45733 | K20: 45991 | L20: 46026
A21: =IF(L21<>"","F",IF(K21<>"","D","")) | B21: Sch. 1-A | C21: Schedule 1-A, Additional Deductions | E21: 12 | F21: Sch. 1-A | G21: 45999 | I21: 45918 | K21: 45918 | L21: 46026
A22: =IF(L22<>"","F",IF(K22<>"","D","")) | B22: Sch 1, Line 1 (SALT) | C22: State and Local Income Tax Refund Worksheet — Line 1 | E22: 13 | F22: =B22 | G22: 45999 | K22: 45990 | L22: 46030 | N22: Tie lines 5 and 6 to previous year standard deduction amounts.
A23: =IF(L23<>"","F",IF(K23<>"","D","")) | B23: Sch. 1 Line 20 (IRA) | C23: IRA Deduction Worksheet — Schedule 1, Line 20 | E23: 14 | F23: =B23 | G23: 45999 | K23: 45990 | L23: 46030 | N23: Update line 1b limits and line 2 IRA deduction amounts
A24: =IF(L24<>"","F",IF(K24<>"","D","")) | B24: Sch. 1 Line 21 (Stu Loan) | C24: Student Loan Interest Deduction Worksheet — Schedule 1, Line 21 | E24: 15 | F24: =B24 | G24: 45999 | K24: 46009 | L24: 46030
A25: =IF(L25<>"","F",IF(K25<>"","D","")) | B25: Sch. 2 | C25: Schedule 2, Additional Taxes | E25: 16 | F25: =B25 | G25: 45999 | H25: 45785 | K25: 45862 | L25: 46026
A26: =IF(L26<>"","F",IF(K26<>"","D","")) | B26: Sch. 3 | C26: Schedule 3, Additional Credits and Payments | E26: 17 | F26: =B26 | G26: 45999 | H26: 45785 | I26: 45862 | K26: 46026 | L26: 46027
A27: =IF(L27<>"","F",IF(K27<>"","D","")) | B27: Earned Inc WS | C27: Earned Income Worksheet — Used as input to Line 9 (SD Depnts), Line 13a (CTC), & Form 8812. | E27: 18 | F27: =B27
A28: =IF(L28<>"","F",IF(K28<>"","D","")) | B28: Lines 5ab (Simplified Meth WS) | C28: Simplified Method Worksheet—Lines 5a and 5b -- to determine taxable amount of retirement pension or annuity. | E28: 19 | F28: =B28 | G28: 45999 | I28: 45980 | K28: 45988 | L28: 46030
A29: =IF(L29<>"","F",IF(K29<>"","D","")) | B29: Line 6ab (SS Bene) | C29: Social Security Benefits Worksheet – Lines 6a and 6b -- to determine taxable amount of Social Security benefits. | E29: 20 | F29: =B29 | G29: 45999 | K29: 45989 | L29: 46030
A30: =IF(L30<>"","F",IF(K30<>"","D","")) | B30: Line 12e (SD Depnts) | C30: Standard Deduction Worksheet for Dependents — Line 12e | E30: 21 | F30: =B30 | G30: 45999 | K30: 45990 | L30: 46030 | N30: Check lines 2 and 3 for amount changes.
A31: =IF(L31<>"","F",IF(K31<>"","D","")) | B31: Line 16 (QDCG Tax) | C31: Qualified Dividends and Capital Gain Tax Worksheet—Line 16 | E31: 22 | F31: =B31 | G31: 45999 | K31: 45990 | L31: 46030 | N31: Check lines 6 and 13 for amount changes.
A32: =IF(L32<>"","F",IF(K32<>"","D","")) | B32: Line 27a (EIC) | C32: Line 27a — Earned Income Credit Worksheet — Spreadsheet provides assistance in completing this. | E32: 23 | F32: =B32 | G32: 45999 | L32: 46038 | N32: Check Step 2, line 2, for amount changes. Check Worksheet A, Part 2, line 5, for amount changes.
A33: =IF(L33<>"","F",IF(K33<>"","D","")) | B33: Sch. A | C33: Schedule A, Itemized Deductions | E33: 24 | F33: =B33 | G33: 45992 | H33: 46009 | I33: 45911 | J33: 46008 | K33: 46014 | L33: 46020
A34: =IF(L34<>"","F",IF(K34<>"","D","")) | B34: Sch. B | C34: Schedule B, Interest and Ordinary Dividends | E34: 25 | F34: =B34 | G34: 45770 | I34: 45784 | K34: 45955 | L34: 46030
A35: =IF(L35<>"","F",IF(K35<>"","D","")) | B35: Sch. C | C35: Schedule C, Profit or Loss from Business (Two Schedule C's are included) | E35: 26 | F35: =B35 | G35: 45985 | H35: 46028 | I35: 45756 | J35: 46028 | L35: 46029
A36: =IF(L36<>"","F",IF(K36<>"","D","")) | B36: Sch. D | C36: Schedule D, Capital Gains and Losses | E36: 27 | F36: =B36 | G36: 46002 | H36: 46002 | I36: 45936 | J36: 46008 | K36: 45983 | L36: 46021
A37: =IF(L37<>"","F",IF(K37<>"","D","")) | B37: Sch. D WS | C37: Schedule D Worksheets - Capital Loss Carryover Worksheet—Schedule D, Lines 6 and 14 - 28% Rate Gain Worksheet—Schedule D, Line 18 - Schedule D Tax Worksheet | E37: 28 | F37: =B37 | G37: 46002 | H37: 46002 | L37: 46021
A38: =IF(L38<>"","F",IF(K38<>"","D","")) | B38: Sch. E | C38: Schedule E, Supplemental Income and Loss (2 forms) | E38: 29 | F38: =B38 | H38: 46009 | I38: 45783 | J38: 46009 | L38: 46021
A39: =IF(L39<>"","F",IF(K39<>"","D","")) | B39: Sch. E (2) | C39: Schedule E, Supplemental Income and Loss (2 forms) | E39: 30 | F39: =B39 | H39: 46009 | I39: 45783 | J39: 46009 | L39: 46021
A40: =IF(L40<>"","F",IF(K40<>"","D","")) | B40: Sch. F | C40: Schedule F, Profit or Loss from Farming | E40: 31 | F40: =B40 | G40: 45987 | H40: 46009 | I40: 45783 | J40: 46009 | L40: 46021
A41: =IF(L41<>"","F",IF(K41<>"","D","")) | B41: Sch. R | C41: Schedule R, Credit for the Elderly or the Disabled | E41: 32 | F41: =B41 | I41: 45931 | J41: 45933 | L41: 46030
A42: =IF(L42<>"","F",IF(K42<>"","D","")) | B42: Sch. SE | C42: Schedule SE, Self-Employement Tax (Two Schedule SE's are included) | E42: 33 | F42: =B42 | G42: 45926 | I42: 45797 | L42: 46030
A43: =IF(L43<>"","F",IF(K43<>"","D","")) | B43: 1116 | C43: Form 1116, Foreign Tax Credit | E43: 34 | F43: =B43 | G43: 45950 | H43: 46029 | I43: 45929 | J43: 46028 | L43: 46030
A44: =IF(L44<>"","F",IF(K44<>"","D","")) | B44: 2210 | C44: Form 2210, Underpayment of Estimated Tax by Individuals, Estates, and Trusts | E44: 35 | F44: =B44 | G44: 45940 | I44: 46014 | J44: 46036
A45: =IF(L45<>"","F",IF(K45<>"","D","")) | B45: 2441 | C45: Form 2441, Child and Dependent Care Expenses | E45: 36 | F45: =B45 | G45: 45930 | H45: 46007 | J45: 46007 | L45: 46023
A46: =IF(L46<>"","F",IF(K46<>"","D","")) | B46: 2555 | C46: Form 2555, Foreign Earned Income | E46: 37 | F46: =B46 | G46: 45917 | H46: 45917 | J46: 45917 | L46: 46006
A47: =IF(L47<>"","F",IF(K47<>"","D","")) | B47: 4137 | C47: Form 4137, Social Security and Medicare Tax on Unreported Tip Income | E47: 38 | F47: =B47 | L47: 46054
A48: =IF(L48<>"","F",IF(K48<>"","D","")) | B48: 4562 | C48: Form 4562, Depreciation and Amortization | E48: 39 | F48: =B48 | J48: 46029 | L48: 46031
A49: =IF(L49<>"","F",IF(K49<>"","D","")) | B49: 5695 | C49: Residential Energy Credits | E49: 40 | F49: 5695 | H49: 45994 | J49: 45994 | L49: 46025
A50: =IF(L50<>"","F",IF(K50<>"","D","")) | B50: 6251 | C50: Form 6251, Alternative Minimum Tax—Individuals | E50: 41 | F50: =B50 | G50: 45995 | I50: 45930 | J50: 46029 | K50: 45862 | L50: 46031
A51: =IF(L51<>"","F",IF(K51<>"","D","")) | B51: 8283 | C51: Form 8283, Noncash Charitable Contributions | E51: 42 | F51: =B51 | G51: 46014 | J51: 46028
A52: =IF(L52<>"","F",IF(K52<>"","D","")) | B52: 8582 | C52: Form, 8582, Passive Activity Loss Limitations | E52: 43 | F52: =B52 | G52: 45989 | H52: 45967 | J52: 45967 | L52: 46038
A53: =IF(L53<>"","F",IF(K53<>"","D","")) | B53: 8606 | C53: Form 8606, Nondeductible IRAs | E53: 44 | F53: =B53 | G53: 45992 | J53: 46006 | L53: 46093
A54: =IF(L54<>"","F",IF(K54<>"","D","")) | B54: 8801 | C54: Credit for Prior Year Minimum Tax — Individuals, Estates, and Trusts | E54: 45 | F54: =B54 | G54: 45869 | H54: 46014 | I54: 45777 | J54: 46014 | K54: 45904 | L54: 46035
A55: =IF(L55<>"","F",IF(K55<>"","D","")) | B55: 8812 | C55: Schedule 8812, Additional Child Tax Credit | E55: 46 | F55: =B55 | G55: 46006 | H55: 46010 | I55: 45896 | J55: 46010 | K55: 46010 | L55: 46020
A56: =IF(L56<>"","F",IF(K56<>"","D","")) | B56: 8829 | C56: Form 8829, Expenses for Business Use of Your Home | E56: 47 | F56: =B56 | G56: 45876 | H56: 46031 | J56: 46006
A57: =IF(L57<>"","F",IF(K57<>"","D","")) | B57: 8863 | C57: Form 8863, Education Credits (American Opportunity and Lifetime Learning Credits) | E57: 48 | F57: =B57 | J57: 46006 | L57: 46031
A58: =IF(L58<>"","F",IF(K58<>"","D","")) | B58: 8880 | C58: Form 8880, Credit for Qualified Retirement Savings Contributions | E58: 49 | F58: =B58 | I58: 45908 | J58: 46006
A59: =IF(L59<>"","F",IF(K59<>"","D","")) | B59: 8889 | C59: Form 8889, Health Savings Accounts | E59: 50 | F59: =B59 | G59: 46000 | H59: 46006 | J59: 46006
A60: =IF(L60<>"","F",IF(K60<>"","D","")) | B60: 8919 | C60: Form 8919, Uncollected Social Security and Medicare Tax on Wages | E60: 51 | F60: =B60 | L60: 46054
A61: =IF(L61<>"","F",IF(K61<>"","D","")) | B61: 8949A | C61: Form 8949, Sales and Other Dispositions of Capital Assets | E61: 52 | F61: =B61 | I61: 45783 | J61: 46002 | K61: 45983 | L61: 46030
A62: =IF(L62<>"","F",IF(K62<>"","D","")) | B62: 8949B | C62: Form 8949, Sales and Other Dispositions of Capital Assets | E62: 53 | F62: =B62 | I62: 45783 | J62: 46002 | K62: 45983 | L62: 46030
A63: =IF(L63<>"","F",IF(K63<>"","D","")) | B63: 8949C | C63: Form 8949, Sales and Other Dispositions of Capital Assets | E63: 54 | F63: =B63 | I63: 45783 | J63: 46002 | K63: 45983 | L63: 46030
A64: =IF(L64<>"","F",IF(K64<>"","D","")) | B64: 8949D | C64: Form 8949, Sales and Other Dispositions of Capital Assets | E64: 55 | F64: =B64 | I64: 45783 | J64: 46002 | K64: 45983 | L64: 46030
A65: =IF(L65<>"","F",IF(K65<>"","D","")) | B65: 8959 | C65: Form 8959, Additional Medicare Tax | E65: 56 | F65: =B65 | G65: 45916 | H65: 46006 | J65: 46006 | L65: 46042
A66: =IF(L66<>"","F",IF(K66<>"","D","")) | B66: 8960 | C66: Form 8960, Net Investment Income Tax—Individuals, Estates, and Trusts | E66: 57 | F66: =B66 | G66: 45999 | I66: 45917 | J66: 46029 | K66: 46042 | L66: 46091
A67: =IF(L67<>"","F",IF(K67<>"","D","")) | B67: 8962 | C67: Form 8962, Premium Tax Credit | E67: 58 | F67: =B67 | G67: 45946 | I67: 45800 | J67: 46029 | L67: 46038
A68: =IF(L68<>"","F",IF(K68<>"","D","")) | B68: 8995 | C68: Form 8995, Qualified Business Income Deduction Simplified Computation | E68: 59 | F68: =B68 | H68: 46036 | I68: 45917 | J68: 46031 | K68: 46013 | L68: 46038 | N68: OBBBA: Implemented minimum $400 deduction for QBI >=$1,000.
A69: =IF(L69<>"","F",IF(K69<>"","D","")) | B69: EIC Table | C69: Earned Income Credit (EIC) Table (From Form 1040, General Instructions) | E69: 60 | F69: =B69 | J69: 46009
A70: =IF(L70<>"","F",IF(K70<>"","D","")) | B70: Tax Table | C70: Tax Table (From Form 1040, General Instructions) | E70: 61 | F70: =B70 | G70: 45853 | H70: 45853 | I70: 45853 | J70: 45853 | K70: 45853 | L70: 45853 | N70: No changes.
A71: =IF(L71<>"","F",IF(K71<>"","D","")) | B71: Changes | C71: Changes made to this spreadsheet since it's first publication this tax year | E71: 62 | F71: =B71
F75: Improvement ideas for 2025
F76: Form 8801, Credit for Prior Year Minimum Tax - Individuals, Estates, and Trusts
F77: Form 8936, Clean Vehicle Credits
F78: 1099-SEC
F79: 1099-MISC
F80: 1099-V, Payment Voucher for Individuals
F82: 2210, Underpayment of Estimated Tax by Individuals, Estates, and Trusts

Sheet Instructions
A2: Excel1040 -- Income Tax Spreadsheet
A3: Instructions for Use
B5: IMPORTANT NOTES:
B6: 1. | C6: The purpose of this spreadsheet is to help U.S. taxpayers calculate their own federal income tax returns.
C7: The spreadsheet attempts to perform the mechanics of tax preparation (i.e. 'do the math') in accordance
C8: with IRS forms and instructions.
B10: 2. | C10: This spreadsheet is designed for taxpayers who are capable of preparing their own federal income tax returns.
C11: Users of this spreadsheet must know what information needs to be entered and where to enter it.
C12: Users of this spreadsheet must also be sufficiently familiar with the IRS forms and instructions that apply to
C13: their tax return in order to detect and correct any and all user and spreadsheet errors that might occur.
C14: Although some error checking is included, this spreadsheet will not prevent you from making mistakes.
B16: 3. | C16: The user must assume full responsibility as to the correctness and appropriateness of any and all amounts
C17: entered and results produced. Be sure to use current copies of actual IRS forms and instructions when
C18: validating the spreadsheet's results. | H18: IRS forms and instructions: | I18: https://www.irs.gov/downloads/irs-pdf
B20: 4. | C20: It is vitally important to the continued success of this spreadsheet that users promptly report errors
C21: so that the spreadsheet can be corrected. | H21: Please report errors to: | I21: incometaxspreadsheet@gmail.com
B23: GENERAL NOTES:
B24: 1. | C24: Unprotected data entry cells have a light blue fill color.
C25: Cells containing calculated amounts are usually protected and have a darker blue fill color.
C26: Form and worksheet areas are protected. However, users are able to adjust printing properties.
C27: Formatting of cells, rows, and columns is also available.
B29: 2. | C29: "Manual override" cells are available for many calculated cells. The use of override cells is discouraged
C30: because manual overrides can defeat the spreadsheet's automatic updating feature. If you are having
C31: to use a manual override because of a spreadsheet error, be sure to report the error as soon as possible.
C33: NOTE: To clear data from an override cell, highlight it and then press the <Delete> key.
C34: Do not press the <space> bar because, although it is invisible, the <space> character is treated the
C35: same as any visible character.
B37: 3. | C37: To check a checkbox, simply type an 'X' (any character will work) in the box and press <Enter>.
C39: NOTE: To clear an 'X' from an checkbox, highlight it and then press the <Delete> key.
C40: Do not press the <space> bar because, although it is invisible, the <space> character is treated the
C41: same as any visible character.
B43: 4. | C43: Prior to printing, to remove colors from all forms and worksheets, place an 'X' in Cell AV2 on the '1040' sheet.
C44: Likewise, to remove social security numbers from all forms and worksheets, place an "X" in Cell AV3
C45: on the '1040' sheet.
B47: 5. | C47: If using copy/paste to copy information from another source, be sure to paste using 'Paste-Values'.
C48: Otherwise, cell properties could be inadvertently changed. (e.g. A normally unprotected cell could become
C49: protected.)
B51: 6. | C51: On Form 1040, to save time, it's generally okay to enter alternate information (e.g. SSN = 111-22-3333).
C52: Be aware, to perform an accurate tax calculation, the spreadsheet will need reasonably complete and
C53: accurate birthdate, accurate state of residence, and a valid SSN. Don't leave these cells blank.
B55: 7. | C55: Any personal information entered into this spreadsheet is available only to you. This spreadsheet
C56: has no ability to transmit your information anywhere.
B58: NOTES for LibreOffice Users:
B60: 1. | C60: LibreOffice users tell me LibreOffice version 25 will successfully open this spreadsheet.
B62: 2. | C62: To save a copy of this spreadsheet in .ods format, try performing the following steps:
C63: 1). Load the spreadsheet as an .xlsx file, then save it as an .fods file.
C64: 2). Close the .fods file. Then re-open the .fods file
C65: 3). Save the .fods file as an .ods file.
C66: 4) Close the .ods file. Then, re-open the .ods file.
B68: INSTRUCTIONS:
B69: 1. | C69: Click on the tab labeled '1040' and enter all of the taxpayer information required at the top of Form 1040.
B70: 2. | C70: Enter your birthdate and, if filing Married - Filing Jointly, enter your spouse's birthdate to the right of
C71: the Form 1040.
B72: 3. | C72: Click on the tab labeled 'W-2s' and enter any employment income reported to you on Form W-2.
C73: Be sure to enter your information in Rows 2 through 24 and your spouse's information into Rows 31 through 53.
B74: 4. | C74: Click on the tab labeled '1099-INT' and enter any interest income reported to you on Form 1099-INT.
C75: (Interest income information will automatically appear on Schedule B, Line 1.)
B76: 5. | C76: Click on the tab labeled '1099-DIV' and enter any dividend income reported on Form 1099-DIV.
C77: (Dividend income information will automatically appear on Schedule B, Line 5.)
B78: 6. | C78: Click on the tab labeled '1099-R' and enter any IRA/pension/annuity income reported to you on Form 1099-R.
B79: 7. | C79: Click on the tab labeled 'SSA-1099' and enter any Social Security income reported to you on Form SSA-1099.
B80: 8. | C80: Begin a careful, line-by-line, review of the sheet labeled '1040'. If additional information is needed for a
C81: particular line, then look for a sheet associated with that line (e.g. "Line 9 (QBID)") to determine if additional
C82: information needs to be entered.
C83: HINT: Recommend regularly checking and saving your spreadsheet.
B84: 9. | C84: Review every tab to determine its applicability to your tax return and make sure each sheet is completed.
C85: NOTE: At any time, you may change the tab color by right-mouse clicking on the tab. Also, at any time,
C86: you may click and drag sheet tabs to be arranged in any order you desire. Doing so will not affect
C87: the function of the spreadsheet.
B88: 10. | C88: Recommend printing your return and reviewing the printed copy against actual IRS forms and instructions.
B89: 11. | C89: Transfer results to an electronic filing service or hard copies of the forms.
C93: Table of Contents

Sheet W-2s
C1: Information from Form W-2, Wage and Tax Statement | G1: Maximum SS Tax Earnings: | H1: 176100 | I1: SS Tax Rate: | J1: 0.062 | L1: Max. SS Tax: | M1: =ROUND(MaxSSTaxEarnings*SSTaxRate,2) | N1: per person | P1: Notes
A2: Line | B2: Code | C2: =IF(Name_1st_Yours="","Enter your name on the"&CHAR(10)&"sheet labeled '1040'",NameYours) | D2: Your Employer #1 | E2: Your Employer #2 | F2: Your Employer #3 | G2: Your Employer #4 | H2: Your Employer #5 | I2: Your Employer #6 | J2: Total | K2: Excess | M2: Used at: | P2: Date
A3: 1 | C3: Wages, tips, other compensation | J3: =SUM(ROUND(D3,0),ROUND(E3,0),ROUND(F3,0),ROUND(G3,0),ROUND(H3,0),ROUND(I3,0)) | O3: 120000
A4: 2 | C4: Federal income tax withheld | J4: =SUM(ROUND(D4,0),ROUND(E4,0),ROUND(F4,0),ROUND(G4,0),ROUND(H4,0),ROUND(I4,0)) | O4: =0.19*O3
A5: 3 | C5: Social security wages | J5: =SUM(ROUND(D5,0),ROUND(E5,0),ROUND(F5,0),ROUND(G5,0),ROUND(H5,0),ROUND(I5,0)) | M5: Sch. SE, Line 8a, Form 8919, line 8 | O5: =IF(O3="",0,MIN(O3,MaxSSTaxEarnings))
A6: 4 | C6: Social security tax withheld | J6: =SUM(D6:I6) | K6: =IF(SUM(J6,-MaxSSTax)>0,SUM(J6,-MaxSSTax),0) | M6: =IF(AND(EmployerCountYou>1,K6>0),"Schedule 3, line 11.",IF(AND(EmployerCountYou=1,K6>0),"See note below.","")) | N6: =IF(K6<1000,TEXT(K6,"$0.00"),TEXT(K6,"$0,000.00")) | O6: =MIN(SSTaxRate*O3,MaxSSTax)
A7: 5 | C7: Medicare wages and tips | J7: =SUM(ROUND(D7,0),ROUND(E7,0),ROUND(F7,0),ROUND(G7,0),ROUND(H7,0),ROUND(I7,0)) | O7: =O3
A8: 6 | C8: Medicare tax withheld | J8: =SUM(ROUND(D8,0),ROUND(E8,0),ROUND(F8,0),ROUND(G8,0),ROUND(H8,0),ROUND(I8,0)) | M8: Only bolded amounts are used in this spreadsheet. | O8: =MedicareTaxRate*O7
A9: 7 | C9: Social Security Tips | J9: =SUM(ROUND(D9,0),ROUND(E9,0),ROUND(F9,0),ROUND(G9,0),ROUND(H9,0),ROUND(I9,0)) | M9: Sch. SE, Line 8a, Form 8919, line 8 | O9: 26789
A10: 8 | C10: Allocated Tips | J10: =SUM(ROUND(D10,0),ROUND(E10,0),ROUND(F10,0),ROUND(G10,0),ROUND(H10,0),ROUND(I10,0))
A11: 10 | C11: Dependent Care Benefits | J11: =SUM(ROUND(D11,0),ROUND(E11,0),ROUND(F11,0),ROUND(G11,0),ROUND(H11,0),ROUND(I11,0))
A12: 11 | C12: Nonqualified plans | J12: =SUM(ROUND(D12,0),ROUND(E12,0),ROUND(F12,0),ROUND(G12,0),ROUND(H12,0),ROUND(I12,0))
A13: 12 | B13: A | C13: Uncollected Social Security Tax on Tips | I13: --- | J13: =SUM(ROUND(D13,0),ROUND(E13,0),ROUND(F13,0),ROUND(G13,0),ROUND(H13,0)) | M13: Form 8919 (You), lines 1-5
A14: 12 | B14: B | C14: Uncollected Medicare tax on Tips | I14: --- | J14: =SUM(ROUND(D14,0),ROUND(E14,0),ROUND(F14,0),ROUND(G14,0),ROUND(H14,0)) | M14: Form 8919 (You), lines 1-5
A15: 12 | B15: H | C15: Elective Deferral to 501(c)(18)(D) plan | J15: =SUM(ROUND(D15,0),ROUND(E15,0),ROUND(F15,0),ROUND(G15,0),ROUND(H15,0),ROUND(I15,0)) | M15: Form 8880, line 2 (a)
A16: 12 | B16: K | C16: 20% Excise Tax on Excess 'golden parachute' payments | J16: =SUM(ROUND(D16,0),ROUND(E16,0),ROUND(F16,0),ROUND(G16,0),ROUND(H16,0),ROUND(I16,0)) | M16: Form 1040, Sch. 2, line 17k
A17: 12 | B17: M | C17: Uncollected Social Security tax on group-term life (former employees) | J17: =SUM(ROUND(D17,0),ROUND(E17,0),ROUND(F17,0),ROUND(G17,0),ROUND(H17,0),ROUND(I17,0)) | M17: Form 1040, Sch. 2, line 13
A18: 12 | B18: N | C18: Uncollected medicare tax on group-term life (former employees) | J18: =SUM(ROUND(D18,0),ROUND(E18,0),ROUND(F18,0),ROUND(G18,0),ROUND(H18,0),ROUND(I18,0)) | M18: Form 1040, Sch. 2, line 13
A19: 12 | B19: P | C19: Excludable moving expense reinbursements for military | J19: =SUM(ROUND(D19,0),ROUND(E19,0),ROUND(F19,0),ROUND(G19,0),ROUND(H19,0),ROUND(I19,0)) | M19: Form 1040, Sch. 2, line 14
A20: 12 | B20: Q | C20: Non Taxable Combat Pay | J20: =SUM(ROUND(D20,0),ROUND(E20,0),ROUND(F20,0),ROUND(G20,0),ROUND(H20,0),ROUND(I20,0)) | M20: Form 2441, Part 4 of Earned Income Worksheet for Line 4
A21: 12 | B21: S | C21: Elective deferral to SIMPLE IRA | J21: =SUM(ROUND(D21,0),ROUND(E21,0),ROUND(F21,0),ROUND(G21,0),ROUND(H21,0),ROUND(I21,0)) | M21: Form 8880, line 2 (a)
A22: 12 | B22: W | C22: Employer contributions to HSA. | J22: =SUM(ROUND(D22,0),ROUND(E22,0),ROUND(F22,0),ROUND(G22,0),ROUND(H22,0),ROUND(I22,0)) | M22: Form 8889, Part I, line 9 (You)
A23: 13 | C23: Stat Emp / Retire / 3rd Party Sick | J23: =SUM(ROUND(D23,0),ROUND(E23,0),ROUND(F23,0),ROUND(G23,0),ROUND(H23,0),ROUND(I23,0))
A24: 14 | C24: Other | J24: =SUM(ROUND(D24,0),ROUND(E24,0),ROUND(F24,0),ROUND(G24,0),ROUND(H24,0),ROUND(I24,0))
A25: 14 | C25: Railroad retire (RRTA) compensation | J25: =SUM(ROUND(D25,0),ROUND(E25,0),ROUND(F25,0),ROUND(G25,0),ROUND(H25,0),ROUND(I25,0)) | M25: =IF(J35,"Form 8959, line 14","")
A26: 14 | C26: RRTA medicare tax withheld (see Form CT-2) | J26: =SUM(ROUND(D26,0),ROUND(E26,0),ROUND(F26,0),ROUND(G26,0),ROUND(H26,0),ROUND(I26,0))
A27: 15 | C27: State - Employer's state ID number | J27: - - -
A28: 16 | C28: State wages, tips, etc. | J28: =SUM(ROUND(D28,0),ROUND(E28,0),ROUND(F28,0),ROUND(G28,0),ROUND(H28,0),ROUND(I28,0))
A29: 17 | C29: State income tax | J29: =SUM(ROUND(D29,0),ROUND(E29,0),ROUND(F29,0),ROUND(G29,0),ROUND(H29,0),ROUND(I29,0)) | O29: =0.05*O3
A30: 18 | C30: Local wages, tips, etc. | J30: =SUM(ROUND(D30,0),ROUND(E30,0),ROUND(F30,0),ROUND(G30,0),ROUND(H30,0),ROUND(I30,0))
A31: 19 | C31: Local income tax | J31: =SUM(ROUND(D31,0),ROUND(E31,0),ROUND(F31,0),ROUND(G31,0),ROUND(H31,0),ROUND(I31,0))
A32: 20 | C32: Locality name | J32: - - -
C33: Employer count (You) | D33: =IF(D6<>"",1,0) | E33: =IF(E6<>"",1,0) | F33: =IF(F6<>"",1,0) | G33: =IF(G6<>"",1,0) | H33: =IF(H6<>"",1,0) | I33: =IF(I6<>"",1,0) | J33: =SUM(D33:I33)
C34: ="Medicare wages and tip > "&TEXT(K34,"$0,000") | D34: =(D7>$K34) | E34: =(E7>$K34) | F34: =(F7>$K34) | G34: =(G7>$K34) | H34: =(H7>$K34) | I34: =(I7>$K34) | J34: =OR(D34:I34) | K34: ='8959'!$H$24
C35: ="RRTA > "&TEXT(K35,"$0,000") | D35: =IF(D25>'8959'!$H$24,TRUE,FALSE) | E35: =IF(E25>'8959'!$H$24,TRUE,FALSE) | F35: =IF(F25>'8959'!$H$24,TRUE,FALSE) | G35: =IF(G25>'8959'!$H$24,TRUE,FALSE) | H35: =IF(H25>'8959'!$H$24,TRUE,FALSE) | I35: =IF(I25>'8959'!$H$24,TRUE,FALSE) | J35: =OR(D35:I35) | K35: ='8959'!H46
D36: =IF(AND(J6>MaxSSTax,EmployerCountYou=1),"Notify your employer that they withheld "&N6&" too much Social Security Tax or file Form 843, Claim for Refund and Request for Abatement.","")
C37: =IF(OR(AND(D7="",D8<>""),AND(E7="",E8<>""),AND(F7="",F8<>""),AND(G7="",G8<>"")),"CAUTION: Entering an amount into Line 6 without entering an amount into Line 5 will result in a tax calculation error.","")
C38: Information from Form W-2, Wage and Tax Statement
A39: Line | B39: Code | C39: =IF(Name_1st_Sp="","Enter your spouse's name on"&CHAR(10)&"the sheet labeled '1040'",NameSpouse) | D39: Spouse's Employer #1 | E39: Spouse's Employer #2 | F39: Spouse's Employer #3 | G39: Spouse's Employer #4 | H39: Spouse's Employer #5 | I39: Spouse's Employer #6 | J39: Total | K39: Excess | M39: Used at: | O39: 0.75
A40: 1 | C40: Wages, tips, other compensation | J40: =SUM(ROUND(D40,0),ROUND(E40,0),ROUND(F40,0),ROUND(G40,0),ROUND(H40,0),ROUND(I40,0)) | O40: =O3*$O$39
A41: 2 | C41: Federal income tax withheld | J41: =SUM(ROUND(D41,0),ROUND(E41,0),ROUND(F41,0),ROUND(G41,0),ROUND(H41,0),ROUND(I41,0)) | O41: =0.19*O40
A42: 3 | C42: Social security wages | J42: =SUM(ROUND(D42,0),ROUND(E42,0),ROUND(F42,0),ROUND(G42,0),ROUND(H42,0),ROUND(I42,0)) | M42: Sch. SE, Line 8a, Form 8919, line 8 | O42: =MIN(O40,MaxSSTaxEarnings)
A43: 4 | C43: Social security tax withheld | J43: =SUM(D43:I43) | K43: =IF(SUM(J43,-MaxSSTax)>0,SUM(J43,-MaxSSTax),0) | M43: =IF(AND(EmployerCountSpouse>1,K43>0),"Schedule 3, line 11.",IF(AND(EmployerCountSpouse=1,K43>0),"See note below.","")) | N43: =IF(K43<1000,TEXT(K43,"$0.00"),TEXT(K43,"$0,000.00")) | O43: =MIN(SSTaxRate*O40,MaxSSTax)
A44: 5 | C44: Medicare wages and tips | J44: =SUM(ROUND(D44,0),ROUND(E44,0),ROUND(F44,0),ROUND(G44,0),ROUND(H44,0),ROUND(I44,0)) | O44: =O40
A45: 6 | C45: Medicare tax withheld | J45: =SUM(ROUND(D45,0),ROUND(E45,0),ROUND(F45,0),ROUND(G45,0),ROUND(H45,0),ROUND(I45,0)) | M45: Only bolded amounts are used in this spreadsheet. | O45: =MedicareTaxRate*O44
A46: 7 | C46: Social Security Tips | J46: =SUM(ROUND(D46,0),ROUND(E46,0),ROUND(F46,0),ROUND(G46,0),ROUND(H46,0),ROUND(I46,0)) | M46: Sch. SE, Line 8a, Form 8919, line 8
A47: 8 | C47: Allocated Tips | J47: =SUM(ROUND(D47,0),ROUND(E47,0),ROUND(F47,0),ROUND(G47,0),ROUND(H47,0),ROUND(I47,0))
A48: 10 | C48: Dependent Care Benefits | J48: =SUM(ROUND(D48,0),ROUND(E48,0),ROUND(F48,0),ROUND(G48,0),ROUND(H48,0),ROUND(I48,0))
A49: 11 | C49: Nonqualified plans | J49: =SUM(ROUND(D49,0),ROUND(E49,0),ROUND(F49,0),ROUND(G49,0),ROUND(H49,0),ROUND(I49,0))
A50: 12 | B50: A | C50: Uncollected Social Security Tax on Tips | I50: --- | J50: =SUM(ROUND(D50,0),ROUND(E50,0),ROUND(F50,0),ROUND(G50,0),ROUND(H50,0)) | M50: Form 8919 (Spouse), lines 1-5
A51: 12 | B51: B | C51: Uncollected Medicare tax on Tips | I51: --- | J51: =SUM(ROUND(D51,0),ROUND(E51,0),ROUND(F51,0),ROUND(G51,0),ROUND(H51,0)) | M51: Form 8919 (Spouse), lines 1-5
A52: 12 | B52: H | C52: Elective Deferral to 501(c)(18)(D) plan | J52: =SUM(ROUND(D52,0),ROUND(E52,0),ROUND(F52,0),ROUND(G52,0),ROUND(H52,0),ROUND(I52,0)) | M52: Form 8880, line 2 (b)
A53: 12 | B53: K | C53: 20% Excise Tax on Excess 'golden parachute' payments | J53: =SUM(ROUND(D53,0),ROUND(E53,0),ROUND(F53,0),ROUND(G53,0),ROUND(H53,0),ROUND(I53,0)) | M53: Form 1040, Sch. 2, line 17k
A54: 12 | B54: M | C54: Uncollected Social Security tax on group-term life (former employees) | J54: =SUM(ROUND(D54,0),ROUND(E54,0),ROUND(F54,0),ROUND(G54,0),ROUND(H54,0),ROUND(I54,0)) | M54: Form 1040, Sch. 2, line 13
A55: 12 | B55: N | C55: Uncollected medicare tax on group-term life (former employees) | J55: =SUM(ROUND(D55,0),ROUND(E55,0),ROUND(F55,0),ROUND(G55,0),ROUND(H55,0),ROUND(I55,0)) | M55: Form 1040, Sch. 2, line 13
A56: 12 | B56: P | C56: Excludable moving expense reinbursements for military | J56: =SUM(ROUND(D56,0),ROUND(E56,0),ROUND(F56,0),ROUND(G56,0),ROUND(H56,0),ROUND(I56,0)) | M56: Form 1040, Sch. 2, line 14
A57: 12 | B57: Q | C57: Non Taxable Combat Pay | J57: =SUM(ROUND(D57,0),ROUND(E57,0),ROUND(F57,0),ROUND(G57,0),ROUND(H57,0),ROUND(I57,0)) | M57: Form 2441, Part 4 of Earned Income Worksheet for Line 5
A58: 12 | B58: S | C58: Elective deferral to SIMPLE IRA | J58: =SUM(ROUND(D58,0),ROUND(E58,0),ROUND(F58,0),ROUND(G58,0),ROUND(H58,0),ROUND(I58,0)) | M58: Form 8880, line 2 (b)
A59: 12 | B59: W | C59: Employer contributions to HSA. | J59: =SUM(ROUND(D59,0),ROUND(E59,0),ROUND(F59,0),ROUND(G59,0),ROUND(H59,0),ROUND(I59,0)) | M59: Form 8889, Part I, line 9 (Spouse)
A60: 13 | C60: Stat Emp / Retire / 3rd Party Sick | J60: =SUM(ROUND(D60,0),ROUND(E60,0),ROUND(F60,0),ROUND(G60,0),ROUND(H60,0),ROUND(I60,0))
A61: 14 | C61: Other | J61: =SUM(ROUND(D61,0),ROUND(E61,0),ROUND(F61,0),ROUND(G61,0),ROUND(H61,0),ROUND(I61,0))
A62: 14 | C62: Railroad retire (RRTA) compensation | J62: =SUM(ROUND(D62,0),ROUND(E62,0),ROUND(F62,0),ROUND(G62,0),ROUND(H62,0),ROUND(I62,0)) | M62: =IF(J72,"Form 8959, line 14","")
A63: 14 | C63: RRTA medicare tax withheld (see Form CT-2) | J63: =SUM(ROUND(D63,0),ROUND(E63,0),ROUND(F63,0),ROUND(G63,0),ROUND(H63,0),ROUND(I63,0))
A64: 15 | C64: State - Employer's state ID number | J64: - - -
A65: 16 | C65: State wages, tips, etc. | J65: =SUM(ROUND(D65,0),ROUND(E65,0),ROUND(F65,0),ROUND(G65,0),ROUND(H65,0),ROUND(I65,0)) | O65: =0.05*O74
A66: 17 | C66: State income tax | J66: =SUM(ROUND(D66,0),ROUND(E66,0),ROUND(F66,0),ROUND(G66,0),ROUND(H66,0),ROUND(I66,0)) | O66: =0.05*O40
A67: 18 | C67: Local wages, tips, etc. | J67: =SUM(ROUND(D67,0),ROUND(E67,0),ROUND(F67,0),ROUND(G67,0),ROUND(H67,0),ROUND(I67,0))
A68: 19 | C68: Local income tax | J68: =SUM(ROUND(D68,0),ROUND(E68,0),ROUND(F68,0),ROUND(G68,0),ROUND(H68,0),ROUND(I68,0))
A69: 20 | C69: Locality name | J69: - - -
C70: Employer count (You) | D70: =IF(D43<>"",1,0) | E70: =IF(E43<>"",1,0) | F70: =IF(F43<>"",1,0) | G70: =IF(G43<>"",1,0) | H70: =IF(H43<>"",1,0) | I70: =IF(I43<>"",1,0) | J70: =SUM(D70:I70)
C71: ="Medicare wages and tip > "&TEXT($K$34,"$0,000") | D71: =IF(D44>'8959'!$H$24,TRUE,FALSE) | E71: =IF(E44>'8959'!$H$24,TRUE,FALSE) | F71: =IF(F44>'8959'!$H$24,TRUE,FALSE) | G71: =IF(G44>'8959'!$H$24,TRUE,FALSE) | H71: =IF(H44>'8959'!$H$24,TRUE,FALSE) | I71: =IF(I44>'8959'!$H$24,TRUE,FALSE) | J71: =OR(D71:I71) | K71: =OR(J34,J71)
C72: ="RRTA > "&TEXT($K$35,"$0,000") | D72: =IF(D62>'8959'!$H$24,TRUE,FALSE) | E72: =IF(E62>'8959'!$H$24,TRUE,FALSE) | F72: =IF(F62>'8959'!$H$24,TRUE,FALSE) | G72: =IF(G62>'8959'!$H$24,TRUE,FALSE) | H72: =IF(H62>'8959'!$H$24,TRUE,FALSE) | I72: =IF(I62>'8959'!$H$24,TRUE,FALSE) | J72: =OR(D72:I72) | K72: =OR(J35,J72)
D73: =IF(AND(J43>MaxSSTax,EmployerCountSpouse=1),"Notify your employer that they withheld "&N43&" too much Social Security Tax or file Form 843, Claim for Refund and Request for Abatement.","")
C74: =IF(OR(AND(D44="",D45<>""),AND(E44="",E45<>""),AND(F44="",F45<>""),AND(G44="",G45<>"")),"CAUTION: Entering an amount into Line 6 without entering an amount into Line 5 will resutl in a tax calculation error.","")
A75: Line | B75: Code | C75: TOTALs | D75: TOTALs | E75: Used at: | K75: Excess Soc. Sec. Tax Withheld | M75: Used at:
A76: 1 | C76: Wages, tips, other compensation | D76: =SUM(J3,J40) | E76: Form 1040, Line 1.
A77: 2 | C77: Federal income tax withheld | D77: =SUM(J4,J41) | E77: Form 1040, Line 25a | M77: Only bolded amounts are used in this spreadsheet.
A78: 3 | C78: Social security wages | D78: =SUM(J5,J42) | E78: Sch. SE, Line 8a
A79: 4 | C79: Social security tax withheld | D79: =SUM(ROUND(J6,0),ROUND(J43,0)) | E79: Line 13a (CTC), Child Tax Credit W/S, Line 11 W/S, Line 6; Form 8812, Line 9 W/S, Line 1 | K79: =ROUND(SUM(K6,K43),0) | M79: Sch. 3, Line 11
A80: 5 | C80: Medicare wages and tips | D80: =SUM(J7,J44) | E80: Form 8959, Who Must File, Criterion 3; Form 8959, Additional Medicare Tax, Line 1
A81: 6 | C81: Medicare tax withheld | D81: =SUM(J8,J45) | E81: Line 13a, Child Tax Credit Worksheet, Line 14 Worksheet, Line 7; Form 8812, Line 9 W/S, Line 2; Form 8959, Additional Medicare Tax, Line 19
A82: 7 | C82: Social Security Tips | D82: =SUM(J9,J46) | E82: Form 1040, line 13b, worksheet
A83: 8 | C83: Allocated Tips | D83: =SUM(J10,J47)
A84: 10 | C84: Dependent Care Benefits | D84: =SUM(J11,J48) | E84: Form 2441, Part III, Line 12
A85: 11 | C85: Nonqualified plans | D85: =SUM(J12,J49)
A86: 12 | B86: A | C86: Uncollected Social Security Tax on Tips | D86: =SUM(J13,J50) | E86: Sch. 2, line 5
A87: 12 | B87: B | C87: Uncollected Medicare tax on Tips | D87: =SUM(J14,J51) | E87: Sch. 2, line 5
A88: 12 | B88: H | C88: Elective Deferral to 501(c)(18)(D) plan | D88: =SUM(J15,J52) | E88: Form 8880, line 2 (a) & (b)
A89: 12 | B89: K | C89: 20% Excise Tax on Excess 'golden parachute' payments | D89: =SUM(J16,J53) | E89: Form 1040, Sch. 2, line 17k
A90: 12 | B90: M | C90: Uncollected Social Security tax on group-term life (former employees) | D90: =SUM(J17,J54) | E90: Form 1040, Sch. 2, line 13
A91: 12 | B91: N | C91: Uncollected medicare tax on group-term life (former employees) | D91: =SUM(J18,J55) | E91: Form 1040, Sch. 2, line 13
A92: 12 | B92: P | C92: Excludable moving expense reinbursements for military | D92: =SUM(J19,J56) | E92: Form 1040, Sch. 1, line 14
A93: 12 | B93: Q | C93: Non Taxable Combat Pay | D93: =SUM(J20,J57) | E93: Form 1040, line 1i
A94: 12 | B94: S | C94: Elective deferral to SIMPLE IRA | D94: =SUM(J21,J58) | E94: Form 8880, line 2 (a) & (b)
A95: 12 | B95: W | C95: Employer contribution to HSA. | D95: =SUM(J22,J59) | E95: Form 8889, Part I, line 9
A96: 13 | C96: Stat Emp / Retire / 3rd Party Sick | D96: =SUM(J23,J60)
A97: 14 | C97: Other | D97: =SUM(J24,J61)
A98: 14 | C98: Railroad retire (RRTA) compensation | D98: =SUM(J25,J62) | E98: Form 8959, Additional Medicare Tax, Who Must File, Criterion 2 and 4; Line 14
A99: 14 | C99: RRTA medicare tax withheld (see Form CT-2) | D99: =SUM(J26,J63) | E99: Form 8959, Additional Medicare Tax, Line 23
A100: 15 | C100: State - Employer's state ID number | D100: - - -
...

Sheet 1099-INT
B1: Information from Form 1099-INT, Interest Income | K1: Notes
C2: =IF(Name_1st_Yours="","Enter your name(s) on the"&CHAR(10)&"sheet lableled '1040'",IF(File_Marr_Joint<>"",NameYours&CHAR(10)&" and "&NameSpouse,NameYours)) | D2: Payer #1 | E2: Payer #2 | F2: Payer #3 | G2: Payer #4 | H2: Payer #5 | K2: Date:
C3: PAYER's name
C4: PAYER's Federal ID number
C5: Account number
B6: 1 | C6: Interest income | AA6: =ROUND(D6,0) | AB6: =ROUND(E6,0) | AC6: =ROUND(F6,0) | AD6: =ROUND(G6,0) | AE6: =ROUND(H6,0)
B7: 2 | C7: Early withdrawal penalty | AA7: =ROUND(D7,0) | AB7: =ROUND(E7,0) | AC7: =ROUND(F7,0) | AD7: =ROUND(G7,0) | AE7: =ROUND(H7,0)
B8: 3 | C8: Interest on U.S. Savings Bonds & Treas. Obligations | AA8: =ROUND(D8,0) | AB8: =ROUND(E8,0) | AC8: =ROUND(F8,0) | AD8: =ROUND(G8,0) | AE8: =ROUND(H8,0)
B9: 3A | C9: Include Line 3 on Schedule B, Line 1? (Y / N) | D9: N | E9: N | F9: N | G9: N | H9: N
B10: 4 | C10: Federal income tax withheld | AA10: =ROUND(D10,0) | AB10: =ROUND(E10,0) | AC10: =ROUND(F10,0) | AD10: =ROUND(G10,0) | AE10: =ROUND(H10,0)
B11: 5 | C11: Investment expenses | AA11: =ROUND(D11,0) | AB11: =ROUND(E11,0) | AC11: =ROUND(F11,0) | AD11: =ROUND(G11,0) | AE11: =ROUND(H11,0)
B12: 6 | C12: Foreign tax paid | I12: =IF(SUM(D12:H12)>0,"Check Form 1116, Foreign Tax Credit","") | AA12: =ROUND(D12,0) | AB12: =ROUND(E12,0) | AC12: =ROUND(F12,0) | AD12: =ROUND(G12,0) | AE12: =ROUND(H12,0)
B13: 7 | C13: Foreign country or U.S. possession | AA13: =ROUND(D13,0) | AB13: =ROUND(E13,0) | AC13: =ROUND(F13,0) | AD13: =ROUND(G13,0) | AE13: =ROUND(H13,0)
B14: 8 | C14: Tax-exempt interest | AA14: =ROUND(D14,0) | AB14: =ROUND(E14,0) | AC14: =ROUND(F14,0) | AD14: =ROUND(G14,0) | AE14: =ROUND(H14,0)
B15: 9 | C15: Specified private activity bond interest | AA15: =ROUND(D15,0) | AB15: =ROUND(E15,0) | AC15: =ROUND(F15,0) | AD15: =ROUND(G15,0) | AE15: =ROUND(H15,0)
B17: 10 | C17: Market discount | AA17: =ROUND(D17,0) | AB17: =ROUND(E17,0) | AC17: =ROUND(F17,0) | AD17: =ROUND(G17,0) | AE17: =ROUND(H17,0)
B18: 11 | C18: Bond premium | AA18: =ROUND(D18,0) | AB18: =ROUND(E18,0) | AC18: =ROUND(F18,0) | AD18: =ROUND(G18,0) | AE18: =ROUND(H18,0)
B19: 12 | C19: Bond premium on Treasury obligations | AA19: =ROUND(D19,0) | AB19: =ROUND(E19,0) | AC19: =ROUND(F19,0) | AD19: =ROUND(G19,0) | AE19: =ROUND(H19,0)
B20: 13 | C20: Bond premium on tax–exempt bond | AA20: =ROUND(D20,0) | AB20: =ROUND(E20,0) | AC20: =ROUND(F20,0) | AD20: =ROUND(G20,0) | AE20: =ROUND(H20,0)
B21: 14 | C21: Tax-exempt and tax credit bond CUSIP no. | AA21: =ROUND(D21,0) | AB21: =ROUND(E21,0) | AC21: =ROUND(F21,0) | AD21: =ROUND(G21,0) | AE21: =ROUND(H21,0)
B22: 15 | C22: State
B23: 16 | C23: State identification no.
B24: 17 | C24: State tax withheld | AA24: =ROUND(D24,0) | AB24: =ROUND(E24,0) | AC24: =ROUND(F24,0) | AD24: =ROUND(G24,0) | AE24: =ROUND(H24,0)
B25: Only bolded amounts are used in this spreadsheet.
D26: =IF(OR(LEFT(D9,1)="Y",LEFT(D9,1)="y"),D8,"") | E26: =IF(OR(LEFT(E9,1)="Y",LEFT(E9,1)="y"),E8,"") | F26: =IF(OR(LEFT(F9,1)="Y",LEFT(F9,1)="y"),F8,"") | G26: =IF(OR(LEFT(G9,1)="Y",LEFT(G9,1)="y"),G8,"") | H26: =IF(OR(LEFT(H9,1)="Y",LEFT(H9,1)="y"),H8,"")
D27: =IF(D3<>"",D3,"") | E27: =IF(E3<>"",E3,"") | F27: =IF(F3<>"",F3,"") | G27: =IF(G3<>"",G3,"") | H27: =IF(H3<>"",H3,"")
D28: =IF(D4<>"", " - "&D4,"") | E28: =IF(E4<>"", " - "&E4,"") | F28: =IF(F4<>"", " - "&F4,"") | G28: =IF(G4<>"", " - "&G4,"") | H28: =IF(H4<>"", " - "&H4,"")
D29: =IF(D5<>""," - "&D5,"") | E29: =IF(E5<>""," - "&E5,"") | F29: =IF(F5<>""," - "&F5,"") | G29: =IF(G5<>""," - "&G5,"") | H29: =IF(H5<>""," - "&H5,"")
D30: =D27&D28&D29 | E30: =E27&E28&E29 | F30: =F27&F28&F29 | G30: =G27&G28&G29 | H30: =H27&H28&H29
C31: =IF(Name_1st_Yours="","Enter your name(s) on the"&CHAR(10)&"sheet lableled '1040'",IF(File_Marr_Joint<>"",NameYours&CHAR(10)&" and "&NameSpouse,NameYours)) | D31: Payer #6 | E31: Payer #7 | F31: Payer #8 | G31: Payer #9 | H31: Payer #10
C32: PAYER's name
C33: PAYER's Federal ID number
C34: Account number
B35: 1 | C35: Interest income | AA35: =ROUND(D35,0) | AB35: =ROUND(E35,0) | AC35: =ROUND(F35,0) | AD35: =ROUND(G35,0) | AE35: =ROUND(H35,0)
B36: 2 | C36: Early withdrawal penalty | AA36: =ROUND(D36,0) | AB36: =ROUND(E36,0) | AC36: =ROUND(F36,0) | AD36: =ROUND(G36,0) | AE36: =ROUND(H36,0)
B37: 3 | C37: Interest on U.S. Savings Bonds & Treas. Obligations | AA37: =ROUND(D37,0) | AB37: =ROUND(E37,0) | AC37: =ROUND(F37,0) | AD37: =ROUND(G37,0) | AE37: =ROUND(H37,0)
B38: 3A | C38: Include Line 3 on Schedule B, Line 1? (Y / N) | D38: N | E38: N | F38: N | G38: N | H38: N
B39: 4 | C39: Federal income tax withheld | AA39: =ROUND(D39,0) | AB39: =ROUND(E39,0) | AC39: =ROUND(F39,0) | AD39: =ROUND(G39,0) | AE39: =ROUND(H39,0)
B40: 5 | C40: Investment expenses | AA40: =ROUND(D40,0) | AB40: =ROUND(E40,0) | AC40: =ROUND(F40,0) | AD40: =ROUND(G40,0) | AE40: =ROUND(H40,0)
B41: 6 | C41: Foreign tax paid | I41: =IF(SUM(D41:H41)>0,"Check Form 1116, Foreign Tax Credit","") | AA41: =ROUND(D41,0) | AB41: =ROUND(E41,0) | AC41: =ROUND(F41,0) | AD41: =ROUND(G41,0) | AE41: =ROUND(H41,0)
B42: 7 | C42: Foreign country or U.S. possession | AA42: =ROUND(D42,0) | AB42: =ROUND(E42,0) | AC42: =ROUND(F42,0) | AD42: =ROUND(G42,0) | AE42: =ROUND(H42,0)
B43: 8 | C43: Tax-exempt interest | AA43: =ROUND(D43,0) | AB43: =ROUND(E43,0) | AC43: =ROUND(F43,0) | AD43: =ROUND(G43,0) | AE43: =ROUND(H43,0)
B44: 9 | C44: Specified private activity bond interest | AA44: =ROUND(D44,0) | AB44: =ROUND(E44,0) | AC44: =ROUND(F44,0) | AD44: =ROUND(G44,0) | AE44: =ROUND(H44,0)
B46: 10 | C46: Market discount | AA46: =ROUND(D46,0) | AB46: =ROUND(E46,0) | AC46: =ROUND(F46,0) | AD46: =ROUND(G46,0) | AE46: =ROUND(H46,0)
B47: 11 | C47: Bond premium | AA47: =ROUND(D47,0) | AB47: =ROUND(E47,0) | AC47: =ROUND(F47,0) | AD47: =ROUND(G47,0) | AE47: =ROUND(H47,0)
B48: 12 | C48: Bond premium on Treasury obligations | AA48: =ROUND(D48,0) | AB48: =ROUND(E48,0) | AC48: =ROUND(F48,0) | AD48: =ROUND(G48,0) | AE48: =ROUND(H48,0)
B49: 13 | C49: Bond premium on tax–exempt bond | AA49: =ROUND(D49,0) | AB49: =ROUND(E49,0) | AC49: =ROUND(F49,0) | AD49: =ROUND(G49,0) | AE49: =ROUND(H49,0)
B50: 14 | C50: Tax-exempt and tax credit bond CUSIP no. | AA50: =ROUND(D50,0) | AB50: =ROUND(E50,0) | AC50: =ROUND(F50,0) | AD50: =ROUND(G50,0) | AE50: =ROUND(H50,0)
B51: 15 | C51: State
B52: 16 | C52: State identification no.
B53: 17 | C53: State tax withheld | AA53: =ROUND(D53,0) | AB53: =ROUND(E53,0) | AC53: =ROUND(F53,0) | AD53: =ROUND(G53,0) | AE53: =ROUND(H53,0)
B54: Only bolded amounts are used in this spreadsheet.
D55: =IF(OR(LEFT(D38,1)="Y",LEFT(D38,1)="y"),D37,"") | E55: =IF(OR(LEFT(E38,1)="Y",LEFT(E38,1)="y"),E37,"") | F55: =IF(OR(LEFT(F38,1)="Y",LEFT(F38,1)="y"),F37,"") | G55: =IF(OR(LEFT(G38,1)="Y",LEFT(G38,1)="y"),G37,"") | H55: =IF(OR(LEFT(H38,1)="Y",LEFT(H38,1)="y"),H37,"")
D56: =IF(D32<>"",D32,"") | E56: =IF(E32<>"",E32,"") | F56: =IF(F32<>"",F32,"") | G56: =IF(G32<>"",G32,"") | H56: =IF(H32<>"",H32,"")
D57: =IF(D33<>"", " - "&D33,"") | E57: =IF(E33<>"", " - "&E33,"") | F57: =IF(F33<>"", " - "&F33,"") | G57: =IF(G33<>"", " - "&G33,"") | H57: =IF(H33<>"", " - "&H33,"")
D58: =IF(D34<>""," - "&D34,"") | E58: =IF(E34<>""," - "&E34,"") | F58: =IF(F34<>""," - "&F34,"") | G58: =IF(G34<>""," - "&G34,"") | H58: =IF(H34<>""," - "&H34,"")
D59: =D56&D57&D58 | E59: =E56&E57&E58 | F59: =F56&F57&F58 | G59: =G56&G57&G58 | H59: =H56&H57&H58
B60: Information from Form 1099-INT, Interest Income
C61: =IF(Name_1st_Yours="","Enter your name(s) on the"&CHAR(10)&"sheet lableled '1040'",IF(File_Marr_Joint<>"",NameYours&CHAR(10)&" and "&NameSpouse,NameYours)) | D61: Payer #11 | E61: Payer #12 | F61: Payer #13 | G61: Payer #14 | H61: Payer #15 | I61: Total | J61: Used at:
C62: PAYER's name
C63: PAYER's Federal ID number
C64: Account number | J64: =IF(AND(ForeignTaxPaid_INT<>"",ForeignTaxPaid_INT>0),"Check Form 1116, Foreign Tax Credit","")
B65: 1 | C65: Interest income | I65: =ROUND(SUM(D6:H6,D35:H35,D65:H65),0) | J65: Sch. B, Line 1 | AA65: =ROUND(D65,0) | AB65: =ROUND(E65,0) | AC65: =ROUND(F65,0) | AD65: =ROUND(G65,0) | AE65: =ROUND(H65,0)
B66: 2 | C66: Early withdrawal penalty | I66: =ROUND(SUM(D7:H7,D36:H36,D66:H66),0) | J66: Form 1040, Sch. 1, Line 18 | AA66: =ROUND(D66,0) | AB66: =ROUND(E66,0) | AC66: =ROUND(F66,0) | AD66: =ROUND(G66,0) | AE66: =ROUND(H66,0)
B67: 3 | C67: Interest on U.S. Savings Bonds & Treas. Obligations | I67: =ROUND(SUM(D8:H8,D37:H37,D67:H67),0) | J67: Sch. B, Line 1 (If line 3A is "Y") | AA67: =ROUND(D67,0) | AB67: =ROUND(E67,0) | AC67: =ROUND(F67,0) | AD67: =ROUND(G67,0) | AE67: =ROUND(H67,0)
B68: 3A | C68: Include Line 3 on Schedule B, Line 1? (Y / N) | D68: N | E68: N | F68: N | G68: N | H68: N
B69: 4 | C69: Federal income tax withheld | I69: =ROUND(SUM(D10:H10,D39:H39,D69:H69),0) | J69: Form 1040, Line 25b | AA69: =ROUND(D69,0) | AB69: =ROUND(E69,0) | AC69: =ROUND(F69,0) | AD69: =ROUND(G69,0) | AE69: =ROUND(H69,0)
B70: 5 | C70: Investment expenses | I70: =ROUND(SUM(D11:H11,D40:H40,D70:H70),0) | J70: Consideration (by you) in Sch. A, Line 9 | AA70: =ROUND(D70,0) | AB70: =ROUND(E70,0) | AC70: =ROUND(F70,0) | AD70: =ROUND(G70,0) | AE70: =ROUND(H70,0)
B71: 6 | C71: Foreign tax paid | I71: =ROUND(SUM(D12:H12,D41:H41,D71:H71),0) | J71: Sch. 3, Line 48 OR Form 1116 (Cell A8) | AA71: =ROUND(D71,0) | AB71: =ROUND(E71,0) | AC71: =ROUND(F71,0) | AD71: =ROUND(G71,0) | AE71: =ROUND(H71,0)
B72: 7 | C72: Foreign country or U.S. possession | I72: =" - - - -" | J72: =IF(ForeignTaxPaid_INT>0,"Check Form 1116, Foreign Tax Credit","") | AA72: =ROUND(D72,0) | AB72: =ROUND(E72,0) | AC72: =ROUND(F72,0) | AD72: =ROUND(G72,0) | AE72: =ROUND(H72,0)
B73: 8 | C73: Tax-exempt interest | I73: =ROUND(SUM(D14:H14,D43:H43,D73:H73),0) | J73: Form 1040, Line 2a | AA73: =ROUND(D73,0) | AB73: =ROUND(E73,0) | AC73: =ROUND(F73,0) | AD73: =ROUND(G73,0) | AE73: =ROUND(H73,0)
B74: 9 | C74: Specified private activity bond interest | I74: =ROUND(SUM(D15:H15,D44:H44,D74:H74),0) | J74: Form 6251, Line 2g | AA74: =ROUND(D74,0) | AB74: =ROUND(E74,0) | AC74: =ROUND(F74,0) | AD74: =ROUND(G74,0) | AE74: =ROUND(H74,0)
I75: =ROUND(SUM(D16:H16,D45:H45,D75:H75),0)
B76: 10 | C76: Market discount | I76: =ROUND(SUM(D17:H17,D46:H46,D76:H76),0) | J76: Sch. B, Line 1 | AA76: =ROUND(D76,0) | AB76: =ROUND(E76,0) | AC76: =ROUND(F76,0) | AD76: =ROUND(G76,0) | AE76: =ROUND(H76,0)
B77: 11 | C77: Bond premium | I77: =ROUND(SUM(D18:H18,D47:H47,D77:H77),0) | AA77: =ROUND(D77,0) | AB77: =ROUND(E77,0) | AC77: =ROUND(F77,0) | AD77: =ROUND(G77,0) | AE77: =ROUND(H77,0)
B78: 12 | C78: Bond premium on Treasury obligations | I78: =ROUND(SUM(D19:H19,D48:H48,D78:H78),0) | AA78: =ROUND(D78,0) | AB78: =ROUND(E78,0) | AC78: =ROUND(F78,0) | AD78: =ROUND(G78,0) | AE78: =ROUND(H78,0)
B79: 13 | C79: Bond premium on tax–exempt bond | I79: =" - - - -" | AA79: =ROUND(D79,0) | AB79: =ROUND(E79,0) | AC79: =ROUND(F79,0) | AD79: =ROUND(G79,0) | AE79: =ROUND(H79,0)
B80: 14 | C80: Tax-exempt and tax credit bond CUSIP no. | I80: =" - - - -" | AA80: =ROUND(D80,0) | AB80: =ROUND(E80,0) | AC80: =ROUND(F80,0) | AD80: =ROUND(G80,0) | AE80: =ROUND(H80,0)
B81: 15 | C81: State | I81: =" - - - -"
B82: 16 | C82: State identification no. | I82: =" - - - -"
B83: 17 | C83: State tax withheld | I83: =ROUND(SUM(D24:H24,D53:H53,D83:H83),0) | J83: Sch. A, Line 5a and Form 8960, Line 9b | AA83: =ROUND(D83,0) | AB83: =ROUND(E83,0) | AC83: =ROUND(F83,0) | AD83: =ROUND(G83,0) | AE83: =ROUND(H83,0)
B84: Only bolded amounts are used in this spreadsheet.
D85: =IF(OR(LEFT(D68,1)="Y",LEFT(D68,1)="y"),D67,"") | E85: =IF(OR(LEFT(E68,1)="Y",LEFT(E68,1)="y"),E67,"") | F85: =IF(OR(LEFT(F68,1)="Y",LEFT(F68,1)="y"),F67,"") | G85: =IF(OR(LEFT(G68,1)="Y",LEFT(G68,1)="y"),G67,"") | H85: =IF(OR(LEFT(H68,1)="Y",LEFT(H68,1)="y"),H67,"")
D86: =IF(D62<>"",D62,"") | E86: =IF(E62<>"",E62,"") | F86: =IF(F62<>"",F62,"") | G86: =IF(G62<>"",G62,"") | H86: =IF(H62<>"",H62,"")
D87: =IF(D63<>"", " - "&D63,"") | E87: =IF(E63<>"", " - "&E63,"") | F87: =IF(F63<>"", " - "&F63,"") | G87: =IF(G63<>"", " - "&G63,"") | H87: =IF(H63<>"", " - "&H63,"")
D88: =IF(D64<>""," - "&D64,"") | E88: =IF(E64<>""," - "&E64,"") | F88: =IF(F64<>""," - "&F64,"") | G88: =IF(G64<>""," - "&G64,"") | H88: =IF(H64<>""," - "&H64,"")
D89: =D86&D87&D88 | E89: =E86&E87&E88 | F89: =F86&F87&F88 | G89: =G86&G87&G88 | H89: =H86&H87&H88
C93: Table of Contents

Sheet 1099-DIV
B1: Information from Form 1099-DIV, Dividends and Distributions | K1: Notes
C2: =IF(Name_1st_Yours="","Enter your name(s) on the"&CHAR(10)&"sheet labeled '1040'",Names) | D2: Payer #1 | E2: Payer #2 | F2: Payer #3 | G2: Payer #4 | H2: Payer #5 | K2: Date:
C3: PAYER's name
C4: PAYER's Federal ID number
C5: Account number
B6: 1a | C6: Total ordinary dividends | I6: =IF(I26,"Error: All qualified dividends must be included in","") | AA6: =B6 | AB6: =ROUND(D6,2) | AC6: =ROUND(E6,2) | AD6: =ROUND(F6,2) | AE6: =ROUND(G6,2) | AF6: =ROUND(H6,2)
B7: 1b | C7: Qualified dividends | I7: =IF(I26,"the Total ordinary dividend amount.","") | AA7: =B7 | AB7: =ROUND(D7,2) | AC7: =ROUND(E7,2) | AD7: =ROUND(F7,2) | AE7: =ROUND(G7,2) | AF7: =ROUND(H7,2)
B8: 2a | C8: Total capital gain distr. | AA8: =B8 | AB8: =ROUND(D8,0) | AC8: =ROUND(E8,0) | AD8: =ROUND(F8,0) | AE8: =ROUND(G8,0) | AF8: =ROUND(H8,0)
B9: 2b | C9: Unrecap. Sec. 1250 gain | AA9: =B9 | AB9: =ROUND(D9,0) | AC9: =ROUND(E9,0) | AD9: =ROUND(F9,0) | AE9: =ROUND(G9,0) | AF9: =ROUND(H9,0)
B10: 2c | C10: Section 1202 gain | AA10: =B10 | AB10: =ROUND(D10,2) | AC10: =ROUND(E10,2) | AD10: =ROUND(F10,2) | AE10: =ROUND(G10,2) | AF10: =ROUND(H10,2)
B11: 2d | C11: Collectibles (28%) gain | AA11: =B11 | AB11: =ROUND(D11,2) | AC11: =ROUND(E11,2) | AD11: =ROUND(F11,2) | AE11: =ROUND(G11,2) | AF11: =ROUND(H11,2)
B12: 3 | C12: Nondividend distributions | AA12: =B12 | AB12: =ROUND(D12,0) | AC12: =ROUND(E12,0) | AD12: =ROUND(F12,0) | AE12: =ROUND(G12,0) | AF12: =ROUND(H12,0)
B13: 4 | C13: Federal income tax withheld | AA13: =B13 | AB13: =ROUND(D13,2) | AC13: =ROUND(E13,2) | AD13: =ROUND(F13,2) | AE13: =ROUND(G13,2) | AF13: =ROUND(H13,2)
B14: 5 | C14: Section 199A dividends | AA14: =B14 | AB14: =ROUND(D14,2) | AC14: =ROUND(E14,2) | AD14: =ROUND(F14,2) | AE14: =ROUND(G14,2) | AF14: =ROUND(H14,2)
B15: 6 | C15: Investment expenses | AA15: =B15 | AB15: =ROUND(D15,0) | AC15: =ROUND(E15,0) | AD15: =ROUND(F15,0) | AE15: =ROUND(G15,0) | AF15: =ROUND(H15,0)
B16: 7 | C16: Foreign tax paid | I16: =IF(SUM(D16:H16)>0,"Check Form 1116, Foreign Tax Credit","") | AA16: =B16 | AB16: =ROUND(D16,2) | AC16: =ROUND(E16,2) | AD16: =ROUND(F16,2) | AE16: =ROUND(G16,2) | AF16: =ROUND(H16,2)
B17: 8 | C17: Foreign country or U.S. possession | AA17: =B17
B18: 9 | C18: Cash liquidation distributions | AA18: =B18 | AB18: =ROUND(D18,0) | AC18: =ROUND(E18,0) | AD18: =ROUND(F18,0) | AE18: =ROUND(G18,0) | AF18: =ROUND(H18,0)
B19: 10 | C19: Noncash liquidation distributions | AA19: =B19 | AB19: =ROUND(D19,0) | AC19: =ROUND(E19,0) | AD19: =ROUND(F19,0) | AE19: =ROUND(G19,0) | AF19: =ROUND(H19,0)
B20: 11 | C20: FATCA filing requirement | AA20: =B20 | AB20: =ROUND(D20,2) | AC20: =ROUND(E20,2) | AD20: =ROUND(F20,2) | AE20: =ROUND(G20,2) | AF20: =ROUND(H20,2)
B21: 12 | C21: Exempt-interest dividends | AA21: =B21 | AB21: =ROUND(D21,2) | AC21: =ROUND(E21,2) | AD21: =ROUND(F21,2) | AE21: =ROUND(G21,2) | AF21: =ROUND(H21,2)
B22: 13 | C22: Specified private activity bond interest dividends | AA22: =B22 | AB22: =ROUND(D22,2) | AC22: =ROUND(E22,2) | AD22: =ROUND(F22,2) | AE22: =ROUND(G22,2) | AF22: =ROUND(H22,2)
B23: 14 | C23: State | AA23: =B23
B24: 15 | C24: State identification no. | AA24: =B24
B25: 16 | C25: State tax withheld | AA25: =B25 | AB25: =ROUND(D25,2) | AC25: =ROUND(E25,2) | AD25: =ROUND(F25,2) | AE25: =ROUND(G25,2) | AF25: =ROUND(H25,2)
B26: Only bolded amounts are used in this spreadsheet. | D26: =D7>D6 | E26: =E7>E6 | F26: =F7>F6 | G26: =G7>G6 | H26: =H7>H6 | I26: =OR(D26:H26)
D27: =IF(D3<>"",D3,"") | E27: =IF(E3<>"",E3,"") | F27: =IF(F3<>"",F3,"") | G27: =IF(G3<>"",G3,"") | H27: =IF(H3<>"",H3,"")
D28: =IF(D4<>"", " - "&D4,"") | E28: =IF(E4<>"", " - "&E4,"") | F28: =IF(F4<>"", " - "&F4,"") | G28: =IF(G4<>"", " - "&G4,"") | H28: =IF(H4<>"", " - "&H4,"")
D29: =IF(D5<>""," - "&D5,"") | E29: =IF(E5<>""," - "&E5,"") | F29: =IF(F5<>""," - "&F5,"") | G29: =IF(G5<>""," - "&G5,"") | H29: =IF(H5<>""," - "&H5,"")
D30: =IF(D6="","",D27&D28&D29) | E30: =IF(E6="","",E27&E28&E29) | F30: =IF(F6="","",F27&F28&F29) | G30: =IF(G6="","",G27&G28&G29) | H30: =IF(H6="","",H27&H28&H29)
C31: =IF(Name_1st_Yours="","Enter your name(s) on the"&CHAR(10)&"sheet labeled '1040'",Names) | D31: Payer #6 | E31: Payer #7 | F31: Payer #8 | G31: Payer #9 | H31: Payer #10
C32: PAYER's name
C33: PAYER's Federal ID number
C34: Account number
B35: 1a | C35: Total ordinary dividends | I35: =IF(I55,"Error: All qualified dividends must be included in","") | AA35: =B35 | AB35: =ROUND(D35,2) | AC35: =ROUND(E35,2) | AD35: =ROUND(F35,2) | AE35: =ROUND(G35,2) | AF35: =ROUND(H35,2)
B36: 1b | C36: Qualified dividends | I36: =IF(I55,"the Total ordinary dividend amount.","") | AA36: =B36 | AB36: =ROUND(D36,2) | AC36: =ROUND(E36,2) | AD36: =ROUND(F36,2) | AE36: =ROUND(G36,2) | AF36: =ROUND(H36,2)
B37: 2a | C37: Total capital gain distr. | AA37: =B37 | AB37: =ROUND(D37,0) | AC37: =ROUND(E37,0) | AD37: =ROUND(F37,0) | AE37: =ROUND(G37,0) | AF37: =ROUND(H37,0)
B38: 2b | C38: Unrecap. Sec. 1250 gain | AA38: =B38 | AB38: =ROUND(D38,0) | AC38: =ROUND(E38,0) | AD38: =ROUND(F38,0) | AE38: =ROUND(G38,0) | AF38: =ROUND(H38,0)
B39: 2c | C39: Section 1202 gain | AA39: =B39 | AB39: =ROUND(D39,2) | AC39: =ROUND(E39,2) | AD39: =ROUND(F39,2) | AE39: =ROUND(G39,2) | AF39: =ROUND(H39,2)
B40: 2d | C40: Collectibles (28%) gain | AA40: =B40 | AB40: =ROUND(D40,2) | AC40: =ROUND(E40,2) | AD40: =ROUND(F40,2) | AE40: =ROUND(G40,2) | AF40: =ROUND(H40,2)
B41: 3 | C41: Nondividend distributions | AA41: =B41 | AB41: =ROUND(D41,0) | AC41: =ROUND(E41,0) | AD41: =ROUND(F41,0) | AE41: =ROUND(G41,0) | AF41: =ROUND(H41,0)
B42: 4 | C42: Federal income tax withheld | AA42: =B42 | AB42: =ROUND(D42,2) | AC42: =ROUND(E42,2) | AD42: =ROUND(F42,2) | AE42: =ROUND(G42,2) | AF42: =ROUND(H42,2)
B43: 5 | C43: Section 199A dividends | AA43: =B43 | AB43: =ROUND(D43,2) | AC43: =ROUND(E43,2) | AD43: =ROUND(F43,2) | AE43: =ROUND(G43,2) | AF43: =ROUND(H43,2)
B44: 6 | C44: Investment expenses | AA44: =B44 | AB44: =ROUND(D44,0) | AC44: =ROUND(E44,0) | AD44: =ROUND(F44,0) | AE44: =ROUND(G44,0) | AF44: =ROUND(H44,0)
B45: 7 | C45: Foreign tax paid | I45: =IF(SUM(D45:H45)>0,"Check Form 1116, Foreign Tax Credit","") | AA45: =B45 | AB45: =ROUND(D45,2) | AC45: =ROUND(E45,2) | AD45: =ROUND(F45,2) | AE45: =ROUND(G45,2) | AF45: =ROUND(H45,2)
B46: 8 | C46: Foreign country or U.S. possession | AA46: =B46
B47: 9 | C47: Cash liquidation distributions | AA47: =B47 | AB47: =ROUND(D47,0) | AC47: =ROUND(E47,0) | AD47: =ROUND(F47,0) | AE47: =ROUND(G47,0) | AF47: =ROUND(H47,0)
B48: 10 | C48: Noncash liquidation distributions | AA48: =B48 | AB48: =ROUND(D48,0) | AC48: =ROUND(E48,0) | AD48: =ROUND(F48,0) | AE48: =ROUND(G48,0) | AF48: =ROUND(H48,0)
B49: 11 | C49: FATCA filing requirement | AA49: =B49 | AB49: =ROUND(D49,2) | AC49: =ROUND(E49,2) | AD49: =ROUND(F49,2) | AE49: =ROUND(G49,2) | AF49: =ROUND(H49,2)
B50: 12 | C50: Exempt-interest dividends | AA50: =B50 | AB50: =ROUND(D50,2) | AC50: =ROUND(E50,2) | AD50: =ROUND(F50,2) | AE50: =ROUND(G50,2) | AF50: =ROUND(H50,2)
B51: 13 | C51: Specified private activity bond interest dividends | AA51: =B51 | AB51: =ROUND(D51,2) | AC51: =ROUND(E51,2) | AD51: =ROUND(F51,2) | AE51: =ROUND(G51,2) | AF51: =ROUND(H51,2)
B52: 14 | C52: State | AA52: =B52
B53: 15 | C53: State identification no. | AA53: =B53
B54: 16 | C54: State tax withheld | AA54: =B54 | AB54: =ROUND(D54,2) | AC54: =ROUND(E54,2) | AD54: =ROUND(F54,2) | AE54: =ROUND(G54,2) | AF54: =ROUND(H54,2)
B55: Only bolded amounts are used in this spreadsheet. | D55: =D36>D35 | E55: =E36>E35 | F55: =F36>F35 | G55: =G36>G35 | H55: =H36>H35 | I55: =OR(D55:H55)
D56: =IF(D32<>"",D32,"") | E56: =IF(E32<>"",E32,"") | F56: =IF(F32<>"",F32,"") | G56: =IF(G32<>"",G32,"") | H56: =IF(H32<>"",H32,"")
D57: =IF(D33<>"", " - "&D33,"") | E57: =IF(E33<>"", " - "&E33,"") | F57: =IF(F33<>"", " - "&F33,"") | G57: =IF(G33<>"", " - "&G33,"") | H57: =IF(H33<>"", " - "&H33,"")
D58: =IF(D34<>""," - "&D34,"") | E58: =IF(E34<>""," - "&E34,"") | F58: =IF(F34<>""," - "&F34,"") | G58: =IF(G34<>""," - "&G34,"") | H58: =IF(H34<>""," - "&H34,"")
D59: =IF(D35="","",D56&D57&D58) | E59: =IF(E35="","",E56&E57&E58) | F59: =IF(F35="","",F56&F57&F58) | G59: =IF(G35="","",G56&G57&G58) | H59: =IF(H35="","",H56&H57&H58)
C60: =IF(Name_1st_Yours="","Enter your name(s) on the"&CHAR(10)&"sheet labeled '1040'",Names) | D60: Payer #11 | E60: Payer #12 | F60: Payer #13 | G60: Payer #14 | H60: Payer #15
C61: PAYER's name
C62: PAYER's Federal ID number
C63: Account number
B64: 1a | C64: Total ordinary dividends | I64: =IF(I84,"Error: All qualified dividends must be included in","") | AA64: =B64 | AB64: =ROUND(D64,2) | AC64: =ROUND(E64,2) | AD64: =ROUND(F64,2) | AE64: =ROUND(G64,2) | AF64: =ROUND(H64,2)
B65: 1b | C65: Qualified dividends | I65: =IF(I84,"the Total ordinary dividend amount.","") | AA65: =B65 | AB65: =ROUND(D65,2) | AC65: =ROUND(E65,2) | AD65: =ROUND(F65,2) | AE65: =ROUND(G65,2) | AF65: =ROUND(H65,2)
B66: 2a | C66: Total capital gain distr. | AA66: =B66 | AB66: =ROUND(D66,0) | AC66: =ROUND(E66,0) | AD66: =ROUND(F66,0) | AE66: =ROUND(G66,0) | AF66: =ROUND(H66,0)
B67: 2b | C67: Unrecap. Sec. 1250 gain | AA67: =B67 | AB67: =ROUND(D67,0) | AC67: =ROUND(E67,0) | AD67: =ROUND(F67,0) | AE67: =ROUND(G67,0) | AF67: =ROUND(H67,0)
B68: 2c | C68: Section 1202 gain | AA68: =B68 | AB68: =ROUND(D68,2) | AC68: =ROUND(E68,2) | AD68: =ROUND(F68,2) | AE68: =ROUND(G68,2) | AF68: =ROUND(H68,2)
B69: 2d | C69: Collectibles (28%) gain | AA69: =B69 | AB69: =ROUND(D69,2) | AC69: =ROUND(E69,2) | AD69: =ROUND(F69,2) | AE69: =ROUND(G69,2) | AF69: =ROUND(H69,2)
B70: 3 | C70: Nondividend distributions | AA70: =B70 | AB70: =ROUND(D70,0) | AC70: =ROUND(E70,0) | AD70: =ROUND(F70,0) | AE70: =ROUND(G70,0) | AF70: =ROUND(H70,0)
B71: 4 | C71: Federal income tax withheld | AA71: =B71 | AB71: =ROUND(D71,2) | AC71: =ROUND(E71,2) | AD71: =ROUND(F71,2) | AE71: =ROUND(G71,2) | AF71: =ROUND(H71,2)
B72: 5 | C72: Section 199A dividends | AA72: =B72 | AB72: =ROUND(D72,2) | AC72: =ROUND(E72,2) | AD72: =ROUND(F72,2) | AE72: =ROUND(G72,2) | AF72: =ROUND(H72,2)
B73: 6 | C73: Investment expenses | AA73: =B73 | AB73: =ROUND(D73,0) | AC73: =ROUND(E73,0) | AD73: =ROUND(F73,0) | AE73: =ROUND(G73,0) | AF73: =ROUND(H73,0)
B74: 7 | C74: Foreign tax paid | I74: =IF(SUM(D74:H74)>0,"Check Form 1116, Foreign Tax Credit","") | AA74: =B74 | AB74: =ROUND(D74,2) | AC74: =ROUND(E74,2) | AD74: =ROUND(F74,2) | AE74: =ROUND(G74,2) | AF74: =ROUND(H74,2)
B75: 8 | C75: Foreign country or U.S. possession | AA75: =B75
B76: 9 | C76: Cash liquidation distributions | AA76: =B76 | AB76: =ROUND(D76,0) | AC76: =ROUND(E76,0) | AD76: =ROUND(F76,0) | AE76: =ROUND(G76,0) | AF76: =ROUND(H76,0)
B77: 10 | C77: Noncash liquidation distributions | AA77: =B77 | AB77: =ROUND(D77,0) | AC77: =ROUND(E77,0) | AD77: =ROUND(F77,0) | AE77: =ROUND(G77,0) | AF77: =ROUND(H77,0)
B78: 11 | C78: FATCA filing requirement | AA78: =B78 | AB78: =ROUND(D78,2) | AC78: =ROUND(E78,2) | AD78: =ROUND(F78,2) | AE78: =ROUND(G78,2) | AF78: =ROUND(H78,2)
B79: 12 | C79: Exempt-interest dividends | AA79: =B79 | AB79: =ROUND(D79,2) | AC79: =ROUND(E79,2) | AD79: =ROUND(F79,2) | AE79: =ROUND(G79,2) | AF79: =ROUND(H79,2)
B80: 13 | C80: Specified private activity bond interest dividends | AA80: =B80 | AB80: =ROUND(D80,2) | AC80: =ROUND(E80,2) | AD80: =ROUND(F80,2) | AE80: =ROUND(G80,2) | AF80: =ROUND(H80,2)
B81: 14 | C81: State | AA81: =B81
B82: 15 | C82: State identification no. | AA82: =B82
B83: 16 | C83: State tax withheld | AA83: =B83 | AB83: =ROUND(D83,2) | AC83: =ROUND(E83,2) | AD83: =ROUND(F83,2) | AE83: =ROUND(G83,2) | AF83: =ROUND(H83,2)
B84: Only bolded amounts are used in this spreadsheet. | D84: =D65>D64 | E84: =E65>E64 | F84: =F65>F64 | G84: =G65>G64 | H84: =H65>H64 | I84: =OR(D84:H84)
D85: =IF(D61<>"",D61,"") | E85: =IF(E61<>"",E61,"") | F85: =IF(F61<>"",F61,"") | G85: =IF(G61<>"",G61,"") | H85: =IF(H61<>"",H61,"")
D86: =IF(D62<>"", " - "&D62,"") | E86: =IF(E62<>"", " - "&E62,"") | F86: =IF(F62<>"", " - "&F62,"") | G86: =IF(G62<>"", " - "&G62,"") | H86: =IF(H62<>"", " - "&H62,"")
D87: =IF(D63<>""," - "&D63,"") | E87: =IF(E63<>""," - "&E63,"") | F87: =IF(F63<>""," - "&F63,"") | G87: =IF(G63<>""," - "&G63,"") | H87: =IF(H63<>""," - "&H63,"")
D88: =IF(D64="","",D85&D86&D87) | E88: =IF(E64="","",E85&E86&E87) | F88: =IF(F64="","",F85&F86&F87) | G88: =IF(G64="","",G85&G86&G87) | H88: =IF(H64="","",H85&H86&H87)
C89: =IF(Name_1st_Yours="","Enter your name(s) on the"&CHAR(10)&"sheet labeled '1040'",Names) | D89: Payer #16 | E89: Payer #17 | F89: Payer #18 | G89: Payer #19 | H89: Total | I89: Used at:
C90: PAYER's name
C91: PAYER's Federal ID number
C92: Account number | I92: =SUM(ForeignTaxPaid_INT,ForeignTaxPaid_DIV)
B93: 1a | C93: Total ordinary dividends | H93: =ROUND(SUM(D6:H6,D35:H35,D64:H64,D93:G93),0) | I93: =IF(I113,"Error: All qualified dividends must be included in","Sch. B, Line 5") | AA93: =B93 | AB93: =ROUND(D93,2) | AC93: =ROUND(E93,2) | AD93: =ROUND(F93,2) | AE93: =ROUND(G93,2)
B94: 1b | C94: Qualified dividends | H94: =ROUND(SUM(D7:H7,D36:H36,D65:H65,D94:G94),0) | I94: =IF(I113,"the Total ordinary dividend amount.","Form 1040, Line 3a and 3b") | AA94: =B94 | AB94: =ROUND(D94,2) | AC94: =ROUND(E94,2) | AD94: =ROUND(F94,2) | AE94: =ROUND(G94,2)
B95: 2a | C95: Total capital gain distr. | H95: =ROUND(SUM(D8:H8,D37:H37,D66:H66,D95:G95),0) | I95: Sch. D, Line 13 | AA95: =B95 | AB95: =ROUND(D95,0) | AC95: =ROUND(E95,0) | AD95: =ROUND(F95,0) | AE95: =ROUND(G95,0)
B96: 2b | C96: Unrecap. Sec. 1250 gain | H96: =ROUND(SUM(D9:H9,D38:H38,D67:H67,D96:G96),0) | AA96: =B96 | AB96: =ROUND(D96,0) | AC96: =ROUND(E96,0) | AD96: =ROUND(F96,0) | AE96: =ROUND(G96,0)
B97: 2c | C97: Section 1202 gain | H97: =SUM(AB10:AF10,AB39:AF39,AB68:AF68,AB97:AE97) | AA97: =B97 | AB97: =ROUND(D97,2) | AC97: =ROUND(E97,2) | AD97: =ROUND(F97,2) | AE97: =ROUND(G97,2)
B98: 2d | C98: Collectibles (28%) gain | H98: =ROUND(SUM(D11:H11,D40:H40,D69:H69,D98:G98),0) | I98: Sch. D. WS, 28% Rate Gain WS, Line 4 | AA98: =B98 | AB98: =ROUND(D98,2) | AC98: =ROUND(E98,2) | AD98: =ROUND(F98,2) | AE98: =ROUND(G98,2)
B99: 3 | C99: Nondividend distributions | H99: =ROUND(SUM(D12:H12,D41:H41,D70:H70,D99:G99),0) | AA99: =B99 | AB99: =ROUND(D99,0) | AC99: =ROUND(E99,0) | AD99: =ROUND(F99,0) | AE99: =ROUND(G99,0)
B100: 4 | C100: Federal income tax withheld | H100: =ROUND(SUM(D13:H13,D42:H42,D71:H71,D100:G100),0) | I100: 1040, line 25b | AA100: =B100 | AB100: =ROUND(D100,2) | AC100: =ROUND(E100,2) | AD100: =ROUND(F100,2) | AE100: =ROUND(G100,2)
...

Sheet 1099-G
B1: Form 1099-G, Certain Government Payments | E1: =IF(FALSE,"After Form 1040 and Schedule 1 are complete,"&CHAR(10)&" be sure to review 'Sch. 1 Line 8 WS', line 1.",IF(FALSE,"'Sch. 1 Line 8 WS', line 1, has been Updated.","")) | M1: Notes
C2: =IF(Name_1st_Yours="","Enter your name on the"&CHAR(10)&"sheet labeled '1040'",NameYours) | D2: Payer #1 | E2: Payer #2 | F2: Payer #3 | G2: Payer #4 | H2: Payer #5 | I2: Payer #6 | J2: Your Total | K2: Used at:
C3: PAYER's name
C4: PAYER's TIN
C5: Account number
B6: 1 | C6: Unemployment Compensation | J6: =ROUND(SUM(D6:I6),0) | K6: Sch. 1 Line 8 WS', line 7
B7: 2 | C7: State or local income tax refunds, credits, offsets | J7: =ROUND(SUM(D7:I7),0) | K7: =IF(Needs_SALT," See sheet labeled"," 'Sch. 1, Line 1 (SALT)', line 1 [State & local tax]")
B8: 3 | C8: Box 2 amount is for tax year | J8: --- | K8: =IF(Needs_SALT,"'Sch. 1, Line 1 (SALT)'. (State & Local Tax)","")
B9: 4 | C9: Federal income tax withheld | J9: =ROUND(SUM(D9:I9),0)
B10: 5 | C10: RTAA Payments | J10: =ROUND(SUM(D10:I10),0)
B11: 6 | C11: Taxable grants | J11: =ROUND(SUM(D11:I11),0)
B12: 7a | C12: Agriculture payments - Disaster payments | J12: =ROUND(SUM(D12:I12),0)
B13: 7b | C13: Agriculture payments - Other payments | J13: =ROUND(SUM(D13:I13),0) | K13: =AND(D13="",E13="",F13="",G13="",J13="")
B14: 8 | C14: Check if box 2 is trade or business income
B15: 9 | C15: Market gain | J15: =ROUND(SUM(D15:I15),0) | K15: =AND(D15="",E15="",F15="",G15="",J15="")
B16: 10a | C16: State
B17: 10b | C17: State identification no.
B18: 11 | C18: State income tax withheld | J18: =ROUND(SUM(D18:I18),0)
B19: Only bolded amounts are used in this spreadsheet.
J20: =IF(J3<>"",J3,"")
C21: =IF(Name_1st_Sp="","Enter your spouse's name on"&CHAR(10)&"the sheet labeled '1040'",NameSpouse) | D21: Payer #1 | E21: Payer #2 | F21: Payer #3 | G21: Payer #4 | H21: Payer #5 | I21: Spouse Total | J21: Total | K21: Used at:
C22: PAYER's name
C23: PAYER's Federal ID number
C24: Account number | K24: =SUM(ForeignTaxPaid_INT,ForeignTaxPaid_DIV)
B25: 1 | C25: Unemployment Compensation | I25: =ROUND(SUM(D25:G25),0) | J25: =SUM(UCE_You,UCE_Spouse) | K25: Sch. 1 Line 8 WS', line 8 / Sch. 1, line 7
B26: 2 | C26: State or local income tax refunds, credits, offsets | I26: =ROUND(SUM(D26:G26),0) | J26: =SUM(J7,I26) | K26: =IF(Needs_SALT," See sheet labeled"," 'Sch. 1, Line 1 (SALT)', line 1 [State & local tax]")
B27: 3 | C27: Box 2 amount is for tax year | I27: --- | J27: --- | K27: =IF(Needs_SALT," 'Sch. 1, Line 1 (SALT)'. (State & Local Tax)","")
B28: 4 | C28: Federal income tax withheld | I28: =ROUND(SUM(D28:G28),0) | J28: =SUM(J9,I28) | K28: 1040, line 25b
B29: 5 | C29: RTAA Payments | I29: =ROUND(SUM(D29:G29),0) | J29: =SUM(J10,I29) | K29: Sch. 1, line 8z
B30: 6 | C30: Taxable grants | I30: =ROUND(SUM(D30:G30),0) | J30: =SUM(J11,I30) | K30: Sch. 1, line 8z
B31: 7a | C31: Agriculture payments - Disaster payments | I31: =ROUND(SUM(D31:G31),0) | J31: =SUM(J12,I31) | K31: Sch. F, Line 6a
B32: 7b | C32: Agriculture payments - Other payments | I32: =ROUND(SUM(D32:G32),0) | J32: =SUM(J13,I32) | K32: Sch. F, Line 4a
B33: 8 | C33: Check if box 2 is trade or business income | K33: =AND(K13,D31="",E31="",F31="",G31="")
B34: 9 | C34: Market gain | I34: =ROUND(SUM(D34:G34),0) | J34: =SUM(J15,I34) | K34: Sch. F, Line 4a
B35: 10a | C35: State | K35: =AND(K15,D33="",E33="",F33="",G33="")
B36: 10b | C36: State identification no.
B37: 11 | C37: State income tax withheld | I37: =ROUND(SUM(D37:G37),0) | J37: =SUM(J18,I37) | K37: Sch. A, Line 5a
B38: Only bolded amounts are used in this spreadsheet.
C43: Table of Contents

Sheet 1099-MISC
C3: This form has yet to be implemented.
C5: Download and follow IRS instructions for where the information and amounts should be entered.
C7: NOTE: | D7: Amounts of more than $600 will NOT typically be reported on Schedule 1 (Form 1040), Line 8 a - z.
C9: Form 1099-MISC and Instructions may be downloaded from the IRS:"
C10: https://www.irs.gov/pub/irs-pdf/f1099msc.pdf | H10: https://www.irs.gov/instructions/i1099mec
C70: Table of Contents

Sheet 1099-NEC
B1: Form 1099-NEC, Nonemployee Compensation | E1: =IF(FALSE,"After Form 1040 and Schedule 1 are complete,"&CHAR(10)&" be sure to review 'Sch. 1 Line 8 WS', line 1.",IF(FALSE,"'Sch. 1 Line 8 WS', line 1, has been Updated.","")) | M1: Notes
C2: =IF(Name_1st_Yours="","Enter your name on the"&CHAR(10)&"sheet labeled '1040'",NameYours) | D2: Payer #1 | E2: Payer #2 | F2: Payer #3 | G2: Payer #4 | H2: Payer #5 | I2: Payer #6 | J2: Your Total | K2: Used at:
C3: PAYER's name | J3: ---
C4: PAYER's TIN | J4: ---
C5: Account number | J5: ---
B6: 1 | C6: Nonemployee compensation | J6: =ROUND(SUM(D6:I6),0) | K6: Sch C, line 1 (for you)
B7: 2 | C7: Payer made direct sales of $5,000 or more of consumer productes to recipient for resale | D7: Y/ N | E7: Y/ N | F7: Y/ N | G7: Y/ N | H7: Y/ N | I7: Y/ N | J7: ---
B8: 3 | C8: Excess golden parachute payments | J8: =ROUND(SUM(D8:I8),0) | K8: =IF(Needs_SALT,"'Sch. 1, Line 1 (SALT)'. (State & Local Tax)","")
B9: 4 | C9: Federal income tax withheld | J9: =ROUND(SUM(D9:I9),0)
B10: 5 | C10: State tax withheld | J10: =ROUND(SUM(D10:I10),0)
B11: 6 | C11: State/Payer's state no. | J11: =ROUND(SUM(D11:I11),0)
B12: 7 | C12: State income | J12: =ROUND(SUM(D12:I12),0)
B13: Only bolded amounts are used in this spreadsheet.
J14: =IF(J3<>"",J3,"")
C15: =IF(Name_1st_Sp="","Enter your spouse's name on"&CHAR(10)&"the sheet labeled '1040'",NameSpouse) | D15: Payer #1 | E15: Payer #2 | F15: Payer #3 | G15: Payer #4 | H15: Payer #5 | I15: Spouse Total | J15: Total | K15: Used at:
C16: PAYER's name | J16: ---
C17: PAYER's Federal ID number | J17: ---
C18: Account number | J18: --- | K18: =SUM(ForeignTaxPaid_INT,ForeignTaxPaid_DIV)
B19: 1 | C19: Nonemployee compensation | I19: =ROUND(SUM(D19:H19),0) | J19: =SUM(NonEmployeeComp_You,NonEmployeeComp_Spouse) | K19: Sch C, line 1 (for your spouse)
B20: 2 | C20: Payer made direct sales of $5,000 or more of consumer productes to recipient for resale | D20: Y/ N | E20: Y/ N | F20: Y/ N | G20: Y/ N | H20: Y/ N | I20: --- | J20: ---
B21: 3 | C21: Excess golden parachute payments | I21: =ROUND(SUM(D21:H21),0) | J21: =SUM(J8,I21)
B22: 4 | C22: Federal income tax withheld | I22: =ROUND(SUM(D22:H22),0) | J22: =SUM(J9,I22) | K22: Form 1040, line 25b
B23: 5 | C23: State tax withheld | I23: =ROUND(SUM(D23:H23),0) | J23: =SUM(J10,I23) | K23: Sch. A, line 5a
B24: 6 | C24: State/Payer's state no. | I24: =ROUND(SUM(D24:H24),0) | J24: =SUM(J11,I24)
B25: 7 | C25: State income | I25: =ROUND(SUM(D25:H25),0) | J25: =SUM(J12,I25)
B26: Only bolded amounts are used in this spreadsheet.
C31: Table of Contents

Sheet 1099-R
B1: Information from Form 1099-R, Distributions From Pensions, Annuities, Retirement or Profit-Sharing Plans, IRAs, Insurance Contracts, etc. | AU1: Notes
C2: =IF(Name_1st_Yours="","Enter your name on the"&CHAR(10)&"sheet labeled '1040'",NameYours) | D2: Enter payer's name here. | E2: Payer #2 | F2: Payer #3 | G2: Payer #4 | H2: Payer #5 | I2: Payer #6 | J2: Payer #7 | K2: Payer #8 | L2: Payer #9 | M2: Total IRAs | N2: Total Pension / Annuities | O2: Qualified CONVersion to ROTH IRA | U2: IRA | AE2: P/A | AO2: CONV
C3: Enter "IRA" or "P/A" or "CONV" >>> | M3: IRA | N3: P/A | O3: CONV | Q3: =NOT(AND(ISERROR(FIND("IRA",D3,1)),ISERROR(FIND("ira",D3,1)))) | R3: =NOT(AND(ISERROR(FIND("IRA",E3,1)),ISERROR(FIND("ira",E3,1)))) | S3: =NOT(AND(ISERROR(FIND("IRA",F3,1)),ISERROR(FIND("ira",F3,1)))) | T3: =NOT(AND(ISERROR(FIND("IRA",G3,1)),ISERROR(FIND("ira",G3,1)))) | U3: =NOT(AND(ISERROR(FIND("IRA",H3,1)),ISERROR(FIND("ira",H3,1)))) | V3: =NOT(AND(ISERROR(FIND("IRA",I3,1)),ISERROR(FIND("ira",I3,1)))) | W3: =NOT(AND(ISERROR(FIND("IRA",J3,1)),ISERROR(FIND("ira",J3,1)))) | X3: =NOT(AND(ISERROR(FIND("IRA",K3,1)),ISERROR(FIND("ira",K3,1)))) | Y3: =NOT(AND(ISERROR(FIND("IRA",L3,1)),ISERROR(FIND("ira",L3,1)))) | AA3: =NOT(AND(ISERROR(FIND("P/A",D3,1)),ISERROR(FIND("p/a",D3,1)))) | AB3: =NOT(AND(ISERROR(FIND("P/A",E3,1)),ISERROR(FIND("p/a",E3,1)))) | AC3: =NOT(AND(ISERROR(FIND("P/A",F3,1)),ISERROR(FIND("p/a",F3,1)))) | AD3: =NOT(AND(ISERROR(FIND("P/A",G3,1)),ISERROR(FIND("p/a",G3,1)))) | AE3: =NOT(AND(ISERROR(FIND("P/A",H3,1)),ISERROR(FIND("p/a",H3,1)))) | AF3: =NOT(AND(ISERROR(FIND("P/A",I3,1)),ISERROR(FIND("p/a",I3,1)))) | AG3: =NOT(AND(ISERROR(FIND("P/A",J3,1)),ISERROR(FIND("p/a",J3,1)))) | AH3: =NOT(AND(ISERROR(FIND("P/A",K3,1)),ISERROR(FIND("p/a",K3,1)))) | AI3: =NOT(AND(ISERROR(FIND("P/A",L3,1)),ISERROR(FIND("p/a",L3,1)))) | AK3: =NOT(AND(ISERROR(FIND("CONV",D3,1)),ISERROR(FIND("conv",D3,1)))) | AL3: =NOT(AND(ISERROR(FIND("CONV",E3,1)),ISERROR(FIND("conv",E3,1)))) | AM3: =NOT(AND(ISERROR(FIND("CONV",F3,1)),ISERROR(FIND("conv",F3,1)))) | AN3: =NOT(AND(ISERROR(FIND("CONV",G3,1)),ISERROR(FIND("conv",G3,1)))) | AO3: =NOT(AND(ISERROR(FIND("CONV",H3,1)),ISERROR(FIND("conv",H3,1)))) | AP3: =NOT(AND(ISERROR(FIND("CONV",I3,1)),ISERROR(FIND("conv",I3,1)))) | AQ3: =NOT(AND(ISERROR(FIND("CONV",J3,1)),ISERROR(FIND("conv",J3,1)))) | AR3: =NOT(AND(ISERROR(FIND("CONV",K3,1)),ISERROR(FIND("conv",K3,1)))) | AS3: =NOT(AND(ISERROR(FIND("CONV",L3,1)),ISERROR(FIND("conv",L3,1))))
B4: 1 | C4: Gross distribution | M4: =SUM(Q4:Y4) | N4: =SUM(AA4:AI4) | O4: =SUM(AK4:AS4) | Q4: =IF(Q$3,ROUND(D4,0),0) | R4: =IF(R$3,ROUND(E4,0),0) | S4: =IF(S$3,ROUND(F4,0),0) | T4: =IF(T$3,ROUND(G4,0),0) | U4: =IF(U$3,ROUND(H4,0),0) | V4: =IF(V$3,ROUND(I4,0),0) | W4: =IF(W$3,ROUND(J4,0),0) | X4: =IF(X$3,ROUND(K4,0),0) | Y4: =IF(Y$3,ROUND(L4,0),0) | AA4: =IF(AA$3,ROUND(D4,0),0) | AB4: =IF(AB$3,ROUND(E4,0),0) | AC4: =IF(AC$3,ROUND(F4,0),0) | AD4: =IF(AD$3,ROUND(G4,0),0) | AE4: =IF(AE$3,ROUND(H4,0),0) | AF4: =IF(AF$3,ROUND(I4,0),0) | AG4: =IF(AG$3,ROUND(J4,0),0) | AH4: =IF(AH$3,ROUND(K4,0),0) | AI4: =IF(AI$3,ROUND(L4,0),0) | AK4: =IF(AK$3,ROUND(D4,0),0) | AL4: =IF(AL$3,ROUND(E4,0),0) | AM4: =IF(AM$3,ROUND(F4,0),0) | AN4: =IF(AN$3,ROUND(G4,0),0) | AO4: =IF(AO$3,ROUND(H4,0),0) | AP4: =IF(AP$3,ROUND(I4,0),0) | AQ4: =IF(AQ$3,ROUND(J4,0),0) | AR4: =IF(AR$3,ROUND(K4,0),0) | AS4: =IF(AS$3,ROUND(L4,0),0)
B5: 2a | C5: Taxable amount | M5: =SUM(Q5:Y5) | N5: =SUM(AA5:AI5) | O5: =IF(SUM(D5:L5)>0,"See note.","- - - -") | Q5: =IF(Q$3,ROUND(D5,0),0) | R5: =IF(R$3,ROUND(E5,0),0) | S5: =IF(S$3,ROUND(F5,0),0) | T5: =IF(T$3,ROUND(G5,0),0) | U5: =IF(U$3,ROUND(H5,0),0) | V5: =IF(V$3,ROUND(I5,0),0) | W5: =IF(W$3,ROUND(J5,0),0) | X5: =IF(X$3,ROUND(K5,0),0) | Y5: =IF(Y$3,ROUND(L5,0),0) | AA5: =IF(AA$3,ROUND(D5,0),0) | AB5: =IF(AB$3,ROUND(E5,0),0) | AC5: =IF(AC$3,ROUND(F5,0),0) | AD5: =IF(AD$3,ROUND(G5,0),0) | AE5: =IF(AE$3,ROUND(H5,0),0) | AF5: =IF(AF$3,ROUND(I5,0),0) | AG5: =IF(AG$3,ROUND(J5,0),0) | AH5: =IF(AH$3,ROUND(K5,0),0) | AI5: =IF(AI$3,ROUND(L5,0),0) | AK5: ="---" | AL5: ="---" | AM5: ="---" | AN5: ="---" | AO5: ="---" | AP5: ="---" | AQ5: ="---" | AR5: ="---" | AS5: ="---"
B6: 2b | C6: Taxable amount not determined / total distr. | M6: =" - - - -" | N6: =" - - - -" | O6: =" - - - -"
B7: 3 | C7: Capital gain (included in box 2a) | M7: =SUM(Q7:Y7) | N7: =SUM(AA7:AI7) | O7: =SUM(AK7:AS7) | Q7: =IF(Q$3,ROUND(D7,0),0) | R7: =IF(R$3,ROUND(E7,0),0) | S7: =IF(S$3,ROUND(F7,0),0) | T7: =IF(T$3,ROUND(G7,0),0) | U7: =IF(U$3,ROUND(H7,0),0) | V7: =IF(V$3,ROUND(I7,0),0) | W7: =IF(W$3,ROUND(J7,0),0) | X7: =IF(X$3,ROUND(K7,0),0) | Y7: =IF(Y$3,ROUND(L7,0),0) | AA7: =IF(AA$3,ROUND(D7,0),0) | AB7: =IF(AB$3,ROUND(E7,0),0) | AC7: =IF(AC$3,ROUND(F7,0),0) | AD7: =IF(AD$3,ROUND(G7,0),0) | AE7: =IF(AE$3,ROUND(H7,0),0) | AF7: =IF(AF$3,ROUND(I7,0),0) | AG7: =IF(AG$3,ROUND(J7,0),0) | AH7: =IF(AH$3,ROUND(K7,0),0) | AI7: =IF(AI$3,ROUND(L7,0),0) | AK7: =IF(AK$3,ROUND(D7,0),0) | AL7: =IF(AL$3,ROUND(E7,0),0) | AM7: =IF(AM$3,ROUND(F7,0),0) | AN7: =IF(AN$3,ROUND(G7,0),0) | AO7: =IF(AO$3,ROUND(H7,0),0) | AP7: =IF(AP$3,ROUND(I7,0),0) | AQ7: =IF(AQ$3,ROUND(J7,0),0) | AR7: =IF(AR$3,ROUND(K7,0),0) | AS7: =IF(AS$3,ROUND(L7,0),0)
B8: 4 | C8: Federal income tax withheld | M8: =SUM(Q8:Y8) | N8: =SUM(AA8:AI8) | O8: =SUM(AK8:AS8) | Q8: =IF(Q$3,ROUND(D8,0),0) | R8: =IF(R$3,ROUND(E8,0),0) | S8: =IF(S$3,ROUND(F8,0),0) | T8: =IF(T$3,ROUND(G8,0),0) | U8: =IF(U$3,ROUND(H8,0),0) | V8: =IF(V$3,ROUND(I8,0),0) | W8: =IF(W$3,ROUND(J8,0),0) | X8: =IF(X$3,ROUND(K8,0),0) | Y8: =IF(Y$3,ROUND(L8,0),0) | AA8: =IF(AA$3,ROUND(D8,0),0) | AB8: =IF(AB$3,ROUND(E8,0),0) | AC8: =IF(AC$3,ROUND(F8,0),0) | AD8: =IF(AD$3,ROUND(G8,0),0) | AE8: =IF(AE$3,ROUND(H8,0),0) | AF8: =IF(AF$3,ROUND(I8,0),0) | AG8: =IF(AG$3,ROUND(J8,0),0) | AH8: =IF(AH$3,ROUND(K8,0),0) | AI8: =IF(AI$3,ROUND(L8,0),0) | AK8: =IF(AK$3,ROUND(D8,0),0) | AL8: =IF(AL$3,ROUND(E8,0),0) | AM8: =IF(AM$3,ROUND(F8,0),0) | AN8: =IF(AN$3,ROUND(G8,0),0) | AO8: =IF(AO$3,ROUND(H8,0),0) | AP8: =IF(AP$3,ROUND(I8,0),0) | AQ8: =IF(AQ$3,ROUND(J8,0),0) | AR8: =IF(AR$3,ROUND(K8,0),0) | AS8: =IF(AS$3,ROUND(L8,0),0)
B9: 5 | C9: Employee contributions / Insurance premiums / Designated Roth IRA contributions | M9: =SUM(Q9:Y9) | N9: =SUM(AA9:AI9) | O9: =SUM(AK9:AS9) | Q9: =IF(Q$3,ROUND(D9,0),0) | R9: =IF(R$3,ROUND(E9,0),0) | S9: =IF(S$3,ROUND(F9,0),0) | T9: =IF(T$3,ROUND(G9,0),0) | U9: =IF(U$3,ROUND(H9,0),0) | V9: =IF(V$3,ROUND(I9,0),0) | W9: =IF(W$3,ROUND(J9,0),0) | X9: =IF(X$3,ROUND(K9,0),0) | Y9: =IF(Y$3,ROUND(L9,0),0) | AA9: =IF(AA$3,ROUND(D9,0),0) | AB9: =IF(AB$3,ROUND(E9,0),0) | AC9: =IF(AC$3,ROUND(F9,0),0) | AD9: =IF(AD$3,ROUND(G9,0),0) | AE9: =IF(AE$3,ROUND(H9,0),0) | AF9: =IF(AF$3,ROUND(I9,0),0) | AG9: =IF(AG$3,ROUND(J9,0),0) | AH9: =IF(AH$3,ROUND(K9,0),0) | AI9: =IF(AI$3,ROUND(L9,0),0) | AK9: =IF(AK$3,ROUND(D9,0),0) | AL9: =IF(AL$3,ROUND(E9,0),0) | AM9: =IF(AM$3,ROUND(F9,0),0) | AN9: =IF(AN$3,ROUND(G9,0),0) | AO9: =IF(AO$3,ROUND(H9,0),0) | AP9: =IF(AP$3,ROUND(I9,0),0) | AQ9: =IF(AQ$3,ROUND(J9,0),0) | AR9: =IF(AR$3,ROUND(K9,0),0) | AS9: =IF(AS$3,ROUND(L9,0),0)
B10: 6 | C10: Net unrealized appreciation in employer's securities | M10: =SUM(Q10:Y10) | N10: =SUM(AA10:AI10) | O10: =SUM(AK10:AS10) | Q10: =IF(Q$3,ROUND(D10,0),0) | R10: =IF(R$3,ROUND(E10,0),0) | S10: =IF(S$3,ROUND(F10,0),0) | T10: =IF(T$3,ROUND(G10,0),0) | U10: =IF(U$3,ROUND(H10,0),0) | V10: =IF(V$3,ROUND(I10,0),0) | W10: =IF(W$3,ROUND(J10,0),0) | X10: =IF(X$3,ROUND(K10,0),0) | Y10: =IF(Y$3,ROUND(L10,0),0) | AA10: =IF(AA$3,ROUND(D10,0),0) | AB10: =IF(AB$3,ROUND(E10,0),0) | AC10: =IF(AC$3,ROUND(F10,0),0) | AD10: =IF(AD$3,ROUND(G10,0),0) | AE10: =IF(AE$3,ROUND(H10,0),0) | AF10: =IF(AF$3,ROUND(I10,0),0) | AG10: =IF(AG$3,ROUND(J10,0),0) | AH10: =IF(AH$3,ROUND(K10,0),0) | AI10: =IF(AI$3,ROUND(L10,0),0) | AK10: =IF(AK$3,ROUND(D10,0),0) | AL10: =IF(AL$3,ROUND(E10,0),0) | AM10: =IF(AM$3,ROUND(F10,0),0) | AN10: =IF(AN$3,ROUND(G10,0),0) | AO10: =IF(AO$3,ROUND(H10,0),0) | AP10: =IF(AP$3,ROUND(I10,0),0) | AQ10: =IF(AQ$3,ROUND(J10,0),0) | AR10: =IF(AR$3,ROUND(K10,0),0) | AS10: =IF(AS$3,ROUND(L10,0),0)
B11: 7 | C11: Distribution code(s) (Code D only) | M11: =" - - - -" | N11: =" - - - -" | O11: =" - - - -" | AK11: =IF(AK$3,ROUND(D11,0),0) | AL11: =IF(AL$3,ROUND(E11,0),0) | AM11: =IF(AM$3,ROUND(F11,0),0) | AN11: =IF(AN$3,ROUND(G11,0),0) | AO11: =IF(AO$3,ROUND(H11,0),0) | AP11: =IF(AP$3,ROUND(I11,0),0) | AQ11: =IF(AQ$3,ROUND(J11,0),0) | AR11: =IF(AR$3,ROUND(K11,0),0) | AS11: =IF(AS$3,ROUND(L11,0),0)
B12: 8 | C12: Other | M12: =SUM(Q12:Y12) | N12: =SUM(AA12:AI12) | O12: =SUM(AK12:AS12) | Q12: =IF(Q$3,ROUND(D12,0),0) | R12: =IF(R$3,ROUND(E12,0),0) | S12: =IF(S$3,ROUND(F12,0),0) | T12: =IF(T$3,ROUND(G12,0),0) | U12: =IF(U$3,ROUND(H12,0),0) | V12: =IF(V$3,ROUND(I12,0),0) | W12: =IF(W$3,ROUND(J12,0),0) | X12: =IF(X$3,ROUND(K12,0),0) | Y12: =IF(Y$3,ROUND(L12,0),0) | AA12: =IF(AA$3,ROUND(D12,0),0) | AB12: =IF(AB$3,ROUND(E12,0),0) | AC12: =IF(AC$3,ROUND(F12,0),0) | AD12: =IF(AD$3,ROUND(G12,0),0) | AE12: =IF(AE$3,ROUND(H12,0),0) | AF12: =IF(AF$3,ROUND(I12,0),0) | AG12: =IF(AG$3,ROUND(J12,0),0) | AH12: =IF(AH$3,ROUND(K12,0),0) | AI12: =IF(AI$3,ROUND(L12,0),0) | AK12: =IF(AK$3,ROUND(D12,0),0) | AL12: =IF(AL$3,ROUND(E12,0),0) | AM12: =IF(AM$3,ROUND(F12,0),0) | AN12: =IF(AN$3,ROUND(G12,0),0) | AO12: =IF(AO$3,ROUND(H12,0),0) | AP12: =IF(AP$3,ROUND(I12,0),0) | AQ12: =IF(AQ$3,ROUND(J12,0),0) | AR12: =IF(AR$3,ROUND(K12,0),0) | AS12: =IF(AS$3,ROUND(L12,0),0)
B13: 9a | C13: Your percentage of total distribution | M13: =SUM(Q13:Y13) | N13: =SUM(AA13:AI13) | O13: =SUM(AK13:AS13) | Q13: =IF(Q3,D13,0) | R13: =IF(R3,E13,0) | S13: =IF(S3,F13,0) | T13: =IF(T3,G13,0) | U13: =IF(U3,H13,0) | V13: =IF(V3,I13,0) | W13: =IF(W3,J13,0) | X13: =IF(X3,K13,0) | Y13: =IF(Y3,L13,0) | AA13: =IF(AA3,D13,0) | AB13: =IF(AB3,E13,0) | AC13: =IF(AC3,F13,0) | AD13: =IF(AD3,G13,0) | AE13: =IF(AE3,H13,0) | AF13: =IF(AF3,I13,0) | AG13: =IF(AG3,J13,0) | AH13: =IF(AH3,K13,0) | AI13: =IF(AI3,L13,0) | AK13: =IF(AK3,D13,0) | AL13: =IF(AL3,E13,0) | AM13: =IF(AM3,F13,0) | AN13: =IF(AN3,G13,0) | AO13: =IF(AO3,H13,0) | AP13: =IF(AP3,I13,0) | AQ13: =IF(AQ3,J13,0) | AR13: =IF(AR3,K13,0) | AS13: =IF(AS3,L13,0)
B14: 9b | C14: Total employee contributions | M14: =SUM(Q14:Y14) | N14: =SUM(AA14:AI14) | O14: =SUM(AK14:AS14) | Q14: =IF(Q$3,ROUND(D14,0),0) | R14: =IF(R$3,ROUND(E14,0),0) | S14: =IF(S$3,ROUND(F14,0),0) | T14: =IF(T$3,ROUND(G14,0),0) | U14: =IF(U$3,ROUND(H14,0),0) | V14: =IF(V$3,ROUND(I14,0),0) | W14: =IF(W$3,ROUND(J14,0),0) | X14: =IF(X$3,ROUND(K14,0),0) | Y14: =IF(Y$3,ROUND(L14,0),0) | AA14: =IF(AA$3,ROUND(D14,0),0) | AB14: =IF(AB$3,ROUND(E14,0),0) | AC14: =IF(AC$3,ROUND(F14,0),0) | AD14: =IF(AD$3,ROUND(G14,0),0) | AE14: =IF(AE$3,ROUND(H14,0),0) | AF14: =IF(AF$3,ROUND(I14,0),0) | AG14: =IF(AG$3,ROUND(J14,0),0) | AH14: =IF(AH$3,ROUND(K14,0),0) | AI14: =IF(AI$3,ROUND(L14,0),0) | AK14: =IF(AK$3,ROUND(D14,0),0) | AL14: =IF(AL$3,ROUND(E14,0),0) | AM14: =IF(AM$3,ROUND(F14,0),0) | AN14: =IF(AN$3,ROUND(G14,0),0) | AO14: =IF(AO$3,ROUND(H14,0),0) | AP14: =IF(AP$3,ROUND(I14,0),0) | AQ14: =IF(AQ$3,ROUND(J14,0),0) | AR14: =IF(AR$3,ROUND(K14,0),0) | AS14: =IF(AS$3,ROUND(L14,0),0)
B15: 10 | C15: Amount allocable to IRR within 5 years | M15: =SUM(Q15:Y15) | N15: =SUM(AA15:AI15) | O15: =SUM(AK15:AS15) | Q15: =IF(Q$3,ROUND(D15,0),0) | R15: =IF(R$3,ROUND(E15,0),0) | S15: =IF(S$3,ROUND(F15,0),0) | T15: =IF(T$3,ROUND(G15,0),0) | U15: =IF(U$3,ROUND(H15,0),0) | V15: =IF(V$3,ROUND(I15,0),0) | W15: =IF(W$3,ROUND(J15,0),0) | X15: =IF(X$3,ROUND(K15,0),0) | Y15: =IF(Y$3,ROUND(L15,0),0) | AA15: =IF(AA$3,ROUND(D15,0),0) | AB15: =IF(AB$3,ROUND(E15,0),0) | AC15: =IF(AC$3,ROUND(F15,0),0) | AD15: =IF(AD$3,ROUND(G15,0),0) | AE15: =IF(AE$3,ROUND(H15,0),0) | AF15: =IF(AF$3,ROUND(I15,0),0) | AG15: =IF(AG$3,ROUND(J15,0),0) | AH15: =IF(AH$3,ROUND(K15,0),0) | AI15: =IF(AI$3,ROUND(L15,0),0) | AK15: =IF(AK$3,ROUND(D15,0),0) | AL15: =IF(AL$3,ROUND(E15,0),0) | AM15: =IF(AM$3,ROUND(F15,0),0) | AN15: =IF(AN$3,ROUND(G15,0),0) | AO15: =IF(AO$3,ROUND(H15,0),0) | AP15: =IF(AP$3,ROUND(I15,0),0) | AQ15: =IF(AQ$3,ROUND(J15,0),0) | AR15: =IF(AR$3,ROUND(K15,0),0) | AS15: =IF(AS$3,ROUND(L15,0),0)
B16: 11 | C16: 1st year of desig. Roth contrib. | M16: =SUM(Q16:Y16) | N16: =SUM(AA16:AI16) | O16: =SUM(AK16:AS16) | Q16: =IF(Q$3,ROUND(D16,0),0) | R16: =IF(R$3,ROUND(E16,0),0) | S16: =IF(S$3,ROUND(F16,0),0) | T16: =IF(T$3,ROUND(G16,0),0) | U16: =IF(U$3,ROUND(H16,0),0) | V16: =IF(V$3,ROUND(I16,0),0) | W16: =IF(W$3,ROUND(J16,0),0) | X16: =IF(X$3,ROUND(K16,0),0) | Y16: =IF(Y$3,ROUND(L16,0),0) | AA16: =IF(AA$3,ROUND(D16,0),0) | AB16: =IF(AB$3,ROUND(E16,0),0) | AC16: =IF(AC$3,ROUND(F16,0),0) | AD16: =IF(AD$3,ROUND(G16,0),0) | AE16: =IF(AE$3,ROUND(H16,0),0) | AF16: =IF(AF$3,ROUND(I16,0),0) | AG16: =IF(AG$3,ROUND(J16,0),0) | AH16: =IF(AH$3,ROUND(K16,0),0) | AI16: =IF(AI$3,ROUND(L16,0),0) | AK16: =IF(AK$3,ROUND(D16,0),0) | AL16: =IF(AL$3,ROUND(E16,0),0) | AM16: =IF(AM$3,ROUND(F16,0),0) | AN16: =IF(AN$3,ROUND(G16,0),0) | AO16: =IF(AO$3,ROUND(H16,0),0) | AP16: =IF(AP$3,ROUND(I16,0),0) | AQ16: =IF(AQ$3,ROUND(J16,0),0) | AR16: =IF(AR$3,ROUND(K16,0),0) | AS16: =IF(AS$3,ROUND(L16,0),0)
B17: 12 | C17: FATCA filing requirement | M17: =" - - - -" | N17: =" - - - -" | O17: =" - - - -" | Q17: =IF(Q$3,ROUND(D17,0),0) | R17: =IF(R$3,ROUND(E17,0),0) | S17: =IF(S$3,ROUND(F17,0),0) | T17: =IF(T$3,ROUND(G17,0),0) | U17: =IF(U$3,ROUND(H17,0),0) | V17: =IF(V$3,ROUND(I17,0),0) | W17: =IF(W$3,ROUND(J17,0),0) | X17: =IF(X$3,ROUND(K17,0),0) | Y17: =IF(Y$3,ROUND(L17,0),0) | AA17: =IF(AA$3,ROUND(D17,0),0) | AB17: =IF(AB$3,ROUND(E17,0),0) | AC17: =IF(AC$3,ROUND(F17,0),0) | AD17: =IF(AD$3,ROUND(G17,0),0) | AE17: =IF(AE$3,ROUND(H17,0),0) | AF17: =IF(AF$3,ROUND(I17,0),0) | AG17: =IF(AG$3,ROUND(J17,0),0) | AH17: =IF(AH$3,ROUND(K17,0),0) | AI17: =IF(AI$3,ROUND(L17,0),0) | AK17: =IF(AK$3,ROUND(D17,0),0) | AL17: =IF(AL$3,ROUND(E17,0),0) | AM17: =IF(AM$3,ROUND(F17,0),0) | AN17: =IF(AN$3,ROUND(G17,0),0) | AO17: =IF(AO$3,ROUND(H17,0),0) | AP17: =IF(AP$3,ROUND(I17,0),0) | AQ17: =IF(AQ$3,ROUND(J17,0),0) | AR17: =IF(AR$3,ROUND(K17,0),0) | AS17: =IF(AS$3,ROUND(L17,0),0)
B18: 13 | C18: Date of Payment | M18: =" - - - -" | N18: =" - - - -" | O18: =" - - - -" | Q18: =IF(Q$3,ROUND(D18,0),0) | R18: =IF(R$3,ROUND(E18,0),0) | S18: =IF(S$3,ROUND(F18,0),0) | T18: =IF(T$3,ROUND(G18,0),0) | U18: =IF(U$3,ROUND(H18,0),0) | V18: =IF(V$3,ROUND(I18,0),0) | W18: =IF(W$3,ROUND(J18,0),0) | X18: =IF(X$3,ROUND(K18,0),0) | Y18: =IF(Y$3,ROUND(L18,0),0) | AA18: =IF(AA$3,ROUND(D18,0),0) | AB18: =IF(AB$3,ROUND(E18,0),0) | AC18: =IF(AC$3,ROUND(F18,0),0) | AD18: =IF(AD$3,ROUND(G18,0),0) | AE18: =IF(AE$3,ROUND(H18,0),0) | AF18: =IF(AF$3,ROUND(I18,0),0) | AG18: =IF(AG$3,ROUND(J18,0),0) | AH18: =IF(AH$3,ROUND(K18,0),0) | AI18: =IF(AI$3,ROUND(L18,0),0) | AK18: =IF(AK$3,ROUND(D18,0),0) | AL18: =IF(AL$3,ROUND(E18,0),0) | AM18: =IF(AM$3,ROUND(F18,0),0) | AN18: =IF(AN$3,ROUND(G18,0),0) | AO18: =IF(AO$3,ROUND(H18,0),0) | AP18: =IF(AP$3,ROUND(I18,0),0) | AQ18: =IF(AQ$3,ROUND(J18,0),0) | AR18: =IF(AR$3,ROUND(K18,0),0) | AS18: =IF(AS$3,ROUND(L18,0),0)
B19: 14 | C19: State tax withheld | M19: =SUM(Q19:Y19) | N19: =SUM(AA19:AI19) | O19: =SUM(AK19:AS19) | Q19: =IF(Q$3,ROUND(D19,0),0) | R19: =IF(R$3,ROUND(E19,0),0) | S19: =IF(S$3,ROUND(F19,0),0) | T19: =IF(T$3,ROUND(G19,0),0) | U19: =IF(U$3,ROUND(H19,0),0) | V19: =IF(V$3,ROUND(I19,0),0) | W19: =IF(W$3,ROUND(J19,0),0) | X19: =IF(X$3,ROUND(K19,0),0) | Y19: =IF(Y$3,ROUND(L19,0),0) | AA19: =IF(AA$3,ROUND(D19,0),0) | AB19: =IF(AB$3,ROUND(E19,0),0) | AC19: =IF(AC$3,ROUND(F19,0),0) | AD19: =IF(AD$3,ROUND(G19,0),0) | AE19: =IF(AE$3,ROUND(H19,0),0) | AF19: =IF(AF$3,ROUND(I19,0),0) | AG19: =IF(AG$3,ROUND(J19,0),0) | AH19: =IF(AH$3,ROUND(K19,0),0) | AI19: =IF(AI$3,ROUND(L19,0),0) | AK19: =IF(AK$3,ROUND(D19,0),0) | AL19: =IF(AL$3,ROUND(E19,0),0) | AM19: =IF(AM$3,ROUND(F19,0),0) | AN19: =IF(AN$3,ROUND(G19,0),0) | AO19: =IF(AO$3,ROUND(H19,0),0) | AP19: =IF(AP$3,ROUND(I19,0),0) | AQ19: =IF(AQ$3,ROUND(J19,0),0) | AR19: =IF(AR$3,ROUND(K19,0),0) | AS19: =IF(AS$3,ROUND(L19,0),0)
B20: 15 | C20: State/payer's state no. | M20: =" - - - -" | N20: =" - - - -" | O20: =" - - - -"
B21: 16 | C21: State distribution | M21: =SUM(Q21:Y21) | N21: =SUM(AA21:AI21) | O21: =SUM(AK21:AS21) | Q21: =IF(Q$3,ROUND(D21,0),0) | R21: =IF(R$3,ROUND(E21,0),0) | S21: =IF(S$3,ROUND(F21,0),0) | T21: =IF(T$3,ROUND(G21,0),0) | U21: =IF(U$3,ROUND(H21,0),0) | V21: =IF(V$3,ROUND(I21,0),0) | W21: =IF(W$3,ROUND(J21,0),0) | X21: =IF(X$3,ROUND(K21,0),0) | Y21: =IF(Y$3,ROUND(L21,0),0) | AA21: =IF(AA$3,ROUND(D21,0),0) | AB21: =IF(AB$3,ROUND(E21,0),0) | AC21: =IF(AC$3,ROUND(F21,0),0) | AD21: =IF(AD$3,ROUND(G21,0),0) | AE21: =IF(AE$3,ROUND(H21,0),0) | AF21: =IF(AF$3,ROUND(I21,0),0) | AG21: =IF(AG$3,ROUND(J21,0),0) | AH21: =IF(AH$3,ROUND(K21,0),0) | AI21: =IF(AI$3,ROUND(L21,0),0) | AK21: =IF(AK$3,ROUND(D21,0),0) | AL21: =IF(AL$3,ROUND(E21,0),0) | AM21: =IF(AM$3,ROUND(F21,0),0) | AN21: =IF(AN$3,ROUND(G21,0),0) | AO21: =IF(AO$3,ROUND(H21,0),0) | AP21: =IF(AP$3,ROUND(I21,0),0) | AQ21: =IF(AQ$3,ROUND(J21,0),0) | AR21: =IF(AR$3,ROUND(K21,0),0) | AS21: =IF(AS$3,ROUND(L21,0),0)
B22: 17 | C22: Local tax withheld | M22: =SUM(Q22:Y22) | N22: =SUM(AA22:AI22) | O22: =SUM(AK22:AS22) | Q22: =IF(Q$3,ROUND(D22,0),0) | R22: =IF(R$3,ROUND(E22,0),0) | S22: =IF(S$3,ROUND(F22,0),0) | T22: =IF(T$3,ROUND(G22,0),0) | U22: =IF(U$3,ROUND(H22,0),0) | V22: =IF(V$3,ROUND(I22,0),0) | W22: =IF(W$3,ROUND(J22,0),0) | X22: =IF(X$3,ROUND(K22,0),0) | Y22: =IF(Y$3,ROUND(L22,0),0) | AA22: =IF(AA$3,ROUND(D22,0),0) | AB22: =IF(AB$3,ROUND(E22,0),0) | AC22: =IF(AC$3,ROUND(F22,0),0) | AD22: =IF(AD$3,ROUND(G22,0),0) | AE22: =IF(AE$3,ROUND(H22,0),0) | AF22: =IF(AF$3,ROUND(I22,0),0) | AG22: =IF(AG$3,ROUND(J22,0),0) | AH22: =IF(AH$3,ROUND(K22,0),0) | AI22: =IF(AI$3,ROUND(L22,0),0) | AK22: =IF(AK$3,ROUND(D22,0),0) | AL22: =IF(AL$3,ROUND(E22,0),0) | AM22: =IF(AM$3,ROUND(F22,0),0) | AN22: =IF(AN$3,ROUND(G22,0),0) | AO22: =IF(AO$3,ROUND(H22,0),0) | AP22: =IF(AP$3,ROUND(I22,0),0) | AQ22: =IF(AQ$3,ROUND(J22,0),0) | AR22: =IF(AR$3,ROUND(K22,0),0) | AS22: =IF(AS$3,ROUND(L22,0),0)
B23: 18 | C23: Name of locality | D23: =OR(D3="CONV",D3="conv") | E23: =OR(E3="CONV",E3="conv") | F23: =OR(F3="CONV",F3="conv") | G23: =OR(G3="CONV",G3="conv") | H23: =OR(H3="CONV",H3="conv") | I23: =OR(I3="CONV",I3="conv") | J23: =OR(J3="CONV",J3="conv") | K23: =OR(K3="CONV",K3="conv") | L23: =OR(L3="CONV",L3="conv") | M23: =" - - - -" | N23: =" - - - -" | O23: =" - - - -"
B24: 19 | C24: Local distribution | M24: =SUM(Q24:Y24) | N24: =SUM(AA24:AI24) | O24: =SUM(AK24:AS24) | Q24: =IF(Q$3,ROUND(D24,0),0) | R24: =IF(R$3,ROUND(E24,0),0) | S24: =IF(S$3,ROUND(F24,0),0) | T24: =IF(T$3,ROUND(G24,0),0) | U24: =IF(U$3,ROUND(H24,0),0) | V24: =IF(V$3,ROUND(I24,0),0) | W24: =IF(W$3,ROUND(J24,0),0) | X24: =IF(X$3,ROUND(K24,0),0) | Y24: =IF(Y$3,ROUND(L24,0),0) | AA24: =IF(AA$3,ROUND(D24,0),0) | AB24: =IF(AB$3,ROUND(E24,0),0) | AC24: =IF(AC$3,ROUND(F24,0),0) | AD24: =IF(AD$3,ROUND(G24,0),0) | AE24: =IF(AE$3,ROUND(H24,0),0) | AF24: =IF(AF$3,ROUND(I24,0),0) | AG24: =IF(AG$3,ROUND(J24,0),0) | AH24: =IF(AH$3,ROUND(K24,0),0) | AI24: =IF(AI$3,ROUND(L24,0),0) | AK24: =IF(AK$3,ROUND(D24,0),0) | AL24: =IF(AL$3,ROUND(E24,0),0) | AM24: =IF(AM$3,ROUND(F24,0),0) | AN24: =IF(AN$3,ROUND(G24,0),0) | AO24: =IF(AO$3,ROUND(H24,0),0) | AP24: =IF(AP$3,ROUND(I24,0),0) | AQ24: =IF(AQ$3,ROUND(J24,0),0) | AR24: =IF(AR$3,ROUND(K24,0),0) | AS24: =IF(AS$3,ROUND(L24,0),0)
B25: Only bolded amounts are used in this spreadsheet. | D25: =OR(D23:L23) | H25: =IF(D25,"For IRA conversions, leave line 2a blank and complete "&CHAR(10)&"Form 8606.","")
D26: =IF(OR(LEFT(D11,1)="D",LEFT(D11,1)="d"),D5,"") | E26: =IF(OR(LEFT(E11,1)="D",LEFT(E11,1)="d"),E5,"") | F26: =IF(OR(LEFT(F11,1)="D",LEFT(F11,1)="d"),F5,"") | G26: =IF(OR(LEFT(G11,1)="D",LEFT(G11,1)="d"),G5,"") | H26: =IF(OR(LEFT(H11,1)="D",LEFT(H11,1)="d"),H5,"") | I26: =IF(OR(LEFT(I11,1)="D",LEFT(I11,1)="d"),I5,"") | J26: =IF(OR(LEFT(J11,1)="D",LEFT(J11,1)="d"),J5,"") | K26: =IF(OR(LEFT(K11,1)="D",LEFT(K11,1)="d"),K5,"") | L26: =IF(OR(LEFT(L11,1)="D",LEFT(L11,1)="d"),L5,"") | N26: =SUM(D26:L26) | O26: =SUM(E26:M26)
D27: =IF(OR(LEFT(D11,1)="D",LEFT(D11,1)="d"),SUM(D19,D22),"") | E27: =IF(OR(LEFT(E11,1)="D",LEFT(E11,1)="d"),SUM(E19,E22),"") | F27: =IF(OR(LEFT(F11,1)="D",LEFT(F11,1)="d"),SUM(F19,F22),"") | G27: =IF(OR(LEFT(G11,1)="D",LEFT(G11,1)="d"),SUM(G19,G22),"") | H27: =IF(OR(LEFT(H11,1)="D",LEFT(H11,1)="d"),SUM(H19,H22),"") | I27: =IF(OR(LEFT(I11,1)="D",LEFT(I11,1)="d"),SUM(I19,I22),"") | J27: =IF(OR(LEFT(J11,1)="D",LEFT(J11,1)="d"),SUM(J19,J22),"") | K27: =IF(OR(LEFT(K11,1)="D",LEFT(K11,1)="d"),SUM(K19,K22),"") | L27: =IF(OR(LEFT(L11,1)="D",LEFT(L11,1)="d"),SUM(L19,L22),"") | N27: =SUM(D27:L27) | O27: =SUM(E27:M27)
B28: Information from Form 1099-R, Distributions From Pensions, Annuities, Retirement or Profit-Sharing Plans, IRAs, Insurance Contracts, etc.
C29: =IF(Name_1st_Sp="","Enter your spouse's name on the"&CHAR(10)&"sheet labeled '1040'",NameSpouse) | D29: Payer #1 | E29: Payer #2 | F29: Payer #3 | G29: Payer #4 | H29: Payer #5 | I29: Payer #6 | J29: Payer #7 | K29: Payer #8 | L29: Payer #9 | M29: Total IRAs | N29: Total Pension / Annuities | O29: Qualified Conversion to ROTH IRA
C30: Enter "IRA" or "P/A" or "CONV" >>> | M30: IRA | N30: P/A | O30: CONV | Q30: =NOT(AND(ISERROR(FIND("IRA",D30,1)),ISERROR(FIND("ira",D30,1)))) | R30: =NOT(AND(ISERROR(FIND("IRA",E30,1)),ISERROR(FIND("ira",E30,1)))) | S30: =NOT(AND(ISERROR(FIND("IRA",F30,1)),ISERROR(FIND("ira",F30,1)))) | T30: =NOT(AND(ISERROR(FIND("IRA",G30,1)),ISERROR(FIND("ira",G30,1)))) | U30: =NOT(AND(ISERROR(FIND("IRA",H30,1)),ISERROR(FIND("ira",H30,1)))) | V30: =NOT(AND(ISERROR(FIND("IRA",I30,1)),ISERROR(FIND("ira",I30,1)))) | W30: =NOT(AND(ISERROR(FIND("IRA",J30,1)),ISERROR(FIND("ira",J30,1)))) | X30: =NOT(AND(ISERROR(FIND("IRA",K30,1)),ISERROR(FIND("ira",K30,1)))) | Y30: =NOT(AND(ISERROR(FIND("IRA",L30,1)),ISERROR(FIND("ira",L30,1)))) | AA30: =NOT(AND(ISERROR(FIND("P/A",D30,1)),ISERROR(FIND("p/a",D30,1)))) | AB30: =NOT(AND(ISERROR(FIND("P/A",E30,1)),ISERROR(FIND("p/a",E30,1)))) | AC30: =NOT(AND(ISERROR(FIND("P/A",F30,1)),ISERROR(FIND("p/a",F30,1)))) | AD30: =NOT(AND(ISERROR(FIND("P/A",G30,1)),ISERROR(FIND("p/a",G30,1)))) | AE30: =NOT(AND(ISERROR(FIND("P/A",H30,1)),ISERROR(FIND("p/a",H30,1)))) | AF30: =NOT(AND(ISERROR(FIND("P/A",I30,1)),ISERROR(FIND("p/a",I30,1)))) | AG30: =NOT(AND(ISERROR(FIND("P/A",J30,1)),ISERROR(FIND("p/a",J30,1)))) | AH30: =NOT(AND(ISERROR(FIND("P/A",K30,1)),ISERROR(FIND("p/a",K30,1)))) | AI30: =NOT(AND(ISERROR(FIND("P/A",L30,1)),ISERROR(FIND("p/a",L30,1)))) | AK30: =NOT(AND(ISERROR(FIND("CONV",D30,1)),ISERROR(FIND("conv",D30,1)))) | AL30: =NOT(AND(ISERROR(FIND("CONV",E30,1)),ISERROR(FIND("conv",E30,1)))) | AM30: =NOT(AND(ISERROR(FIND("CONV",F30,1)),ISERROR(FIND("conv",F30,1)))) | AN30: =NOT(AND(ISERROR(FIND("CONV",G30,1)),ISERROR(FIND("conv",G30,1)))) | AO30: =NOT(AND(ISERROR(FIND("CONV",H30,1)),ISERROR(FIND("conv",H30,1)))) | AP30: =NOT(AND(ISERROR(FIND("CONV",I30,1)),ISERROR(FIND("conv",I30,1)))) | AQ30: =NOT(AND(ISERROR(FIND("CONV",J30,1)),ISERROR(FIND("conv",J30,1)))) | AR30: =NOT(AND(ISERROR(FIND("CONV",K30,1)),ISERROR(FIND("conv",K30,1)))) | AS30: =NOT(AND(ISERROR(FIND("CONV",L30,1)),ISERROR(FIND("conv",L30,1))))
B31: 1 | C31: Gross distribution | M31: =SUM(Q31:Y31) | N31: =SUM(AA31:AI31) | O31: =SUM(AK31:AS31) | Q31: =IF(Q$30,ROUND(D31,0),0) | R31: =IF(R$30,ROUND(E31,0),0) | S31: =IF(S$30,ROUND(F31,0),0) | T31: =IF(T$30,ROUND(G31,0),0) | U31: =IF(U$30,ROUND(H31,0),0) | V31: =IF(V$30,ROUND(I31,0),0) | W31: =IF(W$30,ROUND(J31,0),0) | X31: =IF(X$30,ROUND(K31,0),0) | Y31: =IF(Y$30,ROUND(L31,0),0) | AA31: =IF(AA$30,ROUND(D31,0),0) | AB31: =IF(AB$30,ROUND(E31,0),0) | AC31: =IF(AC$30,ROUND(F31,0),0) | AD31: =IF(AD$30,ROUND(G31,0),0) | AE31: =IF(AE$30,ROUND(H31,0),0) | AF31: =IF(AF$30,ROUND(I31,0),0) | AG31: =IF(AG$30,ROUND(J31,0),0) | AH31: =IF(AH$30,ROUND(K31,0),0) | AI31: =IF(AI$30,ROUND(L31,0),0) | AK31: =IF(AK$30,ROUND(D31,0),0) | AL31: =IF(AL$30,ROUND(E31,0),0) | AM31: =IF(AM$30,ROUND(F31,0),0) | AN31: =IF(AN$30,ROUND(G31,0),0) | AO31: =IF(AO$30,ROUND(H31,0),0) | AP31: =IF(AP$30,ROUND(I31,0),0) | AQ31: =IF(AQ$30,ROUND(J31,0),0) | AR31: =IF(AR$30,ROUND(K31,0),0) | AS31: =IF(AS$30,ROUND(L31,0),0)
B32: 2a | C32: Taxable amount | M32: =SUM(Q32:Y32) | N32: =SUM(AA32:AI32) | O32: =IF(SUM(D32:L32)>0,"See note.","- - - -") | Q32: =IF(Q$30,ROUND(D32,0),0) | R32: =IF(R$30,ROUND(E32,0),0) | S32: =IF(S$30,ROUND(F32,0),0) | T32: =IF(T$30,ROUND(G32,0),0) | U32: =IF(U$30,ROUND(H32,0),0) | V32: =IF(V$30,ROUND(I32,0),0) | W32: =IF(W$30,ROUND(J32,0),0) | X32: =IF(X$30,ROUND(K32,0),0) | Y32: =IF(Y$30,ROUND(L32,0),0) | AA32: =IF(AA$30,ROUND(D32,0),0) | AB32: =IF(AB$30,ROUND(E32,0),0) | AC32: =IF(AC$30,ROUND(F32,0),0) | AD32: =IF(AD$30,ROUND(G32,0),0) | AE32: =IF(AE$30,ROUND(H32,0),0) | AF32: =IF(AF$30,ROUND(I32,0),0) | AG32: =IF(AG$30,ROUND(J32,0),0) | AH32: =IF(AH$30,ROUND(K32,0),0) | AI32: =IF(AI$30,ROUND(L32,0),0) | AK32: ="---" | AL32: ="---" | AM32: ="---" | AN32: ="---" | AO32: ="---" | AP32: ="---" | AQ32: ="---" | AR32: ="---" | AS32: ="---"
B33: 2b | C33: Taxable amount not determined / total distr. | M33: =" - - - -" | N33: =" - - - -" | O33: =" - - - -"
B34: 3 | C34: Capital gain (not included in box 2a) | M34: =SUM(Q34:Y34) | N34: =SUM(AA34:AI34) | O34: =SUM(AK34:AS34) | Q34: =IF(Q$30,ROUND(D34,0),0) | R34: =IF(R$30,ROUND(E34,0),0) | S34: =IF(S$30,ROUND(F34,0),0) | T34: =IF(T$30,ROUND(G34,0),0) | U34: =IF(U$30,ROUND(H34,0),0) | V34: =IF(V$30,ROUND(I34,0),0) | W34: =IF(W$30,ROUND(J34,0),0) | X34: =IF(X$30,ROUND(K34,0),0) | Y34: =IF(Y$30,ROUND(L34,0),0) | AA34: =IF(AA$30,ROUND(D34,0),0) | AB34: =IF(AB$30,ROUND(E34,0),0) | AC34: =IF(AC$30,ROUND(F34,0),0) | AD34: =IF(AD$30,ROUND(G34,0),0) | AE34: =IF(AE$30,ROUND(H34,0),0) | AF34: =IF(AF$30,ROUND(I34,0),0) | AG34: =IF(AG$30,ROUND(J34,0),0) | AH34: =IF(AH$30,ROUND(K34,0),0) | AI34: =IF(AI$30,ROUND(L34,0),0) | AK34: =IF(AK$30,ROUND(D34,0),0) | AL34: =IF(AL$30,ROUND(E34,0),0) | AM34: =IF(AM$30,ROUND(F34,0),0) | AN34: =IF(AN$30,ROUND(G34,0),0) | AO34: =IF(AO$30,ROUND(H34,0),0) | AP34: =IF(AP$30,ROUND(I34,0),0) | AQ34: =IF(AQ$30,ROUND(J34,0),0) | AR34: =IF(AR$30,ROUND(K34,0),0) | AS34: =IF(AS$30,ROUND(L34,0),0)
B35: 4 | C35: Federal income tax withheld | M35: =SUM(Q35:Y35) | N35: =SUM(AA35:AI35) | O35: =SUM(AK35:AS35) | Q35: =IF(Q$30,ROUND(D35,0),0) | R35: =IF(R$30,ROUND(E35,0),0) | S35: =IF(S$30,ROUND(F35,0),0) | T35: =IF(T$30,ROUND(G35,0),0) | U35: =IF(U$30,ROUND(H35,0),0) | V35: =IF(V$30,ROUND(I35,0),0) | W35: =IF(W$30,ROUND(J35,0),0) | X35: =IF(X$30,ROUND(K35,0),0) | Y35: =IF(Y$30,ROUND(L35,0),0) | AA35: =IF(AA$30,ROUND(D35,0),0) | AB35: =IF(AB$30,ROUND(E35,0),0) | AC35: =IF(AC$30,ROUND(F35,0),0) | AD35: =IF(AD$30,ROUND(G35,0),0) | AE35: =IF(AE$30,ROUND(H35,0),0) | AF35: =IF(AF$30,ROUND(I35,0),0) | AG35: =IF(AG$30,ROUND(J35,0),0) | AH35: =IF(AH$30,ROUND(K35,0),0) | AI35: =IF(AI$30,ROUND(L35,0),0) | AK35: =IF(AK$30,ROUND(D35,0),0) | AL35: =IF(AL$30,ROUND(E35,0),0) | AM35: =IF(AM$30,ROUND(F35,0),0) | AN35: =IF(AN$30,ROUND(G35,0),0) | AO35: =IF(AO$30,ROUND(H35,0),0) | AP35: =IF(AP$30,ROUND(I35,0),0) | AQ35: =IF(AQ$30,ROUND(J35,0),0) | AR35: =IF(AR$30,ROUND(K35,0),0) | AS35: =IF(AS$30,ROUND(L35,0),0)
B36: 5 | C36: Employee contributions / Insurance premiums / Designated Roth IRA contributions | M36: =SUM(Q36:Y36) | N36: =SUM(AA36:AI36) | O36: =SUM(AK36:AS36) | Q36: =IF(Q$30,ROUND(D36,0),0) | R36: =IF(R$30,ROUND(E36,0),0) | S36: =IF(S$30,ROUND(F36,0),0) | T36: =IF(T$30,ROUND(G36,0),0) | U36: =IF(U$30,ROUND(H36,0),0) | V36: =IF(V$30,ROUND(I36,0),0) | W36: =IF(W$30,ROUND(J36,0),0) | X36: =IF(X$30,ROUND(K36,0),0) | Y36: =IF(Y$30,ROUND(L36,0),0) | AA36: =IF(AA$30,ROUND(D36,0),0) | AB36: =IF(AB$30,ROUND(E36,0),0) | AC36: =IF(AC$30,ROUND(F36,0),0) | AD36: =IF(AD$30,ROUND(G36,0),0) | AE36: =IF(AE$30,ROUND(H36,0),0) | AF36: =IF(AF$30,ROUND(I36,0),0) | AG36: =IF(AG$30,ROUND(J36,0),0) | AH36: =IF(AH$30,ROUND(K36,0),0) | AI36: =IF(AI$30,ROUND(L36,0),0) | AK36: =IF(AK$30,ROUND(D36,0),0) | AL36: =IF(AL$30,ROUND(E36,0),0) | AM36: =IF(AM$30,ROUND(F36,0),0) | AN36: =IF(AN$30,ROUND(G36,0),0) | AO36: =IF(AO$30,ROUND(H36,0),0) | AP36: =IF(AP$30,ROUND(I36,0),0) | AQ36: =IF(AQ$30,ROUND(J36,0),0) | AR36: =IF(AR$30,ROUND(K36,0),0) | AS36: =IF(AS$30,ROUND(L36,0),0)
B37: 6 | C37: Net unrealized appreciation in employer's securities | M37: =SUM(Q37:Y37) | N37: =SUM(AA37:AI37) | O37: =SUM(AK37:AS37) | Q37: =IF(Q$30,ROUND(D37,0),0) | R37: =IF(R$30,ROUND(E37,0),0) | S37: =IF(S$30,ROUND(F37,0),0) | T37: =IF(T$30,ROUND(G37,0),0) | U37: =IF(U$30,ROUND(H37,0),0) | V37: =IF(V$30,ROUND(I37,0),0) | W37: =IF(W$30,ROUND(J37,0),0) | X37: =IF(X$30,ROUND(K37,0),0) | Y37: =IF(Y$30,ROUND(L37,0),0) | AA37: =IF(AA$30,ROUND(D37,0),0) | AB37: =IF(AB$30,ROUND(E37,0),0) | AC37: =IF(AC$30,ROUND(F37,0),0) | AD37: =IF(AD$30,ROUND(G37,0),0) | AE37: =IF(AE$30,ROUND(H37,0),0) | AF37: =IF(AF$30,ROUND(I37,0),0) | AG37: =IF(AG$30,ROUND(J37,0),0) | AH37: =IF(AH$30,ROUND(K37,0),0) | AI37: =IF(AI$30,ROUND(L37,0),0) | AK37: =IF(AK$30,ROUND(D37,0),0) | AL37: =IF(AL$30,ROUND(E37,0),0) | AM37: =IF(AM$30,ROUND(F37,0),0) | AN37: =IF(AN$30,ROUND(G37,0),0) | AO37: =IF(AO$30,ROUND(H37,0),0) | AP37: =IF(AP$30,ROUND(I37,0),0) | AQ37: =IF(AQ$30,ROUND(J37,0),0) | AR37: =IF(AR$30,ROUND(K37,0),0) | AS37: =IF(AS$30,ROUND(L37,0),0)
B38: 7 | C38: Distribution code(s) (Code D only) | M38: =" - - - -" | N38: =" - - - -" | O38: =" - - - -"
B39: 8 | C39: Other | M39: =SUM(Q39:Y39) | N39: =SUM(AA39:AI39) | O39: =SUM(AK39:AS39) | Q39: =IF(Q$30,ROUND(D39,0),0) | R39: =IF(R$30,ROUND(E39,0),0) | S39: =IF(S$30,ROUND(F39,0),0) | T39: =IF(T$30,ROUND(G39,0),0) | U39: =IF(U$30,ROUND(H39,0),0) | V39: =IF(V$30,ROUND(I39,0),0) | W39: =IF(W$30,ROUND(J39,0),0) | X39: =IF(X$30,ROUND(K39,0),0) | Y39: =IF(Y$30,ROUND(L39,0),0) | AA39: =IF(AA$30,ROUND(D39,0),0) | AB39: =IF(AB$30,ROUND(E39,0),0) | AC39: =IF(AC$30,ROUND(F39,0),0) | AD39: =IF(AD$30,ROUND(G39,0),0) | AE39: =IF(AE$30,ROUND(H39,0),0) | AF39: =IF(AF$30,ROUND(I39,0),0) | AG39: =IF(AG$30,ROUND(J39,0),0) | AH39: =IF(AH$30,ROUND(K39,0),0) | AI39: =IF(AI$30,ROUND(L39,0),0) | AK39: =IF(AK$30,ROUND(D39,0),0) | AL39: =IF(AL$30,ROUND(E39,0),0) | AM39: =IF(AM$30,ROUND(F39,0),0) | AN39: =IF(AN$30,ROUND(G39,0),0) | AO39: =IF(AO$30,ROUND(H39,0),0) | AP39: =IF(AP$30,ROUND(I39,0),0) | AQ39: =IF(AQ$30,ROUND(J39,0),0) | AR39: =IF(AR$30,ROUND(K39,0),0) | AS39: =IF(AS$30,ROUND(L39,0),0)
B40: 9a | C40: Your percentage of total distribution | M40: =SUM(Q40:Y40) | N40: =SUM(AA40:AI40) | O40: =SUM(AK40:AS40) | Q40: =IF(Q30,D40,0) | R40: =IF(R30,E40,0) | S40: =IF(S30,F40,0) | T40: =IF(T30,G40,0) | U40: =IF(U30,H40,0) | V40: =IF(V30,I40,0) | W40: =IF(W30,J40,0) | X40: =IF(X30,K40,0) | Y40: =IF(Y30,L40,0) | AA40: =IF(AA30,D40,0) | AB40: =IF(AB30,E40,0) | AC40: =IF(AC30,F40,0) | AD40: =IF(AD30,G40,0) | AE40: =IF(AE30,H40,0) | AF40: =IF(AF30,I40,0) | AG40: =IF(AG30,J40,0) | AH40: =IF(AH30,K40,0) | AI40: =IF(AI30,L40,0) | AK40: =IF(AK30,D40,0) | AL40: =IF(AL30,E40,0) | AM40: =IF(AM30,F40,0) | AN40: =IF(AN30,G40,0) | AO40: =IF(AO30,H40,0) | AP40: =IF(AP30,I40,0) | AQ40: =IF(AQ30,J40,0) | AR40: =IF(AR30,K40,0) | AS40: =IF(AS30,L40,0)
B41: 9b | C41: Total employee contributions | M41: =SUM(Q41:Y41) | N41: =SUM(AA41:AI41) | O41: =SUM(AK41:AS41) | Q41: =IF(Q$30,ROUND(D41,0),0) | R41: =IF(R$30,ROUND(E41,0),0) | S41: =IF(S$30,ROUND(F41,0),0) | T41: =IF(T$30,ROUND(G41,0),0) | U41: =IF(U$30,ROUND(H41,0),0) | V41: =IF(V$30,ROUND(I41,0),0) | W41: =IF(W$30,ROUND(J41,0),0) | X41: =IF(X$30,ROUND(K41,0),0) | Y41: =IF(Y$30,ROUND(L41,0),0) | AA41: =IF(AA$30,ROUND(D41,0),0) | AB41: =IF(AB$30,ROUND(E41,0),0) | AC41: =IF(AC$30,ROUND(F41,0),0) | AD41: =IF(AD$30,ROUND(G41,0),0) | AE41: =IF(AE$30,ROUND(H41,0),0) | AF41: =IF(AF$30,ROUND(I41,0),0) | AG41: =IF(AG$30,ROUND(J41,0),0) | AH41: =IF(AH$30,ROUND(K41,0),0) | AI41: =IF(AI$30,ROUND(L41,0),0) | AK41: =IF(AK$30,ROUND(D41,0),0) | AL41: =IF(AL$30,ROUND(E41,0),0) | AM41: =IF(AM$30,ROUND(F41,0),0) | AN41: =IF(AN$30,ROUND(G41,0),0) | AO41: =IF(AO$30,ROUND(H41,0),0) | AP41: =IF(AP$30,ROUND(I41,0),0) | AQ41: =IF(AQ$30,ROUND(J41,0),0) | AR41: =IF(AR$30,ROUND(K41,0),0) | AS41: =IF(AS$30,ROUND(L41,0),0)
B42: 10 | C42: Amount allocable to IRR within 5 years | M42: =SUM(Q42:Y42) | N42: =SUM(AA42:AI42) | O42: =SUM(AK42:AS42) | Q42: =IF(Q$30,ROUND(D42,0),0) | R42: =IF(R$30,ROUND(E42,0),0) | S42: =IF(S$30,ROUND(F42,0),0) | T42: =IF(T$30,ROUND(G42,0),0) | U42: =IF(U$30,ROUND(H42,0),0) | V42: =IF(V$30,ROUND(I42,0),0) | W42: =IF(W$30,ROUND(J42,0),0) | X42: =IF(X$30,ROUND(K42,0),0) | Y42: =IF(Y$30,ROUND(L42,0),0) | AA42: =IF(AA$30,ROUND(D42,0),0) | AB42: =IF(AB$30,ROUND(E42,0),0) | AC42: =IF(AC$30,ROUND(F42,0),0) | AD42: =IF(AD$30,ROUND(G42,0),0) | AE42: =IF(AE$30,ROUND(H42,0),0) | AF42: =IF(AF$30,ROUND(I42,0),0) | AG42: =IF(AG$30,ROUND(J42,0),0) | AH42: =IF(AH$30,ROUND(K42,0),0) | AI42: =IF(AI$30,ROUND(L42,0),0) | AK42: =IF(AK$30,ROUND(D42,0),0) | AL42: =IF(AL$30,ROUND(E42,0),0) | AM42: =IF(AM$30,ROUND(F42,0),0) | AN42: =IF(AN$30,ROUND(G42,0),0) | AO42: =IF(AO$30,ROUND(H42,0),0) | AP42: =IF(AP$30,ROUND(I42,0),0) | AQ42: =IF(AQ$30,ROUND(J42,0),0) | AR42: =IF(AR$30,ROUND(K42,0),0) | AS42: =IF(AS$30,ROUND(L42,0),0)
B43: 11 | C43: 1st year of desig. Roth contrib. | M43: =SUM(Q43:Y43) | N43: =SUM(AA43:AI43) | O43: =SUM(AK43:AS43) | Q43: =IF(Q$30,ROUND(D43,0),0) | R43: =IF(R$30,ROUND(E43,0),0) | S43: =IF(S$30,ROUND(F43,0),0) | T43: =IF(T$30,ROUND(G43,0),0) | U43: =IF(U$30,ROUND(H43,0),0) | V43: =IF(V$30,ROUND(I43,0),0) | W43: =IF(W$30,ROUND(J43,0),0) | X43: =IF(X$30,ROUND(K43,0),0) | Y43: =IF(Y$30,ROUND(L43,0),0) | AA43: =IF(AA$30,ROUND(D43,0),0) | AB43: =IF(AB$30,ROUND(E43,0),0) | AC43: =IF(AC$30,ROUND(F43,0),0) | AD43: =IF(AD$30,ROUND(G43,0),0) | AE43: =IF(AE$30,ROUND(H43,0),0) | AF43: =IF(AF$30,ROUND(I43,0),0) | AG43: =IF(AG$30,ROUND(J43,0),0) | AH43: =IF(AH$30,ROUND(K43,0),0) | AI43: =IF(AI$30,ROUND(L43,0),0) | AK43: =IF(AK$30,ROUND(D43,0),0) | AL43: =IF(AL$30,ROUND(E43,0),0) | AM43: =IF(AM$30,ROUND(F43,0),0) | AN43: =IF(AN$30,ROUND(G43,0),0) | AO43: =IF(AO$30,ROUND(H43,0),0) | AP43: =IF(AP$30,ROUND(I43,0),0) | AQ43: =IF(AQ$30,ROUND(J43,0),0) | AR43: =IF(AR$30,ROUND(K43,0),0) | AS43: =IF(AS$30,ROUND(L43,0),0)
B44: 12 | C44: FATCA filing requirement | M44: =" - - - -" | N44: =" - - - -" | O44: =" - - - -" | Q44: =IF(Q$30,ROUND(D44,0),0) | R44: =IF(R$30,ROUND(E44,0),0) | S44: =IF(S$30,ROUND(F44,0),0) | T44: =IF(T$30,ROUND(G44,0),0) | U44: =IF(U$30,ROUND(H44,0),0) | V44: =IF(V$30,ROUND(I44,0),0) | W44: =IF(W$30,ROUND(J44,0),0) | X44: =IF(X$30,ROUND(K44,0),0) | Y44: =IF(Y$30,ROUND(L44,0),0) | AA44: =IF(AA$30,ROUND(D44,0),0) | AB44: =IF(AB$30,ROUND(E44,0),0) | AC44: =IF(AC$30,ROUND(F44,0),0) | AD44: =IF(AD$30,ROUND(G44,0),0) | AE44: =IF(AE$30,ROUND(H44,0),0) | AF44: =IF(AF$30,ROUND(I44,0),0) | AG44: =IF(AG$30,ROUND(J44,0),0) | AH44: =IF(AH$30,ROUND(K44,0),0) | AI44: =IF(AI$30,ROUND(L44,0),0) | AK44: =IF(AK$30,ROUND(D44,0),0) | AL44: =IF(AL$30,ROUND(E44,0),0) | AM44: =IF(AM$30,ROUND(F44,0),0) | AN44: =IF(AN$30,ROUND(G44,0),0) | AO44: =IF(AO$30,ROUND(H44,0),0) | AP44: =IF(AP$30,ROUND(I44,0),0) | AQ44: =IF(AQ$30,ROUND(J44,0),0) | AR44: =IF(AR$30,ROUND(K44,0),0) | AS44: =IF(AS$30,ROUND(L44,0),0)
B45: 13 | C45: Date of Payment | M45: =" - - - -" | N45: =" - - - -" | O45: =" - - - -" | Q45: =IF(Q$30,ROUND(D45,0),0) | R45: =IF(R$30,ROUND(E45,0),0) | S45: =IF(S$30,ROUND(F45,0),0) | T45: =IF(T$30,ROUND(G45,0),0) | U45: =IF(U$30,ROUND(H45,0),0) | V45: =IF(V$30,ROUND(I45,0),0) | W45: =IF(W$30,ROUND(J45,0),0) | X45: =IF(X$30,ROUND(K45,0),0) | Y45: =IF(Y$30,ROUND(L45,0),0) | AA45: =IF(AA$30,ROUND(D45,0),0) | AB45: =IF(AB$30,ROUND(E45,0),0) | AC45: =IF(AC$30,ROUND(F45,0),0) | AD45: =IF(AD$30,ROUND(G45,0),0) | AE45: =IF(AE$30,ROUND(H45,0),0) | AF45: =IF(AF$30,ROUND(I45,0),0) | AG45: =IF(AG$30,ROUND(J45,0),0) | AH45: =IF(AH$30,ROUND(K45,0),0) | AI45: =IF(AI$30,ROUND(L45,0),0) | AK45: =IF(AK$30,ROUND(D45,0),0) | AL45: =IF(AL$30,ROUND(E45,0),0) | AM45: =IF(AM$30,ROUND(F45,0),0) | AN45: =IF(AN$30,ROUND(G45,0),0) | AO45: =IF(AO$30,ROUND(H45,0),0) | AP45: =IF(AP$30,ROUND(I45,0),0) | AQ45: =IF(AQ$30,ROUND(J45,0),0) | AR45: =IF(AR$30,ROUND(K45,0),0) | AS45: =IF(AS$30,ROUND(L45,0),0)
B46: 14 | C46: State tax withheld | M46: =SUM(Q46:Y46) | N46: =SUM(AA46:AI46) | O46: =SUM(AK46:AS46) | Q46: =IF(Q$30,ROUND(D46,0),0) | R46: =IF(R$30,ROUND(E46,0),0) | S46: =IF(S$30,ROUND(F46,0),0) | T46: =IF(T$30,ROUND(G46,0),0) | U46: =IF(U$30,ROUND(H46,0),0) | V46: =IF(V$30,ROUND(I46,0),0) | W46: =IF(W$30,ROUND(J46,0),0) | X46: =IF(X$30,ROUND(K46,0),0) | Y46: =IF(Y$30,ROUND(L46,0),0) | AA46: =IF(AA$30,ROUND(D46,0),0) | AB46: =IF(AB$30,ROUND(E46,0),0) | AC46: =IF(AC$30,ROUND(F46,0),0) | AD46: =IF(AD$30,ROUND(G46,0),0) | AE46: =IF(AE$30,ROUND(H46,0),0) | AF46: =IF(AF$30,ROUND(I46,0),0) | AG46: =IF(AG$30,ROUND(J46,0),0) | AH46: =IF(AH$30,ROUND(K46,0),0) | AI46: =IF(AI$30,ROUND(L46,0),0) | AK46: =IF(AK$30,ROUND(D46,0),0) | AL46: =IF(AL$30,ROUND(E46,0),0) | AM46: =IF(AM$30,ROUND(F46,0),0) | AN46: =IF(AN$30,ROUND(G46,0),0) | AO46: =IF(AO$30,ROUND(H46,0),0) | AP46: =IF(AP$30,ROUND(I46,0),0) | AQ46: =IF(AQ$30,ROUND(J46,0),0) | AR46: =IF(AR$30,ROUND(K46,0),0) | AS46: =IF(AS$30,ROUND(L46,0),0)
B47: 15 | C47: State/payer's state no. | M47: =" - - - -" | N47: =" - - - -" | O47: =" - - - -"
B48: 16 | C48: State distribution | M48: =SUM(Q48:Y48) | N48: =SUM(AA48:AI48) | O48: =SUM(AK48:AS48) | Q48: =IF(Q$30,ROUND(D48,0),0) | R48: =IF(R$30,ROUND(E48,0),0) | S48: =IF(S$30,ROUND(F48,0),0) | T48: =IF(T$30,ROUND(G48,0),0) | U48: =IF(U$30,ROUND(H48,0),0) | V48: =IF(V$30,ROUND(I48,0),0) | W48: =IF(W$30,ROUND(J48,0),0) | X48: =IF(X$30,ROUND(K48,0),0) | Y48: =IF(Y$30,ROUND(L48,0),0) | AA48: =IF(AA$30,ROUND(D48,0),0) | AB48: =IF(AB$30,ROUND(E48,0),0) | AC48: =IF(AC$30,ROUND(F48,0),0) | AD48: =IF(AD$30,ROUND(G48,0),0) | AE48: =IF(AE$30,ROUND(H48,0),0) | AF48: =IF(AF$30,ROUND(I48,0),0) | AG48: =IF(AG$30,ROUND(J48,0),0) | AH48: =IF(AH$30,ROUND(K48,0),0) | AI48: =IF(AI$30,ROUND(L48,0),0) | AK48: =IF(AK$30,ROUND(D48,0),0) | AL48: =IF(AL$30,ROUND(E48,0),0) | AM48: =IF(AM$30,ROUND(F48,0),0) | AN48: =IF(AN$30,ROUND(G48,0),0) | AO48: =IF(AO$30,ROUND(H48,0),0) | AP48: =IF(AP$30,ROUND(I48,0),0) | AQ48: =IF(AQ$30,ROUND(J48,0),0) | AR48: =IF(AR$30,ROUND(K48,0),0) | AS48: =IF(AS$30,ROUND(L48,0),0)
B49: 17 | C49: Local tax withheld | M49: =SUM(Q49:Y49) | N49: =SUM(AA49:AI49) | O49: =SUM(AK49:AS49) | Q49: =IF(Q$30,ROUND(D49,0),0) | R49: =IF(R$30,ROUND(E49,0),0) | S49: =IF(S$30,ROUND(F49,0),0) | T49: =IF(T$30,ROUND(G49,0),0) | U49: =IF(U$30,ROUND(H49,0),0) | V49: =IF(V$30,ROUND(I49,0),0) | W49: =IF(W$30,ROUND(J49,0),0) | X49: =IF(X$30,ROUND(K49,0),0) | Y49: =IF(Y$30,ROUND(L49,0),0) | AA49: =IF(AA$30,ROUND(D49,0),0) | AB49: =IF(AB$30,ROUND(E49,0),0) | AC49: =IF(AC$30,ROUND(F49,0),0) | AD49: =IF(AD$30,ROUND(G49,0),0) | AE49: =IF(AE$30,ROUND(H49,0),0) | AF49: =IF(AF$30,ROUND(I49,0),0) | AG49: =IF(AG$30,ROUND(J49,0),0) | AH49: =IF(AH$30,ROUND(K49,0),0) | AI49: =IF(AI$30,ROUND(L49,0),0) | AK49: =IF(AK$30,ROUND(D49,0),0) | AL49: =IF(AL$30,ROUND(E49,0),0) | AM49: =IF(AM$30,ROUND(F49,0),0) | AN49: =IF(AN$30,ROUND(G49,0),0) | AO49: =IF(AO$30,ROUND(H49,0),0) | AP49: =IF(AP$30,ROUND(I49,0),0) | AQ49: =IF(AQ$30,ROUND(J49,0),0) | AR49: =IF(AR$30,ROUND(K49,0),0) | AS49: =IF(AS$30,ROUND(L49,0),0)
B50: 18 | C50: Name of locality | D50: =OR(D30="CONV",D30="conv") | E50: =OR(E30="CONV",E30="conv") | F50: =OR(F30="CONV",F30="conv") | G50: =OR(G30="CONV",G30="conv") | H50: =OR(H30="CONV",H30="conv") | I50: =OR(I30="CONV",I30="conv") | J50: =OR(J30="CONV",J30="conv") | K50: =OR(K30="CONV",K30="conv") | L50: =OR(L30="CONV",L30="conv") | M50: =" - - - -" | N50: =" - - - -" | O50: =" - - - -" | Q50: =IF(Q$30,ROUND(D50,0),0) | R50: =IF(R$30,ROUND(E50,0),0) | S50: =IF(S$30,ROUND(F50,0),0) | T50: =IF(T$30,ROUND(G50,0),0) | U50: =IF(U$30,ROUND(H50,0),0) | V50: =IF(V$30,ROUND(I50,0),0) | W50: =IF(W$30,ROUND(J50,0),0) | X50: =IF(X$30,ROUND(K50,0),0) | Y50: =IF(Y$30,ROUND(L50,0),0)
B51: 19 | C51: Local distribution | M51: =SUM(Q51:Y51) | N51: =SUM(AA51:AI51) | O51: =SUM(AK51:AS51) | Q51: =IF(Q$30,ROUND(D51,0),0) | R51: =IF(R$30,ROUND(E51,0),0) | S51: =IF(S$30,ROUND(F51,0),0) | T51: =IF(T$30,ROUND(G51,0),0) | U51: =IF(U$30,ROUND(H51,0),0) | V51: =IF(V$30,ROUND(I51,0),0) | W51: =IF(W$30,ROUND(J51,0),0) | X51: =IF(X$30,ROUND(K51,0),0) | Y51: =IF(Y$30,ROUND(L51,0),0) | AA51: =IF(AA$30,ROUND(D51,0),0) | AB51: =IF(AB$30,ROUND(E51,0),0) | AC51: =IF(AC$30,ROUND(F51,0),0) | AD51: =IF(AD$30,ROUND(G51,0),0) | AE51: =IF(AE$30,ROUND(H51,0),0) | AF51: =IF(AF$30,ROUND(I51,0),0) | AG51: =IF(AG$30,ROUND(J51,0),0) | AH51: =IF(AH$30,ROUND(K51,0),0) | AI51: =IF(AI$30,ROUND(L51,0),0) | AK51: =IF(AK$30,ROUND(D51,0),0) | AL51: =IF(AL$30,ROUND(E51,0),0) | AM51: =IF(AM$30,ROUND(F51,0),0) | AN51: =IF(AN$30,ROUND(G51,0),0) | AO51: =IF(AO$30,ROUND(H51,0),0) | AP51: =IF(AP$30,ROUND(I51,0),0) | AQ51: =IF(AQ$30,ROUND(J51,0),0) | AR51: =IF(AR$30,ROUND(K51,0),0) | AS51: =IF(AS$30,ROUND(L51,0),0)
B52: Only bolded amounts are used in this spreadsheet. | D52: =OR(D50:L50) | H52: =IF(D52,"For IRA conversions, leave line 2a blank and complete "&CHAR(10)&"Form 8606.","")
D53: =IF(OR(LEFT(D38,1)="D",LEFT(D38,1)="d"),D32,"") | E53: =IF(OR(LEFT(E38,1)="D",LEFT(E38,1)="d"),E32,"") | F53: =IF(OR(LEFT(F38,1)="D",LEFT(F38,1)="d"),F32,"") | G53: =IF(OR(LEFT(G38,1)="D",LEFT(G38,1)="d"),G32,"") | H53: =IF(OR(LEFT(H38,1)="D",LEFT(H38,1)="d"),H32,"") | I53: =IF(OR(LEFT(I38,1)="D",LEFT(I38,1)="d"),I32,"") | J53: =IF(OR(LEFT(J38,1)="D",LEFT(J38,1)="d"),J32,"") | K53: =IF(OR(LEFT(K38,1)="D",LEFT(K38,1)="d"),K32,"") | L53: =IF(OR(LEFT(L38,1)="D",LEFT(L38,1)="d"),L32,"") | N53: =SUM(D53:L53) | O53: =SUM(E53:M53)
D54: =IF(OR(LEFT(D38,1)="D",LEFT(D38,1)="d"),SUM(D46,D49),"") | E54: =IF(OR(LEFT(E38,1)="D",LEFT(E38,1)="d"),SUM(E46,E49),"") | F54: =IF(OR(LEFT(F38,1)="D",LEFT(F38,1)="d"),SUM(F46,F49),"") | G54: =IF(OR(LEFT(G38,1)="D",LEFT(G38,1)="d"),SUM(G46,G49),"") | H54: =IF(OR(LEFT(H38,1)="D",LEFT(H38,1)="d"),SUM(H46,H49),"") | I54: =IF(OR(LEFT(I38,1)="D",LEFT(I38,1)="d"),SUM(I46,I49),"") | J54: =IF(OR(LEFT(J38,1)="D",LEFT(J38,1)="d"),SUM(J46,J49),"") | K54: =IF(OR(LEFT(K38,1)="D",LEFT(K38,1)="d"),SUM(K46,K49),"") | L54: =IF(OR(LEFT(L38,1)="D",LEFT(L38,1)="d"),SUM(L46,L49),"") | N54: =SUM(D54:L54) | O54: =SUM(E54:M54)
B55: Information from Form 1099-R, Distributions From Pensions, Annuities, Retirement or Profit-Sharing Plans, IRAs, Insurance Contracts, etc.
C56: Total Distributions | D56: Total IRAs | E56: Total Pension / Annuities | F56: Qualified Conversion to ROTH IRA
D57: IRA | E57: P/A | F57: CONV | G57: Used at: | J57: If your IRA is fully taxable, this spreadsheet will automatically enter
B58: 1 | C58: Gross distribution | D58: =SUM(M4,M31) | E58: =SUM(N4,N31) | F58: =SUM(O4,O31) | G58: Form 1040, Line 4a, 5a | I58: =IF(E58=0,0,ROUND(E58,0)) | J58: the total IRA distributions (from Form(s) 1099-R, box 2a) on line 4b;
B59: 2a | C59: Taxable amount | D59: =SUM(IRA_Taxable_You,IRA_Taxable_Spouse) | E59: =SUM(PA_Taxable_You,PA_Taxable_Spouse) | F59: =" - - - -" | G59: Form 1040, Line 4b, 5b | J59: do not make an entry on line 4a.
B60: 2b | C60: Taxable amount not determined / total distr. | D60: =" - - - -" | E60: =" - - - -" | F60: =" - - - -" | J60: If your pension or annuity is fully taxable, this spreadsheet will automatically
B61: 3 | C61: Capital gain (not included in box 2a) | D61: =SUM(M7,M34) | E61: =SUM(N7,N34) | F61: =SUM(O7,O34) | J61: enter the total pension or annuity distributions (from Form(s) 1099-R, box 2a)
B62: 4 | C62: Federal income tax withheld | D62: =SUM(M8,M35) | E62: =SUM(N8,N35) | F62: =SUM(O8,O35) | G62: 1040, line 25b | J62: on line 5b; do not make an entry on line 5a.
B63: 5 | C63: Employee contributions / Insurance premiums / Designated Roth IRA contributions | D63: =SUM(M9,M36) | E63: =SUM(N9,N36) | F63: =SUM(O9,O36)
B64: 6 | C64: Net unrealized appreciation in employer's securities | D64: =SUM(M10,M37) | E64: =SUM(N10,N37) | F64: =SUM(O10,O37) | J64: If your Form 1099-R doesn't show the taxable amount, you must use
B65: 7 | C65: Distribution code(s) (Portion of line 2a w/Code D) | D65: =" - - - -" | E65: =SUM(N26,N53) | F65: =" - - - -" | G65: Form 8960, Line 3 (for Dist. Code 'D' only) | J65: the General Rule explained in Pub. 939 to figure the taxable part to enter on
B66: 8 | C66: Other | D66: =" - - - -" | E66: =" - - - -" | F66: =" - - - -" | J66: line 4b. But if your annuity starting date was after July 1, 1986,
B67: 9a | C67: Your percentage of total distribution | D67: =SUM(M13,M40) | E67: =SUM(N13,N40) | F67: =SUM(O13,O40) | J67: see Simplified Method, sheet "Lines 5ab (Simplified Meth WS)", to find out if you
B68: 9b | C68: Total employee contributions | D68: =SUM(M14,M41) | E68: =SUM(N14,N41) | F68: =SUM(O14,O41) | J68: must use that method to figure the taxable part. You can ask the IRS to figure the
B69: 10 | C69: Amount allocable to IRR within 5 years | D69: =SUM(M15,M42) | E69: =SUM(N15,N42) | F69: =SUM(O15,O42) | J69: taxable part for you for a $1,000 fee. For details, see Pub. 939.
B70: 11 | C70: 1st year of desig. Roth contrib. | D70: =SUM(M16,M43) | E70: =SUM(N16,N43) | F70: =SUM(O16,O43)
B71: 12 | C71: FATCA filing requirement | D71: =" - - - -" | E71: =" - - - -" | F71: =" - - - -"
B72: 13 | C72: Date of Payment | D72: =" - - - -" | E72: =" - - - -" | F72: =" - - - -"
B73: 14 | C73: State tax withheld | D73: =SUM(M19,M46) | E73: =SUM(N19,N46) | F73: =SUM(O19,O46) | G73: Sch. A, Line 5a | J73: The sheet labeled "Line 5ab (Simplified Meth WS)" is a stand-alone worksheet that
B74: 15 | C74: State/payer's state no. | D74: =" - - - -" | E74: =" - - - -" | F74: =" - - - -" | J74: is used to calculate the taxable amount of a pension or annuity that is not fully taxable.
B75: 16 | C75: State distribution | D75: =SUM(M21,M48) | E75: =SUM(N21,N48) | F75: =SUM(O21,O48)
B76: 17 | C76: Local tax withheld | D76: =SUM(M22,M49) | E76: =SUM(N22,N49) | F76: =SUM(O22,O49) | G76: Sch. A, Line 5a
B77: 18 | C77: Portion of state and local taxes w/Code D | D77: =" - - - -" | E77: =ROUND(SUM(N27,N54),0) | F77: =ROUND(SUM(O27,O54),0)
B78: 19 | C78: Local distribution | D78: =SUM(M24,M51) | E78: =SUM(N24,N51) | F78: =SUM(O24,O51)
B79: Only bolded amounts are used in this spreadsheet.
C86: Table of Contents

Sheet Lines 4ab (IRA Dist.)
C3: Lines 4a and 4b | J3: Note: This worksheet is intended to be used for one IRA at a time.
C4: IRA Distributions Worksheet
C6: You should receive a Form 1099-R showing the total amount of any distribution from your IRA before income tax or other deductions were withheld. This amount should be shown in box 1 of Form 1099-R.
C7: Unless otherwise noted in the line 4a and 4b instructions, an IRA includes a traditional IRA, Roth IRA, simplified employee pension (SEP) IRA, and a savings incentive match plan for employees (SIMPLE) IRA.
A9: =OR(A13,A27,A46,A64) | C9: =IF(OR(A34,A35),K27&" AND "&Q32,IF(A27,K27&" AND "&Q27,IF(AND(A49,NOT(A27)),P46&" AND "&L49&" AND "&H50,IF(A48,P46&" AND "&L48&" AND "&H50,IF(A18,H13&" AND "&K18&" "&G20,IF(AND(A19,NOT(A27)),H13&" AND "&K19&". "&G20,IF(A66,S64&" AND "&Q66&" AND "&H69,IF(A9,"See below.","Except as provided next, leave line 4a blank AND enter the total distribution (from Form 1099-R, box 1) on line 4b."))))))))
C11: TIP: | D11: For purposes of these Exceptions, Roth IRA includes Roth SEP IRA and Roth SIMPLE IRAs.
A13: =OR(A18,AND((A19),NOT(A27))) | D13: =IF(A13,"X","") | G13: Exception 1. | H13: Enter the total distribution on line 4a | L13: if you rolled over part or all of the distribution from one:
H15: · Roth IRA to another Roth IRA, or
H16: · IRA (other than a Roth IRA) to a qualified plan or another IRA (other than a Roth IRA).
A18: =F18<>"" | G18: If the total distribution was rolled over, | K18: enter -0- on line 4b.
A19: =F19<>"" | G19: If the total distribution wasn't rolled over, | K19: enter the part not rolled over on line 4b | P19: unless Exception 2 applies to the part not rolled over.
G20: Also enter “Rollover” next to line 4b.
G22: Generally, a rollover must be made within 60 days after the day you received the distribution. For more details on rollovers, see Pub. 590-A and Pub. 590-B.
G24: ="If you rolled over the distribution into a qualified plan or you made the rollover in "&TaxYear+1&", include a statement explaining what you did. "
A27: =OR(A29,A32,A34,A35,A37,A39,A41,A43) | D27: =IF(A27,"X","") | G27: Exception 2. | H27: If any of the following apply, | K27: =IF(A27,"Enter the total distribution on line 4a","enter the total distribution on line 4a") | P27: and | Q27: see Form 8606 and its instructions to figure the amount to enter on line 4b.
A28: =AND(OR(A29,A32,A37,A39,A41,A43),NOT(A34),NOT(A35))
A29: =E29<>"" | G29: 1. | H29: ="You received a distribution from an IRA (other than a Roth IRA) and you made nondeductible contributions to any of your traditional or SEP IRAs for "&TaxYear&" or an earlier year. "
H30: ="If you made nondeductible contributions to these IRAs for "&TaxYear&", also see Pub. 590-A and Pub. 590-B."
A32: =E32<>"" | G32: 2. | H32: You received a distribution from a Roth IRA. But if either (a) or (b) below applies, | Q32: enter -0- on line 4b; you don’t have to see Form 8606 or its instructions.
A34: =F34<>"" | H34: a. Distribution code T is shown in box 7 of Form 1099-R and you made a contribution (including a conversion) to a Roth IRA for 2016 or an earlier year.
A35: =F35<>"" | H35: b. Distribution code Q is shown in box 7 of Form 1099-R.
A37: =E37<>"" | G37: 3. | H37: ="You converted part or all of a traditional, SEP, or SIMPLE IRA to a Roth IRA in "&TaxYear&"."
A39: =E39<>"" | G39: 4. | H39: ="You had a "&TaxYear-1&" or "&TaxYear&" IRA contribution returned to you, with the related earnings or less any loss, by the due date (including extensions) of your tax return for that year."
A41: =E41<>"" | G41: 5. | H41: ="You made excess contributions to your IRA for an earlier year and had them returned to you in "&TaxYear&"."
A43: =E43<>"" | G43: 6. | H43: You re-characterized part or all of a contribution to a Roth IRA as a contribution to another type of IRA, or vice versa.
A46: =OR(A48,AND(A49,NOT(A27))) | D46: =IF(A46,"X","") | G46: Exception 3. | H46: If all or part of the distribution is a qualified charitable distribution (QCD), | P46: =IF(IRA_QCD," Enter the total distribution on line 4a","enter the total distribution on line 4a.")
A48: =F48<>"" | G48: 1. | H48: If the total amount distributed is a QCD, | L48: =IF(A48,"enter -0- on line 4b","enter -0- on line 4b.")
A49: =F49<>"" | G49: 2. | H49: If only part of the distribution is a QCD, | L49: enter the part that is not a QCD on line 4b | R49: unless Exception 2 applies to that part.
H50: =IF(AND(IRA_QCD,NOT(A27)),"enter “QCD” next to line 4b.","Enter “QCD” next to line 4b.")
H52: A QCD is a distribution made directly by the trustee of your IRA (other than an ongoing SEP or SIMPLE IRA) to an organization eligible to receive tax-deductible
H53: contributions (with certain exceptions). You must have been at least age 70 1/2 when the distribution was made.
H55: Generally, your total QCDs for the year can't be more than $100,000. This includes any amount (up to $50,000) of a one-time QCD to a split-interest entity.
H56: If you file a joint return, the same rules apply to your spouse.
H58: The amount of the QCD is limited to the amount that would otherwise be included in your income.
H60: If your IRA includes nondeductible contributions, the distribution is first considered to be paid out of otherwise taxable income. See Pub. 590-B for details.
G61: CAUTION! | H61: You can't claim a charitable contribution deduction for any QCD not included in your income.
A64: =OR(A66,AND(A67,NOT(A27))) | D64: =IF(A64,"X","") | G64: Exception 4. | H64: If all or part of the distribution is a health savings account (HSA) funding distribution (HFD), | S64: =IF(AND(IRA_HFD,NOT(A27)),"Enter the total distribution on line 4a","enter the total distribution on line 4a.")
A66: =F66<>"" | G66: 1. | H66: If the total amount distributed is an HFD and you elect to exclude it from income, | Q66: =IF(AND(IRA_HFD,NOT(A27)),"enter -0- on line 4b","enter -0- on line 4b.")
A67: =F67<>"" | G67: 2. | H67: If only part of the distribution is an HFD and you elect to exclude that part from income,
H68: enter the part that isn't an HFD on line 4b | M68: unless Exception 2 applies to that part.
H69: =IF(AND(IRA_HFD,NOT(A27)),"enter “HFD” next to line 4b.","Enter “HFD” next to line 4b.")
H71: An HFD is a distribution made directly by the trustee of your IRA (other than an ongoing SEP or SIMPLE IRA) to your HSA.
H72: If eligible, you can generally elect to exclude an HFD from your income once in your lifetime.
H73: You can't exclude more than the limit on HSA contributions or more than the amount that would otherwise be included in your income.
H74: If your IRA includes nondeductible contributions, the HFD is first considered to be paid out of otherwise taxable income. See Pub. 969 for details.
G76: CAUTION! | H76: The amount of an HFD reduces the amount you can contribute to your HSA for the year.
H77: If you fail to maintain eligibility for an HSA for the 12 months following the month of the HFD, you may have to report the HFD as income and
H78: pay an additional tax. See Form 8889, Part III.
G80: More than one exception applies. If more than one exception applies, include a statement showing the amount of each exception, instead of making an entry next to line 4b.
G81: For example: “Line 4b – $1,000 Rollover and $500 HFD.” But you do not need to attach a statement if only Exception 2 and one other exception apply.
G83: More than one distribution. If you (or your spouse if filing jointly) received more than one distribution, figure the taxable amount of each distribution and
G84: Enter the total of the taxable amounts on line 4b. Enter the total amount of those distributions on line 4a.
C86: TIP: | D86: ="You must start receiving at least a minimum amount from your traditional IRA by April 1 of the year following the year you reach age 72 (age 73 if you reach age 72 in "&TaxYear&")."
D87: If you don’t receive the minimum distribution amount, you may have to pay an additional tax on the amount that should have been distributed.
D88: For details, including how to figure the minimum required distribution, see Pub. 590-B.
D90: CAUTION! | E90: You may have to pay an additional tax if you received an early distribution from your IRA and the total wasn't rolled over. See the instructions for Schedule 2, line 8, for details.
G92: More information. For more information about IRAs, see Pub. 590-A and Pub. 590-B.

Sheet SSA-1099
B1: Information from Form SSA-1099, Social Security Benefit Statement | N1: Notes
B3: 1 | C3: =IF(Name_1st_Yours="","Enter your name on sheet labeled '1040'",NameYours)
B4: 3 | C4: ="Benefits Paid in "&TaxYear
B5: 4 | C5: ="Benefits Repaid in "&TaxYear
B6: 5 | C6: ="Net Benefits for "&TaxYear&" (Box 3 minus Box 4)" | D6: =SUM(D4,-D5) | E6: Used on Notice 703, Line A (below)
B7: 6 | C7: Voluntary Federal income Tax Withheld | E7: Used in 1040, line 25b | G7: =ROUND(D7,0)
B8: 1 | C8: =IF(Name_1st_Sp="","Enter your spouse's name on the sheet labeled '1040'",NameSpouse)
B9: 3 | C9: ="Benefits Paid in "&TaxYear
B10: 4 | C10: ="Benefits Repaid in "&TaxYear
B11: 5 | C11: ="Net Benefits for "&TaxYear&" (Box 3 minus Box 4)" | D11: =SUM(D9,-D10) | E11: Used on Notice 703, Line A (below)
B12: 6 | C12: Voluntary Federal income Tax Withheld | E12: Used in 1040, line 25b | G12: =ROUND(D12,0)
C14: Notice 703 | I14: Department of the Treasury
C15: (Rev. October 2020) | I15: Internal Revenue Service
C16: Read This To See If Your Social Security Benefits May Be Taxable
C18: ="If your social security and/or SSI (supplemental security income) benefits were your only source of income for "&TaxYear&", you probably will not have to file a federal income tax return. See IRS Pub. 501, Exemptions, Standard Deduction, and Filing Information, or your tax return instructions to find out if you have to file a return." | D18: ="We developed this worksheet for you to see if your benefits may be taxable for "&TaxYear&". Fill in lines A through E."&CHAR(10)&CHAR(10)&"Do not use the worksheet below if any of the following apply to you; instead, go directly to IRS Pub. 915, Social Security and Equivalent Railroad Retirement Benefits."&CHAR(10)&CHAR(10)&"o You received Form RRB-1099, Form SSA-1042S, or Form RRB-1042S." | G18: o You exclude income from sources outside the United States or foreign housing, income earned by bona fide residents of American Samoa or Puerto Rico, interest income from series EE or I U.S. savings bonds issued after 1989, or employer-provided adoption benefits. | L18: Manual Override ê
C19: Note. If you plan to file a joint income tax return, include your spouse's amounts, if any, on lines A, C, and D
B20: A | C20: Enter the total amount from box 5 of all your Forms SSA-1099. Include the
C21: ="full amount of any lump-sum benefit payments received in "&TaxYear&", for "&TaxYear&" and" | M21: Line A is used in
C22: earlier years. . . . . . . . . . . . . . . . . . . . . . . . . . . . . . . . . . . . . . . . . . . . . . | D22: . . . . . . . . . . . . . . . . . . . . . . . . . . . . . . . . . . . . . . . . . . . . . | E22: . . . . . . . . . . . . . . . . . . . . . . . . . . . . . . . . . . . . . . . . . . . . . | F22: A | G22: =IF(L22<>"",ROUND(L22,0),ROUND(SUM(D6,D11),0)) | I22: 0.5 | M22: Sheet "Line 6ab (SS Bene)", line 1.
B23: B | C23: ="Multiply line A by "&TEXT(I22,"0%")&" ("&TEXT(I22,"0.00")&")" | G23: . . . . . . . . . . . . . . . . . . . . . . . . . . . . . . . . . . . . . . . . . . . . . . . . . . . | H23: B | I23: =ROUND(G22*I22,0)
B24: C | C24: Enter your total income that is taxable (excluding Line A), such as pensions, wages, interest, ordinary dividends, and capital gain distributions. Do not reduce your income by any items such as student loan interest deduction, the standard deduction (or itemized deductions), or
C25: exemptions . . . . . . . . . . . . . . . . . . . . . . . . . . . . . . . . . . . . . . . . . | H25: C | I25: =IF(L25<>"",ROUND(L25,0),M25) | M25: =SUM(Wages,TaxableInterest,OrdinaryDividends,IRA_Taxable,PA_Taxable,CapitalGains,Additional_Income)
B26: D | C26: Enter any tax-exempt interest such as interest on municipal bonds | G26: . . . . . . . . . . . . . . . . . . . . . | H26: D | I26: =IF(L26<>"",ROUND(L26,0),TaxExemptInt)
B27: E | C27: Add lines B, C, and D, and enter the total here. Then, read the information below | G27: . . . . . . . . . . . . . . | H27: E | I27: =SUM(I23,I25,I26) | M27: 32000
M28: 25000
C29: Part of your social security benefits may be taxable. | I29: =AND(M29<>0,I27>M29) | M29: =IF(OR(File_Single<>"",File_Head<>""),M28,IF(File_Marr_Joint<>"",M27,IF(AND(File_Marr_Sep<>"",LivedApart),M28,0)))
C30: ="Part of your social security benefits may be taxable if, for "&TaxYear&", item 1, 2, or 3 below applies to you:" | D30: If none of your benefits are taxable, but you must otherwise file a tax return, do the following | G30: Railroad Retirement Benefits, for rules on a lump-sum election you can make that may reduce the amount of your taxable benefits.
C31: ="1. You were single, a head of household, or a qualifying widow(er) and line E above is more than "&TEXT(M28,"$0,000")&"." | D31: o Enter the total amount from line A above on Form 1040, line 6a, and enter -0- on Form 1040, line 6b. | G31: Get More Information From the IRS
C32: =CHAR(10)&"2. You were married, would file jointly, and line E above is more than "&TEXT(M27,"$0,000")&"."&CHAR(10)&CHAR(10)&"3. You were married, would file separately, and line E above is more than zero (more than "&TEXT(M28,"$0,000")&" if you lived apart from your spouse for all of "&TaxYear&")." | D32: =CHAR(10)&"o If you were married, file separately, and lived apart from your spouse for all of "&TaxYear&", enter “D” to the right of the word “benefits” on Form 1040, line 6a." | G32: ="If you still have questions about whether your social security benefits are taxable, see IRS "&CHAR(10)&"Pub. 915 or your "&TaxYear&" federal income tax return instructions, or visit IRS.gov and enter 'social security income' in the search box. Go to www.irs.gov/Forms to view, download, or print all of the forms and publications you may need."
C33: ="If your figures show that part of"&CHAR(10)&"your benefits may be taxable, see"&CHAR(10)&"IRS Pub. 915, and Social Security"&CHAR(10)&"Benefits in your "&TaxYear&" federal"&CHAR(10)&"income tax return instructions." | D33: ="Note. If your figures show that part of your benefits may be taxable and you received benefits in "&TaxYear&" that were for a prior year, see IRS Pub. 915, Social Security and Equivalent"
D34: Do not return this notice to the SSA or the IRS. Keep it with your records.
C35: IRS.gov | I35: Catalog No. 61879N
C40: Table of Contents

Sheet Dependents
M1: =IF(BV3,"By entering a first name, last name, or relationship, 'Default' SSNs are automatically generated here."&CHAR(10)&"These may be used in lieu of real SSNs.","") | Y1: To be counted as a qualifying child for Earned Income Credit (EIC) purposes, a child must: - be under 19 years old, - be a full-time student under 24 years old, or - be permanently and totally disabled AND - have lived with you, in the U.S., for at least half of the tax year. | AK1: =IF(BY3,"Enter child/dependent's birthdate to ensure accurate tax credit determination - unless permanently and totally disabled.","")
C2: To be counted as your dependent, that person must: - be a qualifying child or dependent - have a valid Social Security Number - receive at least 1/2 of support from you - be a US citizen, national, or resident alien, or resident of Canada or Mexico See general rules for dependents, below. | BA2: Scroll down to view Dependents Summary. | BQ2: Both (Error) | BY2: =AK7 | BZ2: =SpouseBirthDate | CA2: =SpouseBirthDate | CD2: =YourBirthDate | CO2: CTC - Qualifying child under 17 w/ SSN | CP2: Credit for Other Dependent - Qualifying child not under 17 | CQ2: Credit for Other Dependents - Qualifying Relative | CR2: Other Dependent | CX2: EIC - Qualifying child - Lived with you at least half in the U.S.
BV3: =OR(BV7:BV10,BV15:BV30) | BY3: =OR(BY7:BY10,BY15:BY30) | BZ3: Age | CA3: Age | CB3: Age | CM3: =OR(AND(NOT(BX7),BW7),AND(NOT(BX7),BB7<>"",CA7=0))
B4: Dependents | E4: See IRS instructions. | M4: (3) Social security number Enter 'N' if dependent has no SSN, ITIN or ATIN. (See IRS instructions.) | S4: (4) Relationship | Y4: (5) Check if child | AE4: (6) Check if child is: | AK4: Birthdate | AQ4: ="Age "&CHAR(10)&"(in "&TaxYear&")" | AR4: NOTE: To receive either the CTC or the credit for other dependents, all three must be checked. Check if child or other relative: | BA4: Child tax credit (CTC) | BD4: Check if qualifying relative: | BJ4: Credit for other dependents (CFOD) | BZ4: 17 | CA4: 19 | CB4: 24 | CH4: QC Depend or QR Depend
Y5: ="lived with you more than half "&TaxYear | BU5: Valid SSN? | BV5: Default SSN? | BZ5: Qualifying Child | CJ5: Qualifying Relative | CL5: Dependent
B6: If more than four dependents, see instructions and check | E6: (1) First name | I6: (2) Last name | Y6: Yes | AB6: And in the U.S. (Needed to qualify for EIC.) | AE6: Full-time student | AH6: Permanently and totally disabled | AR6: Was a US citizen, US national, US resident alien, or resident of Canada or Mexico | AU6: Didn't provide over half of their own support. | AX6: Was a US citizen, US national, or US resident alien | BA6: Auto calculated. To override, click left to clear, click right to check. | BD6: Has Gross Income < $5,200 | BG6: Had over half of support provided by you | BJ6: Auto calculated. To override, click left to clear, click right to check. | BW6: QC | BX6: File jointly & Spouse | BY6: Birthdate Missing | BZ6: ="Under "&BZ$4 | CA6: ="Under "&CA$4 | CB6: ="Under "&CB$4 | CC6: Full-time Student | CD6: Younger than You (and your spouse if filing jointly) | CE6: Totally Disabled | CF6: Didn't provide over half of their own support. | CG6: Lived with you more than half the year | CH6: A US citizen or national, or resident of Canada or Mexico | CI6: A US citizen, US national, or US resident alien | CJ6: Relative's gross income < $5,200 | CK6: You provided at least half of relative's support | CL6: Qualifying Child and Dependent | CM6: Qualifying Relative and Dependent | CU6: Lived with you more than half the year in the United States | CV6: Qualifying Child for EIC purposes
A7: 03 | M7: =IF(OR(E7<>"",I7<>"",S7<>"",AS7<>"",AV7<>"",Z7<>"",AC7<>"",AF7<>"",AI7<>"",AK7<>""),"001-01-00"&A7,"") | AQ7: =IF(AK7="","",TaxYear-YEAR(AK7)) | BB7: =IF(CO7=1,"X","") | BK7: =IF(OR(CP7=1,CQ7=1),"X","") | BN7: =IF(M7="","",IF(BQ7,"Error - two credit boxes checked.",IF(BX7,"Error - You can't claim spouse if filing jointly.",IF(BC7<>"","Override:CTC",IF(BL7<>"","Override CFOD",IF(AND(CC7,CP7=1),"CFOD for full-time student - at least "&$CA$4&" and under "&$CB$4&".",IF(AND(CE7,CP7=1),"CFOD for permanently & totally disabled child.",IF(OR(CP7=1,CQ7=1),"CFOD - Credit for other dependent.",IF(AND(CL7,BZ7),"CTC for dependent child under "&CTC_AgeLimit&".",IF(CL7,"Dependent child.",IF(CM7,"Dependent relative.",IF(CX7,"Qualified child for EIC.","Not qualified as a dependent.")))))))))))) | BQ7: =AND(BB7<>"",BK7<>"") | BS7: =TEXT(M7,"000-00-0000") | BT7: =LEFT(BS7,3) | BU7: =M7<>"n" | BV7: =LEFT(M7,6)="001-01" | BW7: =AND(M7<>"",BU7) | BX7: =AND(File_Marr_Joint<>"",OR(S7="spouse",S7="wife",S7="husband")) | BY7: =AND(AK7="",OR(Z7<>"",AC7<>"")) | BZ7: =AND(NOT(BY7),AQ7<BZ$4) | CA7: =AND(CD7,AQ7<CA$4) | CB7: =AND(AQ7<>"",AQ7<CB$4) | CC7: =AF7<>"" | CD7: =IF(AK7=0,TRUE,IF(OR(ISERROR(YourBirthDate),ISERROR(AK7)),TRUE,IF(AND(File_Marr_Joint<>"",ISERROR(SpouseBirthDate)),TRUE,IF(File_Marr_Joint<>"",AND(AK7>YourBirthDate,AK7>SpouseBirthDate),AK7>YourBirthDate)))) | CE7: =AI7<>"" | CF7: =AV7<>"" | CG7: =(Z7<>"") | CH7: =AS7<>"" | CI7: =AY7<>"" | CJ7: =BE7<>"" | CK7: =BH7<>"" | CL7: =IF(BA7<>"",FALSE,IF(BC7<>"",TRUE,AND(OR(AND(CA7,CD7),AND(CC7,NOT(CA7),CB7,CD7),CE7),CF7,CG7,CH7))) | CM7: =AND(NOT(BX7),NOT(CL7),CJ7,CK7,CH7) | CO7: =IF(BA7<>"",0,IF(BC7<>"",1,IF(AND(CL7,BU7,CI7,BZ7),1,0))) | CP7: =IF(AND(CL7,BU7,CI7,NOT(BZ7)),1,0) | CQ7: =IF(BJ7<>"",0,IF(BL7<>"",1,IF(AND(CM7,BU7,CI7),1,0))) | CR7: =IF(OR(CL7,CM7),MAX(0,1-SUM(CO7:CQ7)),0) | CU7: =AND(Z7<>"",AC7<>"") | CV7: =AND(OR(CA7,AND(CB7,CC7),CE7),CD7,CU7) | CX7: =IF(CV7,1,0)
A8: 04 | M8: =IF(OR(E8<>"",I8<>"",S8<>"",AS8<>"",AV8<>"",Z8<>"",AC8<>"",AF8<>"",AI8<>"",AK8<>""),"001-01-00"&A8,"") | AQ8: =IF(AK8="","",TaxYear-YEAR(AK8)) | BB8: =IF(CO8=1,"X","") | BK8: =IF(OR(CP8=1,CQ8=1),"X","") | BN8: =IF(M8="","",IF(BQ8,"Error - two credit boxes checked.",IF(BX8,"Error - You can't claim spouse if filing jointly.",IF(BC8<>"","Override:CTC",IF(BL8<>"","Override CFOD",IF(AND(CC8,CP8=1),"CFOD for full-time student - at least "&$CA$4&" and under "&$CB$4&".",IF(AND(CE8,CP8=1),"CFOD for permanently & totally disabled child.",IF(OR(CP8=1,CQ8=1),"CFOD - Credit for other dependent.",IF(AND(CL8,BZ8),"CTC for dependent child under "&CTC_AgeLimit&".",IF(CL8,"Dependent child.",IF(CM8,"Dependent relative.",IF(CX8,"Qualified child for EIC.","Not qualified as a dependent.")))))))))))) | BQ8: =AND(BB8<>"",BK8<>"") | BS8: =TEXT(M8,"000-00-0000") | BT8: =LEFT(BS8,3) | BU8: =M8<>"n" | BV8: =LEFT(M8,6)="001-01" | BW8: =AND(M8<>"",BU8) | BX8: =AND(File_Marr_Joint<>"",OR(S8="spouse",S8="wife",S8="husband")) | BY8: =AND(AK8="",OR(Z8<>"",AC8<>"")) | BZ8: =AND(NOT(BY8),AQ8<BZ$4) | CA8: =AND(CD8,AQ8<CA$4) | CB8: =AND(AQ8<>"",AQ8<CB$4) | CC8: =AF8<>"" | CD8: =IF(AK8=0,TRUE,IF(OR(ISERROR(YourBirthDate),ISERROR(AK8)),TRUE,IF(AND(File_Marr_Joint<>"",ISERROR(SpouseBirthDate)),TRUE,IF(File_Marr_Joint<>"",AND(AK8>YourBirthDate,AK8>SpouseBirthDate),AK8>YourBirthDate)))) | CE8: =AI8<>"" | CF8: =AV8<>"" | CG8: =(Z8<>"") | CH8: =AS8<>"" | CI8: =AY8<>"" | CJ8: =BE8<>"" | CK8: =BH8<>"" | CL8: =AND(OR(AND(CA8,CD8),AND(CC8,NOT(CA8),CB8,CD8),CE8),CF8,CG8,CH8) | CM8: =AND(NOT(BX8),NOT(CL8),CJ8,CK8,CH8) | CO8: =IF(BA8<>"",0,IF(BC8<>"",1,IF(AND(CL8,BU8,CI8,BZ8),1,0))) | CP8: =IF(AND(CL8,BU8,CI8,NOT(BZ8)),1,0) | CQ8: =IF(BJ8<>"",0,IF(BL8<>"",1,IF(AND(CM8,BU8,CI8),1,0))) | CR8: =IF(OR(CL8,CM8),MAX(0,1-SUM(CO8:CQ8)),0) | CU8: =AND(Z8<>"",AC8<>"") | CV8: =AND(OR(CA8,AND(CB8,CC8),CE8),CD8,CU8) | CX8: =IF(CV8,1,0)
A9: 05 | M9: =IF(OR(E9<>"",I9<>"",S9<>"",AS9<>"",AV9<>"",Z9<>"",AC9<>"",AF9<>"",AI9<>"",AK9<>""),"001-01-00"&A9,"") | AQ9: =IF(AK9="","",TaxYear-YEAR(AK9)) | BB9: =IF(CO9=1,"X","") | BK9: =IF(OR(CP9=1,CQ9=1),"X","") | BN9: =IF(M9="","",IF(BQ9,"Error - two credit boxes checked.",IF(BX9,"Error - You can't claim spouse if filing jointly.",IF(BC9<>"","Override:CTC",IF(BL9<>"","Override CFOD",IF(AND(CC9,CP9=1),"CFOD for full-time student - at least "&$CA$4&" and under "&$CB$4&".",IF(AND(CE9,CP9=1),"CFOD for permanently & totally disabled child.",IF(OR(CP9=1,CQ9=1),"CFOD - Credit for other dependent.",IF(AND(CL9,BZ9),"CTC for dependent child under "&CTC_AgeLimit&".",IF(CL9,"Dependent child.",IF(CM9,"Dependent relative.",IF(CX9,"Qualified child for EIC.","Not qualified as a dependent.")))))))))))) | BQ9: =AND(BB9<>"",BK9<>"") | BS9: =TEXT(M9,"000-00-0000") | BT9: =LEFT(BS9,3) | BU9: =M9<>"n" | BV9: =LEFT(M9,6)="001-01" | BW9: =AND(M9<>"",BU9) | BX9: =AND(File_Marr_Joint<>"",OR(S9="spouse",S9="wife",S9="husband")) | BY9: =AND(AK9="",OR(Z9<>"",AC9<>"")) | BZ9: =AND(NOT(BY9),AQ9<BZ$4) | CA9: =AND(CD9,AQ9<CA$4) | CB9: =AND(AQ9<>"",AQ9<CB$4) | CC9: =AF9<>"" | CD9: =IF(AK9=0,TRUE,IF(OR(ISERROR(YourBirthDate),ISERROR(AK9)),TRUE,IF(AND(File_Marr_Joint<>"",ISERROR(SpouseBirthDate)),TRUE,IF(File_Marr_Joint<>"",AND(AK9>YourBirthDate,AK9>SpouseBirthDate),AK9>YourBirthDate)))) | CE9: =AI9<>"" | CF9: =AV9<>"" | CG9: =(Z9<>"") | CH9: =AS9<>"" | CI9: =AY9<>"" | CJ9: =BE9<>"" | CK9: =BH9<>"" | CL9: =AND(OR(AND(CA9,CD9),AND(CC9,NOT(CA9),CB9,CD9),CE9),CF9,CG9,CH9) | CM9: =AND(NOT(BX9),NOT(CL9),CJ9,CK9,CH9) | CO9: =IF(BA9<>"",0,IF(BC9<>"",1,IF(AND(CL9,BU9,CI9,BZ9),1,0))) | CP9: =IF(AND(CL9,BU9,CI9,NOT(BZ9)),1,0) | CQ9: =IF(BJ9<>"",0,IF(BL9<>"",1,IF(AND(CM9,BU9,CI9),1,0))) | CR9: =IF(OR(CL9,CM9),MAX(0,1-SUM(CO9:CQ9)),0) | CU9: =AND(Z9<>"",AC9<>"") | CV9: =AND(OR(CA9,AND(CB9,CC9),CE9),CD9,CU9) | CX9: =IF(CV9,1,0)
A10: 06 | B10: here | D10: =IF(DependentsGT4,"X","") | M10: =IF(OR(E10<>"",I10<>"",S10<>"",AS10<>"",AV10<>"",Z10<>"",AC10<>"",AF10<>"",AI10<>"",AK10<>""),"001-01-00"&A10,"") | AQ10: =IF(AK10="","",TaxYear-YEAR(AK10)) | BB10: =IF(CO10=1,"X","") | BK10: =IF(OR(CP10=1,CQ10=1),"X","") | BN10: =IF(M10="","",IF(BQ10,"Error - two credit boxes checked.",IF(BX10,"Error - You can't claim spouse if filing jointly.",IF(BC10<>"","Override:CTC",IF(BL10<>"","Override CFOD",IF(AND(CC10,CP10=1),"CFOD for full-time student - at least "&$CA$4&" and under "&$CB$4&".",IF(AND(CE10,CP10=1),"CFOD for permanently & totally disabled child.",IF(OR(CP10=1,CQ10=1),"CFOD - Credit for other dependent.",IF(AND(CL10,BZ10),"CTC for dependent child under "&CTC_AgeLimit&".",IF(CL10,"Dependent child.",IF(CM10,"Dependent relative.",IF(CX10,"Qualified child for EIC.","Not qualified as a dependent.")))))))))))) | BQ10: =AND(BB10<>"",BK10<>"") | BS10: =TEXT(M10,"000-00-0000") | BT10: =LEFT(BS10,3) | BU10: =M10<>"n" | BV10: =LEFT(M10,6)="001-01" | BW10: =AND(M10<>"",BU10) | BX10: =AND(File_Marr_Joint<>"",OR(S10="spouse",S10="wife",S10="husband")) | BY10: =AND(AK10="",OR(Z10<>"",AC10<>"")) | BZ10: =AND(NOT(BY10),AQ10<BZ$4) | CA10: =AND(CD10,AQ10<CA$4) | CB10: =AND(AQ10<>"",AQ10<CB$4) | CC10: =AF10<>"" | CD10: =IF(AK10=0,TRUE,IF(OR(ISERROR(YourBirthDate),ISERROR(AK10)),TRUE,IF(AND(File_Marr_Joint<>"",ISERROR(SpouseBirthDate)),TRUE,IF(File_Marr_Joint<>"",AND(AK10>YourBirthDate,AK10>SpouseBirthDate),AK10>YourBirthDate)))) | CE10: =AI10<>"" | CF10: =AV10<>"" | CG10: =(Z10<>"") | CH10: =AS10<>"" | CI10: =AY10<>"" | CJ10: =BE10<>"" | CK10: =BH10<>"" | CL10: =AND(OR(AND(CA10,CD10),AND(CC10,NOT(CA10),CB10,CD10),CE10),CF10,CG10,CH10) | CM10: =AND(NOT(BX10),NOT(CL10),CJ10,CK10,CH10) | CO10: =IF(BA10<>"",0,IF(BC10<>"",1,IF(AND(CL10,BU10,CI10,BZ10),1,0))) | CP10: =IF(AND(CL10,BU10,CI10,NOT(BZ10)),1,0) | CQ10: =IF(BJ10<>"",0,IF(BL10<>"",1,IF(AND(CM10,BU10,CI10),1,0))) | CR10: =IF(OR(CL10,CM10),MAX(0,1-SUM(CO10:CQ10)),0) | CU10: =AND(Z10<>"",AC10<>"") | CV10: =AND(OR(CA10,AND(CB10,CC10),CE10),CD10,CU10) | CX10: =IF(CV10,1,0)
CO11: =SUM(CO7:CO10) | CP11: =SUM(CP7:CP10) | CQ11: =SUM(CQ7:CQ10) | CR11: =SUM(CR7:CR10) | CX11: =SUM(CX7:CX10)
B12: More Dependents | E12: See IRS instructions. | M12: (3) Social security number Enter 'N' if no SSN. | S12: (4) Relationship | Y12: ="(5) Check if lived with you more than half "&TaxYear | AE12: (6) Check if | AK12: Birthdate | AQ12: ="Age "&CHAR(10)&"(in "&TaxYear&")" | AR12: Check if child or other relative: | BA12: Child tax credit (CTC) | BD12: Check if qualifying relative: | BJ12: Credit for other dependents (CFOD)
E14: (1) First name | I14: (2) Last name | Y14: Yes | AB14: And in the U.S. (Needed to qualify for EIC.) | AE14: Full-time student | AH14: Permanently and totally disabled | AR14: Was a US citizen, US national, or resident of Canada or Mexico | AU14: Didn't provide over half of their own support. | AX14: Was a US citizen, US national, or US resident alien | BA14: Auto calculated. To override, click left to clear, click right to check | BD14: Has Gross Income < $5,200 | BG14: Had over half of support provided by you | BJ14: Auto calculated. To override, click left to clear, click right to check
A15: 07 | M15: =IF(OR(E15<>"",I15<>"",S15<>"",AS15<>"",AV15<>"",Z15<>"",AC15<>"",AF15<>"",AI15<>"",AK15<>""),"001-01-00"&A15,"") | AQ15: =IF(AK15="","",TaxYear-YEAR(AK15)) | BB15: =IF(CO15=1,"X","") | BK15: =IF(OR(CP15=1,CQ15=1),"X","") | BN15: =IF(M15="","",IF(BQ15,"Error - two credit boxes checked.",IF(BX15,"Error - You can't claim spouse if filing jointly.",IF(BC15<>"","Override:CTC",IF(BL15<>"","Override CFOD",IF(AND(CC15,CP15=1),"CFOD for full-time student - at least "&$CA$4&" and under "&$CB$4&".",IF(AND(CE15,CP15=1),"CFOD for permanently & totally disabled child.",IF(OR(CP15=1,CQ15=1),"CFOD - Credit for other dependent.",IF(AND(CL15,BZ15),"CTC for dependent child under "&CTC_AgeLimit&".",IF(CL15,"Dependent child.",IF(CM15,"Dependent relative.",IF(CX15,"Qualified child for EIC.","Not qualified as a dependent.")))))))))))) | BQ15: =AND(BB15<>"",BK15<>"") | BS15: =TEXT(M15,"000-00-0000") | BT15: =LEFT(BS15,3) | BU15: =M15<>"n" | BV15: =LEFT(M15,6)="001-01" | BW15: =AND(M15<>"",BU15) | BX15: =AND(File_Marr_Joint<>"",OR(S15="spouse",S15="wife",S15="husband")) | BY15: =AND(AK15="",OR(Z15<>"",AC15<>"")) | BZ15: =AND(NOT(BY15),AQ15<BZ$4) | CA15: =AND(CD15,AQ15<CA$4) | CB15: =AND(AQ15<>"",AQ15<CB$4) | CC15: =AF15<>"" | CD15: =IF(AK15=0,TRUE,IF(OR(ISERROR(YourBirthDate),ISERROR(AK15)),TRUE,IF(AND(File_Marr_Joint<>"",ISERROR(SpouseBirthDate)),TRUE,IF(File_Marr_Joint<>"",AND(AK15>YourBirthDate,AK15>SpouseBirthDate),AK15>YourBirthDate)))) | CE15: =AI15<>"" | CF15: =AV15<>"" | CG15: =(Z15<>"") | CH15: =AS15<>"" | CI15: =AY15<>"" | CJ15: =BE15<>"" | CK15: =BH15<>"" | CL15: =AND(OR(AND(CA15,CD15),AND(CC15,NOT(CA15),CB15,CD15),CE15),CF15,CG15,CH15) | CM15: =AND(NOT(BX15),NOT(CL15),CJ15,CK15,CH15) | CO15: =IF(BA15<>"",0,IF(BC15<>"",1,IF(AND(CL15,BU15,CI15,BZ15),1,0))) | CP15: =IF(AND(CL15,BU15,CI15,NOT(BZ15)),1,0) | CQ15: =IF(BJ15<>"",0,IF(BL15<>"",1,IF(AND(CM15,BU15,CI15),1,0))) | CR15: =IF(OR(CL15,CM15),MAX(0,1-SUM(CO15:CQ15)),0) | CU15: =AND(Z15<>"",AC15<>"") | CV15: =AND(OR(CA15,AND(CB15,CC15),CE15),CD15,CU15) | CX15: =IF(CV15,1,0)
A16: 08 | M16: =IF(OR(E16<>"",I16<>"",S16<>"",AS16<>"",AV16<>"",Z16<>"",AC16<>"",AF16<>"",AI16<>"",AK16<>""),"001-01-00"&A16,"") | AQ16: =IF(AK16="","",TaxYear-YEAR(AK16)) | BB16: =IF(CO16=1,"X","") | BK16: =IF(OR(CP16=1,CQ16=1),"X","") | BN16: =IF(M16="","",IF(BQ16,"Error - two credit boxes checked.",IF(BX16,"Error - You can't claim spouse if filing jointly.",IF(BC16<>"","Override:CTC",IF(BL16<>"","Override CFOD",IF(AND(CC16,CP16=1),"CFOD for full-time student - at least "&$CA$4&" and under "&$CB$4&".",IF(AND(CE16,CP16=1),"CFOD for permanently & totally disabled child.",IF(OR(CP16=1,CQ16=1),"CFOD - Credit for other dependent.",IF(AND(CL16,BZ16),"CTC for dependent child under "&CTC_AgeLimit&".",IF(CL16,"Dependent child.",IF(CM16,"Dependent relative.",IF(CX16,"Qualified child for EIC.","Not qualified as a dependent.")))))))))))) | BQ16: =AND(BB16<>"",BK16<>"") | BS16: =TEXT(M16,"000-00-0000") | BT16: =LEFT(BS16,3) | BU16: =M16<>"n" | BV16: =LEFT(M16,6)="001-01" | BW16: =AND(M16<>"",BU16) | BX16: =AND(File_Marr_Joint<>"",OR(S16="spouse",S16="wife",S16="husband")) | BY16: =AND(AK16="",OR(Z16<>"",AC16<>"")) | BZ16: =AND(NOT(BY16),AQ16<BZ$4) | CA16: =AND(CD16,AQ16<CA$4) | CB16: =AND(AQ16<>"",AQ16<CB$4) | CC16: =AF16<>"" | CD16: =IF(AK16=0,TRUE,IF(OR(ISERROR(YourBirthDate),ISERROR(AK16)),TRUE,IF(AND(File_Marr_Joint<>"",ISERROR(SpouseBirthDate)),TRUE,IF(File_Marr_Joint<>"",AND(AK16>YourBirthDate,AK16>SpouseBirthDate),AK16>YourBirthDate)))) | CE16: =AI16<>"" | CF16: =AV16<>"" | CG16: =(Z16<>"") | CH16: =AS16<>"" | CI16: =AY16<>"" | CJ16: =BE16<>"" | CK16: =BH16<>"" | CL16: =AND(OR(AND(CA16,CD16),AND(CC16,NOT(CA16),CB16,CD16),CE16),CF16,CG16,CH16) | CM16: =AND(NOT(BX16),NOT(CL16),CJ16,CK16,CH16) | CO16: =IF(BA16<>"",0,IF(BC16<>"",1,IF(AND(CL16,BU16,CI16,BZ16),1,0))) | CP16: =IF(AND(CL16,BU16,CI16,NOT(BZ16)),1,0) | CQ16: =IF(BJ16<>"",0,IF(BL16<>"",1,IF(AND(CM16,BU16,CI16),1,0))) | CR16: =IF(OR(CL16,CM16),MAX(0,1-SUM(CO16:CQ16)),0) | CU16: =AND(Z16<>"",AC16<>"") | CV16: =AND(OR(CA16,AND(CB16,CC16),CE16),CD16,CU16) | CX16: =IF(CV16,1,0)
A17: 09 | M17: =IF(OR(E17<>"",I17<>"",S17<>"",AS17<>"",AV17<>"",Z17<>"",AC17<>"",AF17<>"",AI17<>"",AK17<>""),"001-01-00"&A17,"") | AQ17: =IF(AK17="","",TaxYear-YEAR(AK17)) | BB17: =IF(CO17=1,"X","") | BK17: =IF(OR(CP17=1,CQ17=1),"X","") | BN17: =IF(M17="","",IF(BQ17,"Error - two credit boxes checked.",IF(BX17,"Error - You can't claim spouse if filing jointly.",IF(BC17<>"","Override:CTC",IF(BL17<>"","Override CFOD",IF(AND(CC17,CP17=1),"CFOD for full-time student - at least "&$CA$4&" and under "&$CB$4&".",IF(AND(CE17,CP17=1),"CFOD for permanently & totally disabled child.",IF(OR(CP17=1,CQ17=1),"CFOD - Credit for other dependent.",IF(AND(CL17,BZ17),"CTC for dependent child under "&CTC_AgeLimit&".",IF(CL17,"Dependent child.",IF(CM17,"Dependent relative.",IF(CX17,"Qualified child for EIC.","Not qualified as a dependent.")))))))))))) | BQ17: =AND(BB17<>"",BK17<>"") | BS17: =TEXT(M17,"000-00-0000") | BT17: =LEFT(BS17,3) | BU17: =M17<>"n" | BV17: =LEFT(M17,6)="001-01" | BW17: =AND(M17<>"",BU17) | BX17: =AND(File_Marr_Joint<>"",OR(S17="spouse",S17="wife",S17="husband")) | BY17: =AND(AK17="",OR(Z17<>"",AC17<>"")) | BZ17: =AND(NOT(BY17),AQ17<BZ$4) | CA17: =AND(CD17,AQ17<CA$4) | CB17: =AND(AQ17<>"",AQ17<CB$4) | CC17: =AF17<>"" | CD17: =IF(AK17=0,TRUE,IF(OR(ISERROR(YourBirthDate),ISERROR(AK17)),TRUE,IF(AND(File_Marr_Joint<>"",ISERROR(SpouseBirthDate)),TRUE,IF(File_Marr_Joint<>"",AND(AK17>YourBirthDate,AK17>SpouseBirthDate),AK17>YourBirthDate)))) | CE17: =AI17<>"" | CF17: =AV17<>"" | CG17: =(Z17<>"") | CH17: =AS17<>"" | CI17: =AY17<>"" | CJ17: =BE17<>"" | CK17: =BH17<>"" | CL17: =AND(OR(AND(CA17,CD17),AND(CC17,NOT(CA17),CB17,CD17),CE17),CF17,CG17,CH17) | CM17: =AND(NOT(BX17),NOT(CL17),CJ17,CK17,CH17) | CO17: =IF(BA17<>"",0,IF(BC17<>"",1,IF(AND(CL17,BU17,CI17,BZ17),1,0))) | CP17: =IF(AND(CL17,BU17,CI17,NOT(BZ17)),1,0) | CQ17: =IF(BJ17<>"",0,IF(BL17<>"",1,IF(AND(CM17,BU17,CI17),1,0))) | CR17: =IF(OR(CL17,CM17),MAX(0,1-SUM(CO17:CQ17)),0) | CU17: =AND(Z17<>"",AC17<>"") | CV17: =AND(OR(CA17,AND(CB17,CC17),CE17),CD17,CU17) | CX17: =IF(CV17,1,0)
A18: 10 | M18: =IF(OR(E18<>"",I18<>"",S18<>"",AS18<>"",AV18<>"",Z18<>"",AC18<>"",AF18<>"",AI18<>"",AK18<>""),"001-01-00"&A18,"") | AQ18: =IF(AK18="","",TaxYear-YEAR(AK18)) | BB18: =IF(CO18=1,"X","") | BK18: =IF(OR(CP18=1,CQ18=1),"X","") | BN18: =IF(M18="","",IF(BQ18,"Error - two credit boxes checked.",IF(BX18,"Error - You can't claim spouse if filing jointly.",IF(BC18<>"","Override:CTC",IF(BL18<>"","Override CFOD",IF(AND(CC18,CP18=1),"CFOD for full-time student - at least "&$CA$4&" and under "&$CB$4&".",IF(AND(CE18,CP18=1),"CFOD for permanently & totally disabled child.",IF(OR(CP18=1,CQ18=1),"CFOD - Credit for other dependent.",IF(AND(CL18,BZ18),"CTC for dependent child under "&CTC_AgeLimit&".",IF(CL18,"Dependent child.",IF(CM18,"Dependent relative.",IF(CX18,"Qualified child for EIC.","Not qualified as a dependent.")))))))))))) | BQ18: =AND(BB18<>"",BK18<>"") | BS18: =TEXT(M18,"000-00-0000") | BT18: =LEFT(BS18,3) | BU18: =M18<>"n" | BV18: =LEFT(M18,6)="001-01" | BW18: =AND(M18<>"",BU18) | BX18: =AND(File_Marr_Joint<>"",OR(S18="spouse",S18="wife",S18="husband")) | BY18: =AND(AK18="",OR(Z18<>"",AC18<>"")) | BZ18: =AND(NOT(BY18),AQ18<BZ$4) | CA18: =AND(CD18,AQ18<CA$4) | CB18: =AND(AQ18<>"",AQ18<CB$4) | CC18: =AF18<>"" | CD18: =IF(AK18=0,TRUE,IF(OR(ISERROR(YourBirthDate),ISERROR(AK18)),TRUE,IF(AND(File_Marr_Joint<>"",ISERROR(SpouseBirthDate)),TRUE,IF(File_Marr_Joint<>"",AND(AK18>YourBirthDate,AK18>SpouseBirthDate),AK18>YourBirthDate)))) | CE18: =AI18<>"" | CF18: =AV18<>"" | CG18: =(Z18<>"") | CH18: =AS18<>"" | CI18: =AY18<>"" | CJ18: =BE18<>"" | CK18: =BH18<>"" | CL18: =AND(OR(AND(CA18,CD18),AND(CC18,NOT(CA18),CB18,CD18),CE18),CF18,CG18,CH18) | CM18: =AND(NOT(BX18),NOT(CL18),CJ18,CK18,CH18) | CO18: =IF(BA18<>"",0,IF(BC18<>"",1,IF(AND(CL18,BU18,CI18,BZ18),1,0))) | CP18: =IF(AND(CL18,BU18,CI18,NOT(BZ18)),1,0) | CQ18: =IF(BJ18<>"",0,IF(BL18<>"",1,IF(AND(CM18,BU18,CI18),1,0))) | CR18: =IF(OR(CL18,CM18),MAX(0,1-SUM(CO18:CQ18)),0) | CU18: =AND(Z18<>"",AC18<>"") | CV18: =AND(OR(CA18,AND(CB18,CC18),CE18),CD18,CU18) | CX18: =IF(CV18,1,0)
A19: 11 | M19: =IF(OR(E19<>"",I19<>"",S19<>"",AS19<>"",AV19<>"",Z19<>"",AC19<>"",AF19<>"",AI19<>"",AK19<>""),"001-01-00"&A19,"") | AQ19: =IF(AK19="","",TaxYear-YEAR(AK19)) | BB19: =IF(CO19=1,"X","") | BK19: =IF(OR(CP19=1,CQ19=1),"X","") | BN19: =IF(M19="","",IF(BQ19,"Error - two credit boxes checked.",IF(BX19,"Error - You can't claim spouse if filing jointly.",IF(BC19<>"","Override:CTC",IF(BL19<>"","Override CFOD",IF(AND(CC19,CP19=1),"CFOD for full-time student - at least "&$CA$4&" and under "&$CB$4&".",IF(AND(CE19,CP19=1),"CFOD for permanently & totally disabled child.",IF(OR(CP19=1,CQ19=1),"CFOD - Credit for other dependent.",IF(AND(CL19,BZ19),"CTC for dependent child under "&CTC_AgeLimit&".",IF(CL19,"Dependent child.",IF(CM19,"Dependent relative.",IF(CX19,"Qualified child for EIC.","Not qualified as a dependent.")))))))))))) | BQ19: =AND(BB19<>"",BK19<>"") | BS19: =TEXT(M19,"000-00-0000") | BT19: =LEFT(BS19,3) | BU19: =M19<>"n" | BV19: =LEFT(M19,6)="001-01" | BW19: =AND(M19<>"",BU19) | BX19: =AND(File_Marr_Joint<>"",OR(S19="spouse",S19="wife",S19="husband")) | BY19: =AND(AK19="",OR(Z19<>"",AC19<>"")) | BZ19: =AND(NOT(BY19),AQ19<BZ$4) | CA19: =AND(CD19,AQ19<CA$4) | CB19: =AND(AQ19<>"",AQ19<CB$4) | CC19: =AF19<>"" | CD19: =IF(AK19=0,TRUE,IF(OR(ISERROR(YourBirthDate),ISERROR(AK19)),TRUE,IF(AND(File_Marr_Joint<>"",ISERROR(SpouseBirthDate)),TRUE,IF(File_Marr_Joint<>"",AND(AK19>YourBirthDate,AK19>SpouseBirthDate),AK19>YourBirthDate)))) | CE19: =AI19<>"" | CF19: =AV19<>"" | CG19: =(Z19<>"") | CH19: =AS19<>"" | CI19: =AY19<>"" | CJ19: =BE19<>"" | CK19: =BH19<>"" | CL19: =AND(OR(AND(CA19,CD19),AND(CC19,NOT(CA19),CB19,CD19),CE19),CF19,CG19,CH19) | CM19: =AND(NOT(BX19),NOT(CL19),CJ19,CK19,CH19) | CO19: =IF(BA19<>"",0,IF(BC19<>"",1,IF(AND(CL19,BU19,CI19,BZ19),1,0))) | CP19: =IF(AND(CL19,BU19,CI19,NOT(BZ19)),1,0) | CQ19: =IF(BJ19<>"",0,IF(BL19<>"",1,IF(AND(CM19,BU19,CI19),1,0))) | CR19: =IF(OR(CL19,CM19),MAX(0,1-SUM(CO19:CQ19)),0) | CU19: =AND(Z19<>"",AC19<>"") | CV19: =AND(OR(CA19,AND(CB19,CC19),CE19),CD19,CU19) | CX19: =IF(CV19,1,0)
A20: 12 | M20: =IF(OR(E20<>"",I20<>"",S20<>"",AS20<>"",AV20<>"",Z20<>"",AC20<>"",AF20<>"",AI20<>"",AK20<>""),"001-01-00"&A20,"") | AQ20: =IF(AK20="","",TaxYear-YEAR(AK20)) | BB20: =IF(CO20=1,"X","") | BK20: =IF(OR(CP20=1,CQ20=1),"X","") | BN20: =IF(M20="","",IF(BQ20,"Error - two credit boxes checked.",IF(BX20,"Error - You can't claim spouse if filing jointly.",IF(BC20<>"","Override:CTC",IF(BL20<>"","Override CFOD",IF(AND(CC20,CP20=1),"CFOD for full-time student - at least "&$CA$4&" and under "&$CB$4&".",IF(AND(CE20,CP20=1),"CFOD for permanently & totally disabled child.",IF(OR(CP20=1,CQ20=1),"CFOD - Credit for other dependent.",IF(AND(CL20,BZ20),"CTC for dependent child under "&CTC_AgeLimit&".",IF(CL20,"Dependent child.",IF(CM20,"Dependent relative.",IF(CX20,"Qualified child for EIC.","Not qualified as a dependent.")))))))))))) | BQ20: =AND(BB20<>"",BK20<>"") | BS20: =TEXT(M20,"000-00-0000") | BT20: =LEFT(BS20,3) | BU20: =M20<>"n" | BV20: =LEFT(M20,6)="001-01" | BW20: =AND(M20<>"",BU20) | BX20: =AND(File_Marr_Joint<>"",OR(S20="spouse",S20="wife",S20="husband")) | BY20: =AND(AK20="",OR(Z20<>"",AC20<>"")) | BZ20: =AND(NOT(BY20),AQ20<BZ$4) | CA20: =AND(CD20,AQ20<CA$4) | CB20: =AND(AQ20<>"",AQ20<CB$4) | CC20: =AF20<>"" | CD20: =IF(AK20=0,TRUE,IF(OR(ISERROR(YourBirthDate),ISERROR(AK20)),TRUE,IF(AND(File_Marr_Joint<>"",ISERROR(SpouseBirthDate)),TRUE,IF(File_Marr_Joint<>"",AND(AK20>YourBirthDate,AK20>SpouseBirthDate),AK20>YourBirthDate)))) | CE20: =AI20<>"" | CF20: =AV20<>"" | CG20: =(Z20<>"") | CH20: =AS20<>"" | CI20: =AY20<>"" | CJ20: =BE20<>"" | CK20: =BH20<>"" | CL20: =AND(OR(AND(CA20,CD20),AND(CC20,NOT(CA20),CB20,CD20),CE20),CF20,CG20,CH20) | CM20: =AND(NOT(BX20),NOT(CL20),CJ20,CK20,CH20) | CO20: =IF(BA20<>"",0,IF(BC20<>"",1,IF(AND(CL20,BU20,CI20,BZ20),1,0))) | CP20: =IF(AND(CL20,BU20,CI20,NOT(BZ20)),1,0) | CQ20: =IF(BJ20<>"",0,IF(BL20<>"",1,IF(AND(CM20,BU20,CI20),1,0))) | CR20: =IF(OR(CL20,CM20),MAX(0,1-SUM(CO20:CQ20)),0) | CU20: =AND(Z20<>"",AC20<>"") | CV20: =AND(OR(CA20,AND(CB20,CC20),CE20),CD20,CU20) | CX20: =IF(CV20,1,0)
A21: 13 | M21: =IF(OR(E21<>"",I21<>"",S21<>"",AS21<>"",AV21<>"",Z21<>"",AC21<>"",AF21<>"",AI21<>"",AK21<>""),"001-01-00"&A21,"") | AQ21: =IF(AK21="","",TaxYear-YEAR(AK21)) | BB21: =IF(CO21=1,"X","") | BK21: =IF(OR(CP21=1,CQ21=1),"X","") | BN21: =IF(M21="","",IF(BQ21,"Error - two credit boxes checked.",IF(BX21,"Error - You can't claim spouse if filing jointly.",IF(BC21<>"","Override:CTC",IF(BL21<>"","Override CFOD",IF(AND(CC21,CP21=1),"CFOD for full-time student - at least "&$CA$4&" and under "&$CB$4&".",IF(AND(CE21,CP21=1),"CFOD for permanently & totally disabled child.",IF(OR(CP21=1,CQ21=1),"CFOD - Credit for other dependent.",IF(AND(CL21,BZ21),"CTC for dependent child under "&CTC_AgeLimit&".",IF(CL21,"Dependent child.",IF(CM21,"Dependent relative.",IF(CX21,"Qualified child for EIC.","Not qualified as a dependent.")))))))))))) | BQ21: =AND(BB21<>"",BK21<>"") | BS21: =TEXT(M21,"000-00-0000") | BT21: =LEFT(BS21,3) | BU21: =M21<>"n" | BV21: =LEFT(M21,6)="001-01" | BW21: =AND(M21<>"",BU21) | BX21: =AND(File_Marr_Joint<>"",OR(S21="spouse",S21="wife",S21="husband")) | BY21: =AND(AK21="",OR(Z21<>"",AC21<>"")) | BZ21: =AND(NOT(BY21),AQ21<BZ$4) | CA21: =AND(CD21,AQ21<CA$4) | CB21: =AND(AQ21<>"",AQ21<CB$4) | CC21: =AF21<>"" | CD21: =IF(AK21=0,TRUE,IF(OR(ISERROR(YourBirthDate),ISERROR(AK21)),TRUE,IF(AND(File_Marr_Joint<>"",ISERROR(SpouseBirthDate)),TRUE,IF(File_Marr_Joint<>"",AND(AK21>YourBirthDate,AK21>SpouseBirthDate),AK21>YourBirthDate)))) | CE21: =AI21<>"" | CF21: =AV21<>"" | CG21: =(Z21<>"") | CH21: =AS21<>"" | CI21: =AY21<>"" | CJ21: =BE21<>"" | CK21: =BH21<>"" | CL21: =AND(OR(AND(CA21,CD21),AND(CC21,NOT(CA21),CB21,CD21),CE21),CF21,CG21,CH21) | CM21: =AND(NOT(BX21),NOT(CL21),CJ21,CK21,CH21) | CO21: =IF(BA21<>"",0,IF(BC21<>"",1,IF(AND(CL21,BU21,CI21,BZ21),1,0))) | CP21: =IF(AND(CL21,BU21,CI21,NOT(BZ21)),1,0) | CQ21: =IF(BJ21<>"",0,IF(BL21<>"",1,IF(AND(CM21,BU21,CI21),1,0))) | CR21: =IF(OR(CL21,CM21),MAX(0,1-SUM(CO21:CQ21)),0) | CU21: =AND(Z21<>"",AC21<>"") | CV21: =AND(OR(CA21,AND(CB21,CC21),CE21),CD21,CU21) | CX21: =IF(CV21,1,0)
A22: 14 | M22: =IF(OR(E22<>"",I22<>"",S22<>"",AS22<>"",AV22<>"",Z22<>"",AC22<>"",AF22<>"",AI22<>"",AK22<>""),"001-01-00"&A22,"") | AQ22: =IF(AK22="","",TaxYear-YEAR(AK22)) | BB22: =IF(CO22=1,"X","") | BK22: =IF(OR(CP22=1,CQ22=1),"X","") | BN22: =IF(M22="","",IF(BQ22,"Error - two credit boxes checked.",IF(BX22,"Error - You can't claim spouse if filing jointly.",IF(BC22<>"","Override:CTC",IF(BL22<>"","Override CFOD",IF(AND(CC22,CP22=1),"CFOD for full-time student - at least "&$CA$4&" and under "&$CB$4&".",IF(AND(CE22,CP22=1),"CFOD for permanently & totally disabled child.",IF(OR(CP22=1,CQ22=1),"CFOD - Credit for other dependent.",IF(AND(CL22,BZ22),"CTC for dependent child under "&CTC_AgeLimit&".",IF(CL22,"Dependent child.",IF(CM22,"Dependent relative.",IF(CX22,"Qualified child for EIC.","Not qualified as a dependent.")))))))))))) | BQ22: =AND(BB22<>"",BK22<>"") | BS22: =TEXT(M22,"000-00-0000") | BT22: =LEFT(BS22,3) | BU22: =M22<>"n" | BV22: =LEFT(M22,6)="001-01" | BW22: =AND(M22<>"",BU22) | BX22: =AND(File_Marr_Joint<>"",OR(S22="spouse",S22="wife",S22="husband")) | BY22: =AND(AK22="",OR(Z22<>"",AC22<>"")) | BZ22: =AND(NOT(BY22),AQ22<BZ$4) | CA22: =AND(CD22,AQ22<CA$4) | CB22: =AND(AQ22<>"",AQ22<CB$4) | CC22: =AF22<>"" | CD22: =IF(AK22=0,TRUE,IF(OR(ISERROR(YourBirthDate),ISERROR(AK22)),TRUE,IF(AND(File_Marr_Joint<>"",ISERROR(SpouseBirthDate)),TRUE,IF(File_Marr_Joint<>"",AND(AK22>YourBirthDate,AK22>SpouseBirthDate),AK22>YourBirthDate)))) | CE22: =AI22<>"" | CF22: =AV22<>"" | CG22: =(Z22<>"") | CH22: =AS22<>"" | CI22: =AY22<>"" | CJ22: =BE22<>"" | CK22: =BH22<>"" | CL22: =AND(OR(AND(CA22,CD22),AND(CC22,NOT(CA22),CB22,CD22),CE22),CF22,CG22,CH22) | CM22: =AND(NOT(BX22),NOT(CL22),CJ22,CK22,CH22) | CO22: =IF(BA22<>"",0,IF(BC22<>"",1,IF(AND(CL22,BU22,CI22,BZ22),1,0))) | CP22: =IF(AND(CL22,BU22,CI22,NOT(BZ22)),1,0) | CQ22: =IF(BJ22<>"",0,IF(BL22<>"",1,IF(AND(CM22,BU22,CI22),1,0))) | CR22: =IF(OR(CL22,CM22),MAX(0,1-SUM(CO22:CQ22)),0) | CU22: =AND(Z22<>"",AC22<>"") | CV22: =AND(OR(CA22,AND(CB22,CC22),CE22),CD22,CU22) | CX22: =IF(CV22,1,0)
